Workbook

Sheet PAYABLES-2024
A2: PAYABLES-2026
A3: S# | B3: NAME | C3: AMOUNT
A4: 1 | B4: AL AZIZ LHR | C4: ='AL AZIZ-LHR-19'!G36 -> 64350
A5: 2 | B5: WAQAS FTC | C5: =39400+28700-18100-20000+27200+14100-26300-20000+4950+7750+32500-50000+60800-20000+5500-20000-26500+42600-22600+44350+17100-25000+16900-33350-20000+20750+18000+9250-28000-20000 -> 40000
A6: 4 | B6: KARACHI COMPUTERS 6TH ROAD | C6: =179795+15500+27380-50000-52600-20000-25000-52500+79545-75+58770-50000+29140-60000+386115-100000-36000-30000+49420-100000+1400+27570-50000-38460-40000+66265+20500-42000-40000+271800-250000+46945+123690-100000-47200-30000+81480+10000-96000-45480+247990-120000+36565-35550+12610-50000+46010-60000-57625-40000+293055+4300-100000-47000+69715-50000-30000-50000-40000-50000+5400+79420-30000+10300+72955-100000+70620-100000-42900-10000+53560+30350 -> 139775
A7: 5 | B7: ZAFAR & SONS RWP | C7: =' ZAFAR & SONS RWP 5 '!G36 -> 361700
A8: 6 | B8: FARHAN BAHI T.COM | C8: =30350+3000+100+100-15000+25000+40000+3380-33000+250000+100000+50000+53500-60000+2000+4500-7000-1000-5930-5000-2000-3000-5000-2000-3000-10000-2000-3000-5000-5000-5000-5000-5000-5000-5000-5000+80920-5000-3000-2920-5000-5000-3500+2000-3500-5000-5000-5000-10000-10000-2000-3000-5000-5000+3150+21950+96000+29700-2000-3800-5000-6500-3500-5000-5000-5000-5000-5000-5000-10000-10000-5000+120000+20000-13500-6500-5000-4000-6000-5000-4200-2000+5000+31250-2000-5000+25000-12000-10000+72000-101000-50000+35000-129000-50000+100000-100000-50000-107000+40000+60500+13000-100000+20000+22000+50000+4000+45000-103000+26500+9000+81000-46000+20000+30000+25000+50000+25000-150000+40000+100000+10000+100000-100000+10000+42900+13500-11000-360000+100000-13000-15000+114500+22000-9000+121000+13500-100000-20000-5000+22000+42900+25000+28000+26800-120000+6000-10000+154000+25000+6500-90000+50000+13750+86000+7000+45000+9200+12500-100000+11400+1500+25500+13000+20000+10000+125000+30000+40340+18500+4500 -> 906840
A9: 7 | B9: NAEEM BHAI PBM ISB LAPTOPS | C9: ='NAEEM BHI PBM ISB LAPTOPS 2'!G36 -> 355750
A10: 8 | B10: NASIM BAHI | C10: =+'NASNIM BHI-2'!G132 -> 590090
A11: 9 | B11: NAEEM BHAI PBM ISB | C11: ='NAEEM BHI PBM-3 '!G36 -> 111500
A12: 10 | B12: Abdul Rafay Accessories Supplier | C12: ='Abdul Rafay'!I105 -> 57825
A13: 11 | B13: ABDUL SATTAR BHAI UK | C13: =100000-80000 -> 20000
A14: 12 | B14: AHMED BAHI | C14: =94510-5000-10000-3000-500-3000-1000-3000-5200-5000-8800-2000-5000-5000-3000-5000-5000-3000-5500 -> 16510
A15: 13 | B15: LOAN FROM ABL TASNIM | C15: =324500+10000+15000+13500-15000+15000+34000-7500+120000+15000-15000-15000-12500-15000-15000-15000-12500+38000+15000-40000-21000-12500-15000-15000-7000-10000-12500-18300-7500-12759-29000-6500-5000-1000-2000-900 -> 261541
A16: 14 | B16: MUSA & ESSA | C16: =40000+120000+144000 -> 304000
A17: TOTAL | C17: =SUM(C4:C16) -> 3229881

Sheet NAEEM BHI PBM 1
A1: TASNIM COMPUTERS SALES & SERVICE
A2: NAEEM BHI PBM ISB LAPTOPS LEDGER
A3: FROM THE MONTH OF JANUARY 2024
A4: DATE | B4: TYPE | C4: REF# | D4: DESCRIPTION | E4: DEBIT | F4: CREDIT | G4: BALANCE
A6: 45008 | B6: PURCHASE | C6: BILL #0345 | D6: HP 840 G6 8GB/256GB | F6: 65000 | G6: =G5+F6-E6 -> 65000 | H6: =IF(G6=0,"NIL",IF(G6>0,"CR","DR")) -> CR
A7: 45008 | B7: PURCHASE | C7: BILL #0346 | D7: HP 450 G4 8GB/128/500GB | F7: 60000 | G7: =G6+F7-E7 -> 125000 | H7: =IF(G7=0,"NIL",IF(G7>0,"CR","DR")) -> CR
A8: 45008 | B8: PURCHASE | C8: BILL #0347 | D8: DELL 5580 TOUCH 1080 8GB/256 | F8: 65000 | G8: =G7+F8-E8 -> 190000 | H8: =IF(G8=0,"NIL",IF(G8>0,"CR","DR")) -> CR
A9: 45008 | B9: PURCHASE | C9: BILL #0348 | D9: DELL 5580 TOUCH 1080 8GB/256 | F9: 65000 | G9: =G8+F9-E9 -> 255000 | H9: =IF(G9=0,"NIL",IF(G9>0,"CR","DR")) -> CR
A10: 45374 | B10: PURCHASE | C10: BILL #0349 | D10: HP 840 G5 8GB/256GB | F10: 58000 | G10: =G9+F10-E10 -> 313000 | H10: =IF(G10=0,"NIL",IF(G10>0,"CR","DR")) -> CR
A11: 45374 | B11: PURCHASE | C11: BILL #0350 | D11: LENOVO T470 8GB/180 | F11: 49000 | G11: =G10+F11-E11 -> 362000 | H11: =IF(G11=0,"NIL",IF(G11>0,"CR","DR")) -> CR
A12: 45374 | B12: PURCHASE | C12: BILL #0351 | D12: DELL 7480 8GB/256GB | F12: 43000 | G12: =G11+F12-E12 -> 405000 | H12: =IF(G12=0,"NIL",IF(G12>0,"CR","DR")) -> CR
A13: 45374 | B13: PURCHASE | C13: BILL #0352 | D13: DELL 7480 8GB/256GB | F13: 43000 | G13: =G12+F13-E13 -> 448000 | H13: =IF(G13=0,"NIL",IF(G13>0,"CR","DR")) -> CR
A14: 45374 | B14: PURCHASE | C14: BILL #0353 | D14: DELL 7480 8GB/256GB | F14: 43000 | G14: =G13+F14-E14 -> 491000 | H14: =IF(G14=0,"NIL",IF(G14>0,"CR","DR")) -> CR
A15: 45374 | B15: PURCHASE | C15: BILL #0354 | D15: HP ELITEBOOK 840 G3 | F15: 45000 | G15: =G14+F15-E15 -> 536000 | H15: =IF(G15=0,"NIL",IF(G15>0,"CR","DR")) -> CR
A16: 45008 | B16: PURCHASE | C16: BILL #0355 | D16: DELL 3570 8GB/256GB | F16: 42000 | G16: =G15+F16-E16 -> 578000 | H16: =IF(G16=0,"NIL",IF(G16>0,"CR","DR")) -> CR
A17: 45374 | B17: PURCHASE | C17: BILL #0356 | D17: TOSHIBA PROTAG Z30 C 8GB/128GB | F17: 33500 | G17: =G16+F17-E17 -> 611500 | H17: =IF(G17=0,"NIL",IF(G17>0,"CR","DR")) -> CR
... A25: 45374 | B25: PURCHASE | C25: BILL #0364 | D25: DELL 6430 4GB/500GB | F25: 17000 | G25: =G24+F25-E25 -> 801000 | H25: =IF(G25=0,"NIL",IF(G25>0,"CR","DR")) -> CR
A26: 45375 | B26: PAYMENT | C26: 4624 | D26: ONLINE PAYMENT THROUGH BANK | E26: 45000 | G26: =G25+F26-E26 -> 756000 | H26: =IF(G26=0,"NIL",IF(G26>0,"CR","DR")) -> CR
A27: 45376 | B27: PURCHASE | C27: BILL #0364 | D27: LENOVO YOGA 460 360 TOUCH I5 6TH 8GB 256GB | F27: 48000 | G27: =G26+F27-E27 -> 804000 | H27: =IF(G27=0,"NIL",IF(G27>0,"CR","DR")) -> CR
A28: 45378 | B28: PURCHASE | C28: BILL #0364 | D28: HP ZBOOK I7 8TH GEN 16GB 256SSD | F28: 102000 | G28: =G27+F28-E28 -> 906000 | H28: =IF(G28=0,"NIL",IF(G28>0,"CR","DR")) -> CR
A29: 45383 | B29: RETURN | C29: BILL#0345 | D29: DELL LATITUDE 7480 I5 6TH 8/256 | E29: 43000 | G29: =G28+F29-E29 -> 863000 | H29: =IF(G29=0,"NIL",IF(G29>0,"CR","DR")) -> CR
A30: 45406 | B30: PAYMENT | C30: 6411 | D30: HP ZBOOK /DELL 6430 | E30: 122000 | G30: =G29+F30-E30 -> 741000 | H30: =IF(G30=0,"NIL",IF(G30>0,"CR","DR")) -> CR
A31: 45406 | B31: RETURN | C31: BILL #0364 | D31: DELL 7480 / LENOVO YOGA 360 | E31: 91000 | G31: =G30+F31-E31 -> 650000 | H31: =IF(G31=0,"NIL",IF(G31>0,"CR","DR")) -> CR
A32: 45414 | B32: PAYMENT | C32: 6411 | D32: HP ELITEBOOK 840 G5 I5 7TH GEN | E32: 58000 | G32: =G31+F32-E32 -> 592000 | H32: =IF(G32=0,"NIL",IF(G32>0,"CR","DR")) -> CR
A33: 45415 | B33: RETURN | C33: BILL #0364 | D33: DELL 5580 QTY 2 | E33: 130000 | G33: =G32+F33-E33 -> 462000 | H33: =IF(G33=0,"NIL",IF(G33>0,"CR","DR")) -> CR
A34: 45421 | B34: PAYMENT | C34: 6411 | D34: TOSHIBA Z30 I5 4TH GEN | E34: 27000 | G34: =G33+F34-E34 -> 435000 | H34: =IF(G34=0,"NIL",IF(G34>0,"CR","DR")) -> CR
A35: 45421 | B35: PURCHASE | C35: BILL#0345 | D35: DELL 5570 I7 6TH HQ 8GB/256GB SSD | F35: 60000 | G35: =G34+F35-E35 -> 495000 | H35: =IF(G35=0,"NIL",IF(G35>0,"CR","DR")) -> CR
D36: TOTAL BALANCE | E36: =SUM(E6:E35) -> 516000 | F36: =SUM(F6:F35) -> 1011000 | G36: =G5+F36-E36 -> 495000 | H36: =IF(G36=0,"NIL",IF(G36>0,"CR","DR")) -> CR

Sheet NAEEM BHI PBM-2
A1: TASNIM COMPUTERS SALES & SERVICE | J1: PAYABLE HOME
A2: NAEEM BHI PBM ISB LAPTOPS LEDGER
A3: FROM THE MONTH OF JANUARY 2024
A4: DATE | B4: TYPE | C4: REF# | D4: DESCRIPTION | E4: DEBIT | F4: CREDIT | G4: BALANCE
G5: ='NAEEM BHI PBM 1'!G36 -> 495000
A6: 45423 | B6: PURCHASE | C6: BILL#0345 | D6: LENOVO T450 I7 5TH 8GB 256GB +CHARGER | F6: 41000 | G6: =G5+F6-E6 -> 536000 | H6: =IF(G6=0,"NIL",IF(G6>0,"CR","DR")) -> CR
A7: 45435 | B7: PURCHASE | D7: HP 840 G3 I5-6TH 8GB-256 NO CHARGER | F7: 43000 | G7: =G6+F7-E7 -> 579000 | H7: =IF(G7=0,"NIL",IF(G7>0,"CR","DR")) -> CR
A8: 45435 | B8: PURCHASE | D8: HP 840 G3 I5-6TH 8GB-256 NO CHARGER | F8: 43000 | G8: =G7+F8-E8 -> 622000 | H8: =IF(G8=0,"NIL",IF(G8>0,"CR","DR")) -> CR
A9: 45435 | B9: PURCHASE | D9: HP 840 G3 I7-6TH 8GB-256 NO CHARGER | F9: 47000 | G9: =G8+F9-E9 -> 669000 | H9: =IF(G9=0,"NIL",IF(G9>0,"CR","DR")) -> CR
A10: 45437 | B10: PURCHASE | D10: DELL 5420 I5-2ND-4GB-250GB NO CHRG | F10: 18000 | G10: =G9+F10-E10 -> 687000 | H10: =IF(G10=0,"NIL",IF(G10>0,"CR","DR")) -> CR
A11: 45441 | B11: PAYMENT | C11: 47882 | D11: TOSIBA Z30 / HP 840 G6 | E11: 98500 | F11: 0 | G11: =G10+F11-E11 -> 588500 | H11: =IF(G11=0,"NIL",IF(G11>0,"CR","DR")) -> CR
A12: 45445 | B12: PURCHASE | D12: LENOVO T52S CORE I7 8TH 16GB 512GB CHARGER | E12: 0 | F12: 105000 | G12: =G11+F12-E12 -> 693500 | H12: =IF(G12=0,"NIL",IF(G12>0,"CR","DR")) -> CR
A13: 45445 | B13: PURCHASE | D13: HP ELITBOOK 84 0 G3 I5 6TH GEN 8GB 256GB | E13: 0 | F13: 43000 | G13: =G12+F13-E13 -> 736500 | H13: =IF(G13=0,"NIL",IF(G13>0,"CR","DR")) -> CR
A14: 45450 | B14: PAYMENT | C14: 47882 | D14: HP 450 g4 / 5420 | E14: 80000 | F14: 0 | G14: =G13+F14-E14 -> 656500 | H14: =IF(G14=0,"NIL",IF(G14>0,"CR","DR")) -> CR
A15: 45454 | B15: PURCHASE | D15: HP 840 G6 I5-8TH 16GB-256 + CHARGER | F15: 70000 | G15: =G14+F15-E15 -> 726500 | H15: =IF(G15=0,"NIL",IF(G15>0,"CR","DR")) -> CR
A16: 45475 | B16: PAYMENT | C16: 47852 | D16: Dell 3570/7440/5420 | E16: 94500 | G16: =G15+F16-E16 -> 632000 | H16: =IF(G16=0,"NIL",IF(G16>0,"CR","DR")) -> CR
A17: 45477 | B17: PURCHASE | D17: ACER CHOROME BOOK | F17: 12000 | G17: =G16+F17-E17 -> 644000 | H17: =IF(G17=0,"NIL",IF(G17>0,"CR","DR")) -> CR
A18: 45477 | B18: PURCHASE | D18: HP CHOROME BOOK (FOR TASNIM) | F18: 12000 | G18: =G17+F18-E18 -> 656000 | H18: =IF(G18=0,"NIL",IF(G18>0,"CR","DR")) -> CR
A19: 45477 | B19: PURCHASE | D19: DELL 5570 I7-7TH-8-256 2GB CARD NO CHARGER | F19: 53000 | G19: =G18+F19-E19 -> 709000 | H19: =IF(G19=0,"NIL",IF(G19>0,"CR","DR")) -> CR
A20: 45477 | B20: PURCHASE | D20: DELL 7470 I7-6TH-8-256 | F20: 42000 | G20: =G19+F20-E20 -> 751000 | H20: =IF(G20=0,"NIL",IF(G20>0,"CR","DR")) -> CR
A21: 45485 | B21: PAYMENT | D21: DELL 5570(53K) / HP 840 G3 QTY 2(43KX2) | E21: 139000 | G21: =G20+F21-E21 -> 612000 | H21: =IF(G21=0,"NIL",IF(G21>0,"CR","DR")) -> CR
A22: 45485 | B22: PURCHASE | D22: DELL 5570 I7-7TH-8-256 2GB CARD NO CHARGER | F22: 53000 | G22: =G21+F22-E22 -> 665000 | H22: =IF(G22=0,"NIL",IF(G22>0,"CR","DR")) -> CR
A23: 45485 | B23: PURCHASE | D23: HP ELITBOOK 840 G3 I5 6TH GEN 8GB 128GB | F23: 41000 | G23: =G22+F23-E23 -> 706000 | H23: =IF(G23=0,"NIL",IF(G23>0,"CR","DR")) -> CR
A24: 45485 | B24: PURCHASE | D24: HP 840 G3 I7-6TH 8GB-256 NO CHARGER | F24: 47000 | G24: =G23+F24-E24 -> 753000 | H24: =IF(G24=0,"NIL",IF(G24>0,"CR","DR")) -> CR
A25: 45485 | B25: PURCHASE | D25: DELL 3490 I3-7TH-8GB-128SSD+500HDD + CHRG | F25: 34000 | G25: =G24+F25-E25 -> 787000 | H25: =IF(G25=0,"NIL",IF(G25>0,"CR","DR")) -> CR
A26: 45485 | B26: PURCHASE | D26: HP ELITE X2 I5 7TH GEN 8GB 256GB + CHARG | F26: 44000 | G26: =G25+F26-E26 -> 831000 | H26: =IF(G26=0,"NIL",IF(G26>0,"CR","DR")) -> CR
A27: 45494 | B27: RETURN | D27: LENOVO T52S RETURN | E27: 105000 | G27: =G26+F27-E27 -> 726000 | H27: =IF(G27=0,"NIL",IF(G27>0,"CR","DR")) -> CR
A28: 45494 | B28: RETURN | D28: DELL 3490 RETURN | E28: 34000 | G28: =G27+F28-E28 -> 692000 | H28: =IF(G28=0,"NIL",IF(G28>0,"CR","DR")) -> CR
A29: 45503 | B29: PAYMENT | D29: HP 840 G6 / DELL 5570 | E29: 130000 | G29: =G28+F29-E29 -> 562000 | H29: =IF(G29=0,"NIL",IF(G29>0,"CR","DR")) -> CR
A30: 45507 | B30: PURCHASE | D30: LENOVO i5-4TH GEN 8 500 NO CHARGER | F30: 28000 | G30: =G29+F30-E30 -> 590000 | H30: =IF(G30=0,"NIL",IF(G30>0,"CR","DR")) -> CR
A31: 45507 | B31: PURCHASE | D31: DELL 5570 I7-6TH-8-256 2GB CARD NO CHARGER | F31: 53000 | G31: =G30+F31-E31 -> 643000 | H31: =IF(G31=0,"NIL",IF(G31>0,"CR","DR")) -> CR
A32: 45511 | B32: PAYMENT | D32: DELL 5570 / LENOVO T470 | E32: 102000 | G32: =G31+F32-E32 -> 541000 | H32: =IF(G32=0,"NIL",IF(G32>0,"CR","DR")) -> CR
A33: 45512 | B33: PURCHASE | D33: HP 840 G6 | F33: 70000 | G33: =G32+F33-E33 -> 611000 | H33: =IF(G33=0,"NIL",IF(G33>0,"CR","DR")) -> CR
D34: TOTAL BALANCE | E34: =SUM(E6:E33) -> 783000 | F34: =SUM(F6:F33) -> 899000 | G34: =G5+F34-E34 -> 611000 | H34: =IF(G34=0,"NIL",IF(G34>0,"CR","DR")) -> CR

Sheet NAEEM BHI PBM-3 
A1: TASNIM COMPUTERS SALES & SERVICE | J1: PAYABLE HOME
A2: NAEEM BHI PBM ISB LAPTOPS LEDGER
A3: FROM THE MONTH OF JANUARY 2024
A4: DATE | B4: TYPE | C4: REF# | D4: DESCRIPTION | E4: DEBIT | F4: CREDIT | G4: BALANCE
G5: ='NAEEM BHI PBM-2'!G34 -> 611000
A6: 45513 | B6: RETURN | C6: RETURN | D6: LENONVO T540 RETURN | E6: 28000 | G6: =G5+F6-E6 -> 583000 | H6: =IF(G6=0,"NIL",IF(G6>0,"CR","DR")) -> CR
A7: 45519 | B7: PURCHASE | C7: 907032174 | D7: lenovo x1 carbon /chrome book | F7: 59000 | G7: =G6+F7-E7 -> 642000 | H7: =IF(G7=0,"NIL",IF(G7>0,"CR","DR")) -> CR
A8: 45521 | B8: RETURN | C8: RETURN | D8: HP 840 G6 RETURN | E8: 70000 | G8: =G7+F8-E8 -> 572000 | H8: =IF(G8=0,"NIL",IF(G8>0,"CR","DR")) -> CR
A9: 45523 | B9: PAYMENT | C9: PAYMENT | D9: ONLINE PAYMENT THROUGH BOP | E9: 179000 | G9: =G8+F9-E9 -> 393000 | H9: =IF(G9=0,"NIL",IF(G9>0,"CR","DR")) -> CR
A10: 45524 | B10: PURCHASE | C10: PURCHASE | D10: HP CHOROME BOOK | F10: 12000 | G10: =G9+F10-E10 -> 405000 | H10: =IF(G10=0,"NIL",IF(G10>0,"CR","DR")) -> CR
A11: 45537 | B11: PAYMENT | C11: PAYMENT | D11: ONLINE PAYMENT THROUGH BOP | E11: 65000 | G11: =G10+F11-E11 -> 340000 | H11: =IF(G11=0,"NIL",IF(G11>0,"CR","DR")) -> CR
A12: 45544 | B12: PAYMENT | C12: PAYMENT | D12: ONLINE PAYMENT THROUGH BOP | E12: 53000 | G12: =G11+F12-E12 -> 287000 | H12: =IF(G12=0,"NIL",IF(G12>0,"CR","DR")) -> CR
A13: 45558 | B13: PAYMENT | C13: PAYMENT | D13: ONLINE PAYMENT THROUGH BOP | E13: 44000 | G13: =G12+F13-E13 -> 243000 | H13: =IF(G13=0,"NIL",IF(G13>0,"CR","DR")) -> CR
A14: 45576 | B14: PAYMENT | C14: PAYMENT | D14: ONLINE PAYMENT THROUGH BOP | E14: 43000 | G14: =G13+F14-E14 -> 200000 | H14: =IF(G14=0,"NIL",IF(G14>0,"CR","DR")) -> CR
A15: 45579 | B15: PURCHASE | C15: PURCHASE | D15: DELL LATITIDUE 5580 I7-7TH-8-256+CHARGER | E15: 0 | F15: 60000 | G15: =G14+F15-E15 -> 260000 | H15: =IF(G15=0,"NIL",IF(G15>0,"CR","DR")) -> CR
A16: 45584 | B16: PURCHASE | C16: PURCHASE | G16: =G15+F16-E16 -> 260000 | H16: =IF(G16=0,"NIL",IF(G16>0,"CR","DR")) -> CR
A17: 45587 | B17: PAYMENT | C17: PAYMENT | D17: ONLINE PAYMENT THROUGH BOP | E17: 47000 | G17: =G16+F17-E17 -> 213000 | H17: =IF(G17=0,"NIL",IF(G17>0,"CR","DR")) -> CR
A18: 45607 | B18: PAYMENT | C18: PAYMENT | D18: ONLINE PAYMENT THROUGH BOP | E18: 60000 | G18: =G17+F18-E18 -> 153000 | H18: =IF(G18=0,"NIL",IF(G18>0,"CR","DR")) -> CR
A19: 45611 | B19: PAYMENT | C19: PAYMENT | D19: ONLINE PAYMENT THROUGH BOP | E19: 12000 | G19: =G18+F19-E19 -> 141000 | H19: =IF(G19=0,"NIL",IF(G19>0,"CR","DR")) -> CR
A20: 45707 | B20: PAYMENT | C20: PAYMENT | D20: ONLINE PAYMENT THROUGH BOP | E20: 29500 | G20: =G19+F20-E20 -> 111500 | H20: =IF(G20=0,"NIL",IF(G20>0,"CR","DR")) -> CR
G21: =G20+F21-E21 -> 111500 | H21: =IF(G21=0,"NIL",IF(G21>0,"CR","DR")) -> CR
G22: =G21+F22-E22 -> 111500 | H22: =IF(G22=0,"NIL",IF(G22>0,"CR","DR")) -> CR
G23: =G22+F23-E23 -> 111500 | H23: =IF(G23=0,"NIL",IF(G23>0,"CR","DR")) -> CR
G24: =G23+F24-E24 -> 111500 | H24: =IF(G24=0,"NIL",IF(G24>0,"CR","DR")) -> CR
G25: =G24+F25-E25 -> 111500 | H25: =IF(G25=0,"NIL",IF(G25>0,"CR","DR")) -> CR
G26: =G25+F26-E26 -> 111500 | H26: =IF(G26=0,"NIL",IF(G26>0,"CR","DR")) -> CR
G27: =G26+F27-E27 -> 111500 | H27: =IF(G27=0,"NIL",IF(G27>0,"CR","DR")) -> CR
G28: =G27+F28-E28 -> 111500 | H28: =IF(G28=0,"NIL",IF(G28>0,"CR","DR")) -> CR
G29: =G28+F29-E29 -> 111500 | H29: =IF(G29=0,"NIL",IF(G29>0,"CR","DR")) -> CR
G30: =G29+F30-E30 -> 111500 | H30: =IF(G30=0,"NIL",IF(G30>0,"CR","DR")) -> CR
G31: =G30+F31-E31 -> 111500 | H31: =IF(G31=0,"NIL",IF(G31>0,"CR","DR")) -> CR
G32: =G31+F32-E32 -> 111500 | H32: =IF(G32=0,"NIL",IF(G32>0,"CR","DR")) -> CR
... G35: =G34+F35-E35 -> 111500 | H35: =IF(G35=0,"NIL",IF(G35>0,"CR","DR")) -> CR
D36: TOTAL BALANCE | E36: =SUM(E6:E35) -> 630500 | F36: =SUM(F6:F35) -> 131000 | G36: =G5+F36-E36 -> 111500 | H36: =IF(G36=0,"NIL",IF(G36>0,"CR","DR")) -> CR

Sheet NAEEM BHI PBM ISB LAPTOPS 1 
A1: TASNIM COMPUTERS SALES & SERVICE | J1: PAYABLE HOME
A2: NAEEM BHI PBM ISB LAPTOPS LEDGER
A3: FROM THE MONTH OF APRIL 2026
A4: DATE | B4: TYPE | C4: REF# | D4: DESCRIPTION | E4: DEBIT | F4: CREDIT | G4: BALANCE
A5: 46078 | B5: PURCHASE | C5: LAPTOPS | D5: PURCHASE LAPTOPS QTY 09 | G5: 502000
A6: 46110 | B6: PAYMENT | C6: CASH | D6: CASH BY HAND AT HOME | E6: 90000 | G6: =G5+F6-E6 -> 412000 | H6: =IF(G6=0,"NIL",IF(G6>0,"CR","DR")) -> CR
A7: 46110 | B7: PURCHASE | C7: LAPTOP/SSD | D7: laptop/ssd | F7: 10450 | G7: =G6+F7-E7 -> 422450 | H7: =IF(G7=0,"NIL",IF(G7>0,"CR","DR")) -> CR
A8: 46113 | B8: PURCHASE | C8: LAPTOP | D8: HP 840 I5 10TH GEN 8/256 | F8: 65000 | G8: =G7+F8-E8 -> 487450 | H8: =IF(G8=0,"NIL",IF(G8>0,"CR","DR")) -> CR
A9: 46113 | B9: PURCHASE | C9: LAPTOP | D9: DELL 7470 I5 6TH 8/256 | F9: 35000 | G9: =G8+F9-E9 -> 522450 | H9: =IF(G9=0,"NIL",IF(G9>0,"CR","DR")) -> CR
A10: 46119 | B10: PURCHASE | C10: CHARGER | D10: LAPTOP CHARGER | F10: 60200 | G10: =G9+F10-E10 -> 582650 | H10: =IF(G10=0,"NIL",IF(G10>0,"CR","DR")) -> CR
A11: 46119 | B11: PURCHASE | C11: LAPTOP | D11: LENOVO T490S I5 8TH 8/256 | F11: 45000 | G11: =G10+F11-E11 -> 627650 | H11: =IF(G11=0,"NIL",IF(G11>0,"CR","DR")) -> CR
A12: 46119 | B12: PAYMENT | C12: CASH | D12: ONLINE MEEZAN BANK NAEEM SIR | E12: 90000 | G12: =G11+F12-E12 -> 537650 | H12: =IF(G12=0,"NIL",IF(G12>0,"CR","DR")) -> CR
A13: 45389 | B13: PAYMENT | C13: CASH | D13: ONLINE MEEZAN BANK NAEEM SIR | E13: 50000 | G13: =G12+F13-E13 -> 487650 | H13: =IF(G13=0,"NIL",IF(G13>0,"CR","DR")) -> CR
A14: 46121 | B14: PURCHASE | C14: LAPTOP | D14: LENOVO L380 I5 8TH 8GB 256 | F14: 44000 | G14: =G13+F14-E14 -> 531650 | H14: =IF(G14=0,"NIL",IF(G14>0,"CR","DR")) -> CR
A15: 46121 | B15: PURCHASE | C15: LAPTOP | D15: LENOVO T460 I5 6TH 8GB 256GB | F15: 35000 | G15: =G14+F15-E15 -> 566650 | H15: =IF(G15=0,"NIL",IF(G15>0,"CR","DR")) -> CR
A16: 46121 | B16: PURCHASE | C16: LAPTOP | D16: PRINTER CABLE 3M | F16: 450 | G16: =G15+F16-E16 -> 567100 | H16: =IF(G16=0,"NIL",IF(G16>0,"CR","DR")) -> CR
A17: 46121 | B17: PURCHASE | C17: LAPTOP | D17: PRINTER CABLE 1.5 QTY 270*5 | F17: 1350 | G17: =G16+F17-E17 -> 568450 | H17: =IF(G17=0,"NIL",IF(G17>0,"CR","DR")) -> CR
A18: 46128 | B18: PURCHASE | C18: LAPTOP | D18: HP 840 I5 8TH 16/512 | F18: 69000 | G18: =G17+F18-E18 -> 637450 | H18: =IF(G18=0,"NIL",IF(G18>0,"CR","DR")) -> CR
A19: 46128 | B19: PURCHASE | C19: LAPTOP | D19: HP 840 I5 8TH 16/512 | F19: 69000 | G19: =G18+F19-E19 -> 706450 | H19: =IF(G19=0,"NIL",IF(G19>0,"CR","DR")) -> CR
A20: 46128 | B20: PURCHASE | C20: CHARGER | D20: LENOVO TYPE-C CHARGER | F20: 4400 | G20: =G19+F20-E20 -> 710850 | H20: =IF(G20=0,"NIL",IF(G20>0,"CR","DR")) -> CR
A21: 46132 | B21: PURCHASE | C21: LAPTOP | D21: HP 840 I7 8TH 16/512 | F21: 74000 | G21: =G20+F21-E21 -> 784850 | H21: =IF(G21=0,"NIL",IF(G21>0,"CR","DR")) -> CR
A22: 46132 | B22: PURCHASE | C22: LAPTOP | D22: HP 840 I7 8TH 16/512 | F22: 74000 | G22: =G21+F22-E22 -> 858850 | H22: =IF(G22=0,"NIL",IF(G22>0,"CR","DR")) -> CR
A23: 46132 | B23: PURCHASE | C23: RAM | D23: LAPTOP RAM DDR 4 8GB | F23: 8000 | G23: =G22+F23-E23 -> 866850 | H23: =IF(G23=0,"NIL",IF(G23>0,"CR","DR")) -> CR
A24: 46137 | B24: RETURNE | C24: LAPTOP | D24: DELL 5491H I5 8TH 8GB 256 | E24: 44000 | G24: =G23+F24-E24 -> 822850 | H24: =IF(G24=0,"NIL",IF(G24>0,"CR","DR")) -> CR
A25: 46137 | B25: RETURNE | C25: LAPTOP | D25: DELL 5491H I5 8TH 8GB 256 | E25: 45000 | G25: =G24+F25-E25 -> 777850 | H25: =IF(G25=0,"NIL",IF(G25>0,"CR","DR")) -> CR
A26: 46141 | B26: RETURNE | C26: LAPTOP | D26: DELL 5501 I5 9TH 8GB 256 | E26: 60000 | G26: =G25+F26-E26 -> 717850 | H26: =IF(G26=0,"NIL",IF(G26>0,"CR","DR")) -> CR
A27: 46136 | B27: PAYMENT | C27: CASH | D27: ONLINE MEEZAN BANK NAEEM SIR | E27: 200000 | G27: =G26+F27-E27 -> 517850 | H27: =IF(G27=0,"NIL",IF(G27>0,"CR","DR")) -> CR
A28: 46138 | B28: PURCHASE | C28: LAPTOP | D28: DELL 5400 I5 8TH 8GB 256GB | F28: 44000 | G28: =G27+F28-E28 -> 561850 | H28: =IF(G28=0,"NIL",IF(G28>0,"CR","DR")) -> CR
A29: 46138 | B29: PURCHASE | C29: LAPTOP | D29: LENOVO T480 I5 8TH 8GB 256GB | F29: 44000 | G29: =G28+F29-E29 -> 605850 | H29: =IF(G29=0,"NIL",IF(G29>0,"CR","DR")) -> CR
A30: 46138 | B30: PURCHASE | C30: LAPTOP | D30: DELL LATITUDE 7440 I5 6TH 8GB 256GB | F30: 35000 | G30: =G29+F30-E30 -> 640850 | H30: =IF(G30=0,"NIL",IF(G30>0,"CR","DR")) -> CR
A31: 46138 | B31: PURCHASE | C31: LAPTOP | D31: HP 840 G5 I5 8TH 8GB 256GB | F31: 62000 | G31: =G30+F31-E31 -> 702850 | H31: =IF(G31=0,"NIL",IF(G31>0,"CR","DR")) -> CR
A32: 46138 | B32: PURCHASE | C32: LAPTOP | D32: LENOVO L490 I7 8TH 8GB 256GB | F32: 47000 | G32: =G31+F32-E32 -> 749850 | H32: =IF(G32=0,"NIL",IF(G32>0,"CR","DR")) -> CR
A33: 46138 | B33: PURCHASE | C33: RAM | D33: L.P RAM DDR 3 4GB | F33: 6000 | G33: =G32+F33-E33 -> 755850 | H33: =IF(G33=0,"NIL",IF(G33>0,"CR","DR")) -> CR
A34: 46138 | B34: PURCHASE | C34: LP CHARGER | D34: LENOVO CHARGER TYPE C QTY 2 | F34: 4400 | G34: =G33+F34-E34 -> 760250 | H34: =IF(G34=0,"NIL",IF(G34>0,"CR","DR")) -> CR
G35: =G34+F35-E35 -> 760250 | H35: =IF(G35=0,"NIL",IF(G35>0,"CR","DR")) -> CR
D36: TOTAL BALANCE | E36: =SUM(E6:E35) -> 579000 | F36: =SUM(F6:F35) -> 837250 | G36: =G5+F36-E36 -> 760250 | H36: =IF(G36=0,"NIL",IF(G36>0,"CR","DR")) -> CR

Sheet NAEEM BHI PBM ISB LAPTOPS 2
A1: TASNIM COMPUTERS SALES & SERVICE | J1: PAYABLE HOME
A2: NAEEM BHI PBM ISB LAPTOPS LEDGER
A3: FROM THE MONTH OF APRIL 2026
A4: DATE | B4: TYPE | C4: REF# | D4: DESCRIPTION | E4: DEBIT | F4: CREDIT | G4: BALANCE
G5: 760250
A6: 46142 | B6: PAYMENT | C6: CASH | D6: ONLINE MEEZAN BANK NAEEM SIR | E6: 40000 | G6: =G5+F6-E6 -> 720250 | H6: =IF(G6=0,"NIL",IF(G6>0,"CR","DR")) -> CR
A7: 46118 | B7: RETURNE | C7: LAPTOP | D7: LENOVO YOGA G5 I7 10TH 16/512 | E7: 100000 | G7: =G6+F7-E7 -> 620250 | H7: =IF(G7=0,"NIL",IF(G7>0,"CR","DR")) -> CR
A8: 46148 | B8: PURCHASE | C8: LAPTOP | D8: DELL LATITUDE 7470 I5 6TH 8/256GB | F8: 37000 | G8: =G7+F8-E8 -> 657250 | H8: =IF(G8=0,"NIL",IF(G8>0,"CR","DR")) -> CR
A9: 46148 | B9: PURCHASE | C9: LAPTOP | D9: LENOVO T470S I7 6TH 8GB /256GB | F9: 40000 | G9: =G8+F9-E9 -> 697250 | H9: =IF(G9=0,"NIL",IF(G9>0,"CR","DR")) -> CR
A10: 46153 | B10: PAYMENT | C10: CASH | D10: ONLINE MEEZAN BANK NAEEM SIR | E10: 130000 | G10: =G9+F10-E10 -> 567250 | H10: =IF(G10=0,"NIL",IF(G10>0,"CR","DR")) -> CR
A11: 46162 | B11: PAYMENT | C11: CASH | D11: ONLINE MEEZAN BANK NAEEM SIR | E11: 65000 | G11: =G10+F11-E11 -> 502250 | H11: =IF(G11=0,"NIL",IF(G11>0,"CR","DR")) -> CR
A12: 46184 | B12: PAYMENT | C12: CASH | D12: 7470-L490-T480 | E12: 128000 | G12: =G11+F12-E12 -> 374250 | H12: =IF(G12=0,"NIL",IF(G12>0,"CR","DR")) -> CR
A13: 46185 | B13: PURCHASE | C13: LAPTOP | D13: HP 840 G7 I5 10TH GEN 16GB/256GB | F13: 73000 | G13: =G12+F13-E13 -> 447250 | H13: =IF(G13=0,"NIL",IF(G13>0,"CR","DR")) -> CR
A14: 46185 | B14: PURCHASE | C14: LAPTOP | D14: LENOVO T470S I7 6TH 8GB /256GB | F14: 39000 | G14: =G13+F14-E14 -> 486250 | H14: =IF(G14=0,"NIL",IF(G14>0,"CR","DR")) -> CR
A15: 46185 | B15: PURCHASE | C15: LAPTOP | D15: LENOVO T490S I5 8TH 8GB/256GB | F15: 44000 | G15: =G14+F15-E15 -> 530250 | H15: =IF(G15=0,"NIL",IF(G15>0,"CR","DR")) -> CR
A16: 46175 | B16: PAYMENT | C16: CASH | D16: ONLINE MEEZAN BANK NAEEM SIR | E16: 39000 | G16: =G15+F16-E16 -> 491250 | H16: =IF(G16=0,"NIL",IF(G16>0,"CR","DR")) -> CR
A17: 46207 | B17: PURCHASE | C17: LAPTOP | D17: LENOVO T470S I5 6TH 8GB /256GB | F17: 35000 | G17: =G16+F17-E17 -> 526250 | H17: =IF(G17=0,"NIL",IF(G17>0,"CR","DR")) -> CR
A18: 46207 | B18: PURCHASE | C18: LAPTOP | D18: LENOVO T460S I5 7TH 8GB / 256GB | F18: 38000 | G18: =G17+F18-E18 -> 564250 | H18: =IF(G18=0,"NIL",IF(G18>0,"CR","DR")) -> CR
A19: 46207 | B19: PURCHASE | C19: LAPTOP | D19: LENOVO L490 I78TH 8GB / 258GB | F19: 46000 | G19: =G18+F19-E19 -> 610250 | H19: =IF(G19=0,"NIL",IF(G19>0,"CR","DR")) -> CR
A20: 46207 | B20: PURCHASE | C20: LAPTOP | D20: LENOVO YOGA L389 I5 8TH 8GB 256GB | F20: 46000 | G20: =G19+F20-E20 -> 656250 | H20: =IF(G20=0,"NIL",IF(G20>0,"CR","DR")) -> CR
A21: 46207 | B21: PURCHASE | C21: LAPTOP | D21: HP PROBOOK 440 I5 7TH 8GB 256GB | F21: 39000 | G21: =G20+F21-E21 -> 695250 | H21: =IF(G21=0,"NIL",IF(G21>0,"CR","DR")) -> CR
A22: 46209 | B22: PAYMENT | C22: CASH | D22: ONLINE MEEZAN BANK NAEEM SIR | E22: 50000 | G22: =G21+F22-E22 -> 645250 | H22: =IF(G22=0,"NIL",IF(G22>0,"CR","DR")) -> CR
A23: 46213 | B23: PAYMENT | C23: CASH | D23: ONLINE MEEZAN BANK NAEEM SIR | E23: 49000 | G23: =G22+F23-E23 -> 596250 | H23: =IF(G23=0,"NIL",IF(G23>0,"CR","DR")) -> CR
A24: 46252 | B24: PURCHASE | C24: SSD | D24: 128GB 256GB BREAKABLE | F24: 18500 | G24: =G23+F24-E24 -> 614750 | H24: =IF(G24=0,"NIL",IF(G24>0,"CR","DR")) -> CR
A25: 46256 | B25: PURCHASE | C25: LAPTOP | D25: HP ELITEBOOK G8 I5 11TH 16GB/256 | F25: 75000 | G25: =G24+F25-E25 -> 689750 | H25: =IF(G25=0,"NIL",IF(G25>0,"CR","DR")) -> CR
A26: 46256 | B26: PURCHASE | C26: LAPTOP | D26: HP ELITEBOOK G9 I5 12TH 16GB/256GB | F26: 11000 | G26: =G25+F26-E26 -> 700750 | H26: =IF(G26=0,"NIL",IF(G26>0,"CR","DR")) -> CR
A27: 46256 | B27: PAYMENT | C27: CASH | D27: ONLINE MEEZAN BANK NAEEM SIR | E27: 345000 | G27: =G26+F27-E27 -> 355750 | H27: =IF(G27=0,"NIL",IF(G27>0,"CR","DR")) -> CR
G28: =G27+F28-E28 -> 355750 | H28: =IF(G28=0,"NIL",IF(G28>0,"CR","DR")) -> CR
G29: =G28+F29-E29 -> 355750 | H29: =IF(G29=0,"NIL",IF(G29>0,"CR","DR")) -> CR
G30: =G29+F30-E30 -> 355750 | H30: =IF(G30=0,"NIL",IF(G30>0,"CR","DR")) -> CR
G31: =G30+F31-E31 -> 355750 | H31: =IF(G31=0,"NIL",IF(G31>0,"CR","DR")) -> CR
G32: =G31+F32-E32 -> 355750 | H32: =IF(G32=0,"NIL",IF(G32>0,"CR","DR")) -> CR
G33: =G32+F33-E33 -> 355750 | H33: =IF(G33=0,"NIL",IF(G33>0,"CR","DR")) -> CR
G34: =G33+F34-E34 -> 355750 | H34: =IF(G34=0,"NIL",IF(G34>0,"CR","DR")) -> CR
G35: =G34+F35-E35 -> 355750 | H35: =IF(G35=0,"NIL",IF(G35>0,"CR","DR")) -> CR
D36: TOTAL BALANCE | E36: =SUM(E6:E35) -> 946000 | F36: =SUM(F6:F35) -> 541500 | G36: =G5+F36-E36 -> 355750 | H36: =IF(G36=0,"NIL",IF(G36>0,"CR","DR")) -> CR

Sheet  ZAFAR & SONS RWP 1
A1: TASNIM COMPUTERS SALES & SERVICE | J1: PAYABLE HOME
A2: ZAFAR & SONS RWP LEDGER
A3: FROM THE MONTH OF JANUARY 2024
A4: DATE | B4: TYPE | C4: REF# | D4: DESCRIPTION | E4: DEBIT | F4: CREDIT | G4: BALANCE
A6: 45296 | B6: PURCHASE | C6: BILL# 0140 | D6: SYSTEMS /LCD/GRAPHIC CARD | F6: 130900 | G6: =G5+F6-E6 -> 130900 | H6: =IF(G6=0,"NIL",IF(G6>0,"CR","DR")) -> CR
A7: 45299 | B7: PAYMENT | C7: 890968438 | D7: ONLINE PAYMENT THROUGH BANK | E7: 50000 | G7: =G6+F7-E7 -> 80900 | H7: =IF(G7=0,"NIL",IF(G7>0,"CR","DR")) -> CR
A8: 45312 | B8: PAYMENT | C8: 897169914 | D8: ONLINE PAYMENT THROUGH BANK | E8: 30900 | G8: =G7+F8-E8 -> 50000 | H8: =IF(G8=0,"NIL",IF(G8>0,"CR","DR")) -> CR
A9: 45315 | B9: PAYMENT | C9: CASH | D9: CASH BY HAND | E9: 100000 | F9: 50000 | G9: =G8+F9-E9 -> 0 | H9: =IF(G9=0,"NIL",IF(G9>0,"CR","DR")) -> NIL
A10: 45315 | B10: PURCHASE | C10: BILL# 0210 | D10: LEDS PURCHASED | F10: 373000 | G10: =G9+F10-E10 -> 373000 | H10: =IF(G10=0,"NIL",IF(G10>0,"CR","DR")) -> CR
A11: 45320 | B11: PAYMENT | C11: 900487264 | D11: ONLINE PAYMENT THROUGH BANK | E11: 45000 | G11: =G10+F11-E11 -> 328000 | H11: =IF(G11=0,"NIL",IF(G11>0,"CR","DR")) -> CR
A12: 45331 | B12: PAYMENT | C12: 907032174 | D12: ONLINE PAYMENT THROUGH BANK | E12: 100000 | G12: =G11+F12-E12 -> 228000 | H12: =IF(G12=0,"NIL",IF(G12>0,"CR","DR")) -> CR
A13: 45339 | B13: PAYMENT | C13: 4372 | D13: ONLINE PAYMENT THROUGH BANK | E13: 100000 | G13: =G12+F13-E13 -> 128000 | H13: =IF(G13=0,"NIL",IF(G13>0,"CR","DR")) -> CR
A14: 45339 | B14: PURCHASE | C14: BILL# 0408 | D14: SYSTEMS /LCD/GRAPHIC CARD | F14: 249000 | G14: =G13+F14-E14 -> 377000 | H14: =IF(G14=0,"NIL",IF(G14>0,"CR","DR")) -> CR
A15: 45339 | B15: PURCHASE | C15: BILL# 0407 | D15: GRAPHIC CARD LED | F15: 177800 | G15: =G14+F15-E15 -> 554800 | H15: =IF(G15=0,"NIL",IF(G15>0,"CR","DR")) -> CR
A16: 45354 | B16: PAYMENT | C16: 918735228 | D16: ONLINE PAYMENT THROUGH BANK | E16: 104800 | G16: =G15+F16-E16 -> 450000 | H16: =IF(G16=0,"NIL",IF(G16>0,"CR","DR")) -> CR
A17: 45355 | B17: PURCHASE | C17: BILL# 0513 | D17: HDD PURCHED | F17: 5200 | G17: =G16+F17-E17 -> 455200 | H17: =IF(G17=0,"NIL",IF(G17>0,"CR","DR")) -> CR
A18: 45364 | B18: PAYMENT | C18: 283496338 | D18: ONLINE PAYMENT THROUGH BANK | E18: 40500 | G18: =G17+F18-E18 -> 414700 | H18: =IF(G18=0,"NIL",IF(G18>0,"CR","DR")) -> CR
A19: 45367 | B19: PAYMENT | C19: CASH | D19: CASH BY HAND | E19: 60000 | G19: =G18+F19-E19 -> 354700 | H19: =IF(G19=0,"NIL",IF(G19>0,"CR","DR")) -> CR
A20: 45367 | B20: PURCHASE | C20: BILL# 0482 | D20: LED / SYSTEMS | F20: 260500 | G20: =G19+F20-E20 -> 615200 | H20: =IF(G20=0,"NIL",IF(G20>0,"CR","DR")) -> CR
A21: 45367 | B21: PURCHASE | C21: BILL# 0484 | D21: LED / SYSTEMS | F21: 37500 | G21: =G20+F21-E21 -> 652700 | H21: =IF(G21=0,"NIL",IF(G21>0,"CR","DR")) -> CR
A22: 45375 | B22: PAYMENT | C22: 907032174 | D22: ONLINE PAYMENT THROUGH BANK | E22: 52700 | G22: =G21+F22-E22 -> 600000 | H22: =IF(G22=0,"NIL",IF(G22>0,"CR","DR")) -> CR
A23: 45390 | B23: PAYMENT | C23: 907032174 | D23: ONLINE PAYMENT THROUGH BANK | E23: 100000 | G23: =G22+F23-E23 -> 500000 | H23: =IF(G23=0,"NIL",IF(G23>0,"CR","DR")) -> CR
A24: 45399 | B24: PAYMENT | C24: 907032174 | D24: ONLINE PAYMENT THROUGH BANK | E24: 30000 | G24: =G23+F24-E24 -> 470000 | H24: =IF(G24=0,"NIL",IF(G24>0,"CR","DR")) -> CR
A25: 45406 | B25: PURCHASE | C25: Bill#0752 | D25: HDD/ DDR 3 | F25: 17000 | G25: =G24+F25-E25 -> 487000 | H25: =IF(G25=0,"NIL",IF(G25>0,"CR","DR")) -> CR
A26: 45413 | B26: PAYMENT | C26: 907032174 | D26: ONLINE PAYMENT THROUGH BANK | E26: 80000 | G26: =G25+F26-E26 -> 407000 | H26: =IF(G26=0,"NIL",IF(G26>0,"CR","DR")) -> CR
A27: 45425 | B27: PAYMENT | C27: 957410210 | D27: ONLINE PAYMENT THROUGH BANK | E27: 57000 | G27: =G26+F27-E27 -> 350000 | H27: =IF(G27=0,"NIL",IF(G27>0,"CR","DR")) -> CR
A28: 45434 | B28: PAYMENT | C28: 907032174 | D28: ONLINE PAYMENT THROUGH BANK | E28: 55500 | G28: =G27+F28-E28 -> 294500 | H28: =IF(G28=0,"NIL",IF(G28>0,"CR","DR")) -> CR
A29: 45437 | B29: PURCHASE | C29: BILL# 1045 | D29: SSD 128GB QTY-5 | F29: 13500 | G29: =G28+F29-E29 -> 308000 | H29: =IF(G29=0,"NIL",IF(G29>0,"CR","DR")) -> CR
A30: 45443 | B30: PAYMENT | C30: 907032174 | D30: ONLINE PAYMENT THROUGH BANK | E30: 55000 | G30: =G29+F30-E30 -> 253000 | H30: =IF(G30=0,"NIL",IF(G30>0,"CR","DR")) -> CR
A31: 45455 | B31: PAYMENT | C31: 90528791 | D31: ONLINE PAYMENT THROUGH BANK | E31: 53000 | G31: =G30+F31-E31 -> 200000 | H31: =IF(G31=0,"NIL",IF(G31>0,"CR","DR")) -> CR
A32: 45474 | B32: PAYMENT | C32: 907032174 | D32: ONLINE PAYMENT THROUGH BANK | E32: 50000 | G32: =G31+F32-E32 -> 150000 | H32: =IF(G32=0,"NIL",IF(G32>0,"CR","DR")) -> CR
A33: 45485 | B33: PAYMENT | C33: 907032174 | D33: ONLINE PAYMENT THROUGH BANK | E33: 75000 | G33: =G32+F33-E33 -> 75000 | H33: =IF(G33=0,"NIL",IF(G33>0,"CR","DR")) -> CR
A34: 45493 | B34: PURCHASE | C34: BILL#1395 | D34: PURCHASING | F34: 72200 | G34: =G33+F34-E34 -> 147200 | H34: =IF(G34=0,"NIL",IF(G34>0,"CR","DR")) -> CR
A35: 45502 | B35: PAYMENT | C35: 907032174 | D35: ONLINE PAYMENT THROUGH BANK | E35: 27200 | G35: =G34+F35-E35 -> 120000 | H35: =IF(G35=0,"NIL",IF(G35>0,"CR","DR")) -> CR
D36: TOTAL BALANCE | E36: =SUM(E6:E35) -> 1266600 | F36: =SUM(F6:F35) -> 1386600 | G36: =G5+F36-E36 -> 120000 | H36: =IF(G36=0,"NIL",IF(G36>0,"CR","DR")) -> CR

Sheet  ZAFAR & SONS RWP 2
A1: TASNIM COMPUTERS SALES & SERVICE | J1: PAYABLE HOME
A2: ZAFAR & SONS RWP LEDGER
A3: FROM THE MONTH OF JANUARY 2024
A4: DATE | B4: TYPE | C4: REF# | D4: DESCRIPTION | E4: DEBIT | F4: CREDIT | G4: BALANCE
G5: =' ZAFAR & SONS RWP 1'!G36 -> 120000
A6: 45512 | B6: PAYMENT | D6: BOP ONLINE PAYMENT | E6: 60000 | F6: 0 | G6: =G5+F6-E6 -> 60000 | H6: =IF(G6=0,"NIL",IF(G6>0,"CR","DR")) -> CR
A7: 45514 | B7: PURCHASE | C7: BILL# 1739 | D7: PURCHASING FROM RWP | E7: 0 | F7: 140000 | G7: =G6+F7-E7 -> 200000 | H7: =IF(G7=0,"NIL",IF(G7>0,"CR","DR")) -> CR
A8: 45526 | B8: PAYMENT | C8: PAYMENT | D8: ONLINE BOP | E8: 40000 | G8: =G7+F8-E8 -> 160000 | H8: =IF(G8=0,"NIL",IF(G8>0,"CR","DR")) -> CR
A9: 45541 | B9: PAYMENT | C9: PAYMENT | D9: ONLINE BOP | E9: 50000 | G9: =G8+F9-E9 -> 110000 | H9: =IF(G9=0,"NIL",IF(G9>0,"CR","DR")) -> CR
A10: 45565 | B10: PAYMENT | C10: PAYMENT | D10: ONLINE BOP | E10: 50000 | G10: =G9+F10-E10 -> 60000 | H10: =IF(G10=0,"NIL",IF(G10>0,"CR","DR")) -> CR
A11: 45572 | B11: ADJUSTMENT | C11: PAYMENT | D11: HP Z40 V5 | E11: 42500 | G11: =G10+F11-E11 -> 17500 | H11: =IF(G11=0,"NIL",IF(G11>0,"CR","DR")) -> CR
A12: 45572 | B12: PURCHASE | C12: BILL#2068 | D12: PURCHASING FROM RWP | F12: =172300+14000 -> 186300 | G12: =G11+F12-E12 -> 203800 | H12: =IF(G12=0,"NIL",IF(G12>0,"CR","DR")) -> CR
A13: 45576 | B13: PAYMENT | C13: PAYMENT | D13: ONLINE BOP | E13: 30000 | G13: =G12+F13-E13 -> 173800 | H13: =IF(G13=0,"NIL",IF(G13>0,"CR","DR")) -> CR
A14: 45583 | B14: PAYMENT | C14: PAYMENT | D14: ONLINE BOP | E14: 23800 | G14: =G13+F14-E14 -> 150000 | H14: =IF(G14=0,"NIL",IF(G14>0,"CR","DR")) -> CR
A15: 45593 | B15: PURCHASE | C15: BILL#2122 | D15: PURCHASING FROM RWP | F15: 107200 | G15: =G14+F15-E15 -> 257200 | H15: =IF(G15=0,"NIL",IF(G15>0,"CR","DR")) -> CR
A16: 45593 | B16: PURCHASE | C16: BILL#2122 | D16: DDR 2 2GB | F16: 3200 | G16: =G15+F16-E16 -> 260400 | H16: =IF(G16=0,"NIL",IF(G16>0,"CR","DR")) -> CR
A17: 45594 | B17: PAYMENT | C17: PAYMENT | D17: ONLINE BOP | E17: 60400 | G17: =G16+F17-E17 -> 200000 | H17: =IF(G17=0,"NIL",IF(G17>0,"CR","DR")) -> CR
A18: 45602 | B18: PAYMENT | C18: PAYMENT | D18: ONLINE BOP | E18: 50000 | G18: =G17+F18-E18 -> 150000 | H18: =IF(G18=0,"NIL",IF(G18>0,"CR","DR")) -> CR
A19: 45611 | B19: PAYMENT | C19: PAYMENT | D19: ONLINE BOP | E19: 30000 | G19: =G18+F19-E19 -> 120000 | H19: =IF(G19=0,"NIL",IF(G19>0,"CR","DR")) -> CR
A20: 45612 | B20: PURCHASE | C20: BILL#2184 | D20: PURCHASING FROM RWP | F20: 41500 | G20: =G19+F20-E20 -> 161500 | H20: =IF(G20=0,"NIL",IF(G20>0,"CR","DR")) -> CR
A21: 45614 | B21: PAYMENT | C21: PAYMENT | D21: ONLINE BOP | E21: 51500 | G21: =G20+F21-E21 -> 110000 | H21: =IF(G21=0,"NIL",IF(G21>0,"CR","DR")) -> CR
A22: 45629 | B22: PURCHASE | C22: BILL# 2234 | D22: I5-6TH GEN 16GB 128 500GB | E22: 0 | F22: 37000 | G22: =G21+F22-E22 -> 147000 | H22: =IF(G22=0,"NIL",IF(G22>0,"CR","DR")) -> CR
A23: 45642 | B23: PAYMENT | C23: PAYMENT | D23: ONLINE BOP | E23: 50000 | G23: =G22+F23-E23 -> 97000 | H23: =IF(G23=0,"NIL",IF(G23>0,"CR","DR")) -> CR
A24: 45661 | B24: PURCHASE | C24: BILL#2328 | D24: PURCHASING FROM RWP | F24: 77100 | G24: =G23+F24-E24 -> 174100 | H24: =IF(G24=0,"NIL",IF(G24>0,"CR","DR")) -> CR
A25: 45661 | B25: PAYMENT | C25: PAYMENT | D25: ONLINE BOP | E25: 100000 | G25: =G24+F25-E25 -> 74100 | H25: =IF(G25=0,"NIL",IF(G25>0,"CR","DR")) -> CR
A26: 45681 | B26: PAYMENT | C26: PAYMENT | D26: ONLINE BOP | E26: 24100 | G26: =G25+F26-E26 -> 50000 | H26: =IF(G26=0,"NIL",IF(G26>0,"CR","DR")) -> CR
A27: 45687 | B27: PURCHASE | C27: BILL#2328 | D27: PURCHASING FROM RWP | F27: 25500 | G27: =G26+F27-E27 -> 75500 | H27: =IF(G27=0,"NIL",IF(G27>0,"CR","DR")) -> CR
A28: 45694 | C28: PAYMENT | D28: ONLINE BOP | E28: 30500 | G28: =G27+F28-E28 -> 45000 | H28: =IF(G28=0,"NIL",IF(G28>0,"CR","DR")) -> CR
A29: 45701 | B29: PURCHASE | C29: BILL#2454 | D29: PURCHASING FROM RWP | F29: 146200 | G29: =G28+F29-E29 -> 191200 | H29: =IF(G29=0,"NIL",IF(G29>0,"CR","DR")) -> CR
A30: 45732 | B30: PAYMENT | C30: PAYMENT | D30: ONLINE BOP | E30: 51200 | G30: =G29+F30-E30 -> 140000 | H30: =IF(G30=0,"NIL",IF(G30>0,"CR","DR")) -> CR
A31: 45744 | B31: PAYMENT | C31: PAYMENT | D31: ONLINE BOP | E31: 50000 | G31: =G30+F31-E31 -> 90000 | H31: =IF(G31=0,"NIL",IF(G31>0,"CR","DR")) -> CR
A32: 45759 | B32: PURCHASE | C32: BILL#2588 | D32: PURCHASING FROM RWP | F32: 121550 | G32: =G31+F32-E32 -> 211550 | H32: =IF(G32=0,"NIL",IF(G32>0,"CR","DR")) -> CR
A33: 45759 | B33: PURCHASE | C33: BILL#2509 | D33: PURCHASING FROM RWP | F33: 56700 | G33: =G32+F33-E33 -> 268250 | H33: =IF(G33=0,"NIL",IF(G33>0,"CR","DR")) -> CR
A34: 45763 | B34: PAYMENT | C34: PAYMENT | D34: ONLINE BOP | E34: 68250 | G34: =G33+F34-E34 -> 200000 | H34: =IF(G34=0,"NIL",IF(G34>0,"CR","DR")) -> CR
G35: =G34+F35-E35 -> 200000 | H35: =IF(G35=0,"NIL",IF(G35>0,"CR","DR")) -> CR
D36: TOTAL BALANCE | E36: =SUM(E6:E35) -> 862250 | F36: =SUM(F6:F35) -> 942250 | G36: =G5+F36-E36 -> 200000 | H36: =IF(G36=0,"NIL",IF(G36>0,"CR","DR")) -> CR

Sheet ZAFAR & SONS RWP 3 
A1: TASNIM COMPUTERS SALES & SERVICE | J1: PAYABLE HOME
A2: ZAFAR & SONS RWP LEDGER
A3: FROM THE MONTH OF JANUARY 2024
A4: DATE | B4: TYPE | C4: REF# | D4: DESCRIPTION | E4: DEBIT | F4: CREDIT | G4: BALANCE
G5: 200000
A6: 45769 | B6: PAYMENT | C6: PAYMENT | D6: BOP ONLINE PAYMENT | E6: 40000 | G6: =G5+F6-E6 -> 160000 | H6: =IF(G6=0,"NIL",IF(G6>0,"CR","DR")) -> CR
A7: 45787 | B7: PURCHASE | C7: BILL#2609 | D7: PURCHASING FROM RWP | F7: 11000 | G7: =G6+F7-E7 -> 171000 | H7: =IF(G7=0,"NIL",IF(G7>0,"CR","DR")) -> CR
A8: 45787 | B8: PURCHASE | C8: BILL#2633 | D8: PURCHASING FROM RWP | F8: 94100 | G8: =G7+F8-E8 -> 265100 | H8: =IF(G8=0,"NIL",IF(G8>0,"CR","DR")) -> CR
A9: 45787 | B9: PAYMENT | C9: PAYMENT | D9: BOP ONLINE PAYMENT | E9: 65100 | G9: =G8+F9-E9 -> 200000 | H9: =IF(G9=0,"NIL",IF(G9>0,"CR","DR")) -> CR
A10: 45797 | B10: PAYMENT | C10: PAYMENT | D10: BOP ONLINE PAYMENT | E10: 40000 | G10: =G9+F10-E10 -> 160000 | H10: =IF(G10=0,"NIL",IF(G10>0,"CR","DR")) -> CR
A11: 45800 | B11: PAYMENT | C11: PAYMENT | D11: BOP ONLINE PAYMENT | E11: 50000 | G11: =G10+F11-E11 -> 110000 | H11: =IF(G11=0,"NIL",IF(G11>0,"CR","DR")) -> CR
A12: 45802 | B12: PURCHASE | C12: BILL#2661 | D12: PURCHASING FROM RWP | F12: 191150 | G12: =G11+F12-E12 -> 301150 | H12: =IF(G12=0,"NIL",IF(G12>0,"CR","DR")) -> CR
A13: 45805 | B13: PAYMENT | C13: PAYMENT | D13: BOP ONLINE PAYMENT | E13: 31000 | G13: =G12+F13-E13 -> 270150 | H13: =IF(G13=0,"NIL",IF(G13>0,"CR","DR")) -> CR
A14: 45811 | B14: PAYMENT | C14: PAYMENT | D14: BOP ONLINE PAYMENT | E14: 30000 | G14: =G13+F14-E14 -> 240150 | H14: =IF(G14=0,"NIL",IF(G14>0,"CR","DR")) -> CR
A15: 45831 | B15: PURCHASE | C15: BILL#2671 | D15: PURCHASING FROM RWP | F15: 36500 | G15: =G14+F15-E15 -> 276650 | H15: =IF(G15=0,"NIL",IF(G15>0,"CR","DR")) -> CR
A16: 45832 | B16: PAYMENT | C16: PAYMENT | D16: BOP ONLINE PAYMENT | E16: 56650 | G16: =G15+F16-E16 -> 220000 | H16: =IF(G16=0,"NIL",IF(G16>0,"CR","DR")) -> CR
A17: 45838 | B17: PAYMENT | C17: PAYMENT | D17: BOP ONLINE PAYMENT | E17: 20000 | G17: =G16+F17-E17 -> 200000 | H17: =IF(G17=0,"NIL",IF(G17>0,"CR","DR")) -> CR
A18: 45839 | B18: PAYMENT | C18: PAYMENT | D18: PURCHASING FROM RWP | F18: 24500 | G18: =G17+F18-E18 -> 224500 | H18: =IF(G18=0,"NIL",IF(G18>0,"CR","DR")) -> CR
A19: 45846 | B19: PAYMENT | C19: PAYMENT | D19: BOP ONLINE PAYMENT | E19: 74500 | G19: =G18+F19-E19 -> 150000 | H19: =IF(G19=0,"NIL",IF(G19>0,"CR","DR")) -> CR
A20: 45846 | B20: PURCHASE | C20: Bill#2737 | D20: PURCHASING FROM RWP | F20: 11000 | G20: =G19+F20-E20 -> 161000 | H20: =IF(G20=0,"NIL",IF(G20>0,"CR","DR")) -> CR
A21: 45854 | B21: PAYMENT | C21: PAYMENT | D21: BOP ONLINE PAYMENT | E21: 20000 | G21: =G20+F21-E21 -> 141000 | H21: =IF(G21=0,"NIL",IF(G21>0,"CR","DR")) -> CR
A22: 45859 | B22: PURCHASE | C22: Bill#2701 | D22: PURCHASING FROM RWP | F22: 49000 | G22: =G21+F22-E22 -> 190000 | H22: =IF(G22=0,"NIL",IF(G22>0,"CR","DR")) -> CR
A23: 45859 | B23: PURCHASE | C23: PAYMENT | D23: BOP ONLINE PAYMENT | E23: 40000 | G23: =G22+F23-E23 -> 150000 | H23: =IF(G23=0,"NIL",IF(G23>0,"CR","DR")) -> CR
A24: 45861 | B24: PURCHASE | C24: BILL#2765 | D24: PURCHASING FROM RWP | F24: 217900 | G24: =G23+F24-E24 -> 367900 | H24: =IF(G24=0,"NIL",IF(G24>0,"CR","DR")) -> CR
A25: 45861 | B25: PURCHASE | C25: BILL2767 | D25: PURCHASING FROM RWP | F25: 34500 | G25: =G24+F25-E25 -> 402400 | H25: =IF(G25=0,"NIL",IF(G25>0,"CR","DR")) -> CR
A26: 45866 | B26: PAYMENT | C26: PAYMENT | D26: BOP ONLINE PAYMENT | E26: 52400 | G26: =G25+F26-E26 -> 350000 | H26: =IF(G26=0,"NIL",IF(G26>0,"CR","DR")) -> CR
A27: 45884 | B27: PAYMENT | C27: PAYMENT | D27: BOP ONLINE PAYMENT | E27: 50000 | G27: =G26+F27-E27 -> 300000 | H27: =IF(G27=0,"NIL",IF(G27>0,"CR","DR")) -> CR
A28: 45894 | B28: PAYMENT | C28: PAYMENT | D28: BOP ONLINE PAYMENT | E28: 30000 | G28: =G27+F28-E28 -> 270000 | H28: =IF(G28=0,"NIL",IF(G28>0,"CR","DR")) -> CR
A29: 45898 | B29: PAYMENT | C29: PAYMENT | D29: BOP ONLINE PAYMENT | E29: 40000 | G29: =G28+F29-E29 -> 230000 | H29: =IF(G29=0,"NIL",IF(G29>0,"CR","DR")) -> CR
A30: 45887 | B30: PURCHASE | C30: BILL2767 | D30: PURCHASING FROM RWP | F30: 26000 | G30: =G29+F30-E30 -> 256000 | H30: =IF(G30=0,"NIL",IF(G30>0,"CR","DR")) -> CR
A31: 45920 | B31: PAYMENT | C31: PAYMENT | D31: BOP ONLINE PAYMENT | E31: 106000 | G31: =G30+F31-E31 -> 150000 | H31: =IF(G31=0,"NIL",IF(G31>0,"CR","DR")) -> CR
A32: 45943 | B32: PURCHASE | C32: BILL#2919 | D32: PURCHASING FROM RWP | F32: 8000 | G32: =G31+F32-E32 -> 158000 | H32: =IF(G32=0,"NIL",IF(G32>0,"CR","DR")) -> CR
A33: 45943 | B33: PAYMENT | C33: PAYMENT | D33: BOP ONLINE PAYMENT | E33: 40000 | G33: =G32+F33-E33 -> 118000 | H33: =IF(G33=0,"NIL",IF(G33>0,"CR","DR")) -> CR
A34: 45949 | B34: PURCHASE | C34: BILL#3002 | D34: PURCHASING FROM RWP | F34: 116500 | G34: =G33+F34-E34 -> 234500 | H34: =IF(G34=0,"NIL",IF(G34>0,"CR","DR")) -> CR
A35: 45949 | B35: PURCHASE | C35: BILL#3003 | D35: PURCHASING FROM RWP | F35: 13400 | G35: =G34+F35-E35 -> 247900 | H35: =IF(G35=0,"NIL",IF(G35>0,"CR","DR")) -> CR
D36: TOTAL BALANCE | E36: =SUM(E6:E35) -> 785650 | F36: =SUM(F6:F35) -> 833550 | G36: =G5+F36-E36 -> 247900 | H36: =IF(G36=0,"NIL",IF(G36>0,"CR","DR")) -> CR

Sheet  ZAFAR & SONS RWP 4  
A1: TASNIM COMPUTERS SALES & SERVICE | J1: PAYABLE HOME
A2: ZAFAR & SONS RWP LEDGER
A3: FROM THE MONTH OF JANUARY 2024
A4: DATE | B4: TYPE | C4: REF# | D4: DESCRIPTION | E4: DEBIT | F4: CREDIT | G4: BALANCE
G5: ='ZAFAR & SONS RWP 3 '!G36 -> 247900
A6: 45952 | B6: PAYMENT | C6: PAYMENT | D6: BOP ONLINE PAYMENT | E6: 100000 | G6: =G5+F6-E6 -> 147900 | H6: =IF(G6=0,"NIL",IF(G6>0,"CR","DR")) -> CR
A7: 45955 | B7: RETURNE | C7: RETURNE | D7: I7 3RD K /8GB DDR 4 | E7: 12500 | G7: =G6+F7-E7 -> 135400 | H7: =IF(G7=0,"NIL",IF(G7>0,"CR","DR")) -> CR
A8: 45955 | B8: PAYMENT | C8: PAYMENT | D8: CASH PAYMENT | E8: 40000 | G8: =G7+F8-E8 -> 95400 | H8: =IF(G8=0,"NIL",IF(G8>0,"CR","DR")) -> CR
A9: 45958 | B9: PURCHASE | C9: BILL#3022 | D9: LED | F9: 57000 | G9: =G8+F9-E9 -> 152400 | H9: =IF(G9=0,"NIL",IF(G9>0,"CR","DR")) -> CR
A10: 45964 | B10: PURCHASE | C10: BILL#3022 | D10: HDD /RAM | F10: 44600 | G10: =G9+F10-E10 -> 197000 | H10: =IF(G10=0,"NIL",IF(G10>0,"CR","DR")) -> CR
A11: 45981 | B11: PAYMENT | C11: PAYMENT | D11: BOP ONLINE PAYMENT | E11: 50000 | G11: =G10+F11-E11 -> 147000 | H11: =IF(G11=0,"NIL",IF(G11>0,"CR","DR")) -> CR
A12: 45992 | B12: PAYMENT | C12: PAYMENT | D12: BOP ONLINE PAYMENT | E12: 50000 | G12: =G11+F12-E12 -> 97000 | H12: =IF(G12=0,"NIL",IF(G12>0,"CR","DR")) -> CR
A13: 45992 | B13: RETURNE | C13: RETURNE | D13: BILL BACK | E13: 4000 | G13: =G12+F13-E13 -> 93000 | H13: =IF(G13=0,"NIL",IF(G13>0,"CR","DR")) -> CR
A14: 45992 | B14: PURCHASE | C14: BILL#3023 | D14: PC PURCHASE | F14: 246050 | G14: =G13+F14-E14 -> 339050 | H14: =IF(G14=0,"NIL",IF(G14>0,"CR","DR")) -> CR
A15: 45993 | B15: PURCHASE | C15: BILL#3037 | D15: PC PURCHASE | F15: 40750 | G15: =G14+F15-E15 -> 379800 | H15: =IF(G15=0,"NIL",IF(G15>0,"CR","DR")) -> CR
A16: 46004 | B16: PAYMENT | C16: PAYMENT | D16: BOP ONLINE PAYMENT | E16: 50000 | G16: =G15+F16-E16 -> 329800 | H16: =IF(G16=0,"NIL",IF(G16>0,"CR","DR")) -> CR
A17: 46021 | B17: PAYMENT | C17: PAYMENT | D17: BOP ONLINE PAYMENT | E17: 30000 | G17: =G16+F17-E17 -> 299800 | H17: =IF(G17=0,"NIL",IF(G17>0,"CR","DR")) -> CR
A18: 45660 | B18: PURCHASE | C18: BILL#3023 | D18: PC PURCHASE | F18: 56900 | G18: =G17+F18-E18 -> 356700 | H18: =IF(G18=0,"NIL",IF(G18>0,"CR","DR")) -> CR
A19: 46036 | B19: PURCHASE | C19: BILL#3037 | D19: DELL 5050 BOX | F19: 12000 | G19: =G18+F19-E19 -> 368700 | H19: =IF(G19=0,"NIL",IF(G19>0,"CR","DR")) -> CR
A20: 46036 | B20: PAYMENT | C20: PAYMENT | D20: BOP ONLINE PAYMENT | E20: 50000 | G20: =G19+F20-E20 -> 318700 | H20: =IF(G20=0,"NIL",IF(G20>0,"CR","DR")) -> CR
A21: 45682 | B21: PURCHASE | D21: PROCESOR I5 3RD/DDR 3 4GB | F21: 5000 | G21: =G20+F21-E21 -> 323700 | H21: =IF(G21=0,"NIL",IF(G21>0,"CR","DR")) -> CR
A22: 46056 | B22: PAYMENT | C22: PAYMENT | D22: BOP ONLINE PAYMENT | E22: 55400 | G22: =G21+F22-E22 -> 268300 | H22: =IF(G22=0,"NIL",IF(G22>0,"CR","DR")) -> CR
A23: 46065 | B23: PURCHASE | C23: BILL3203 | D23: PC PURCHASE | F23: 116900 | G23: =G22+F23-E23 -> 385200 | H23: =IF(G23=0,"NIL",IF(G23>0,"CR","DR")) -> CR
A24: 46065 | B24: PURCHASE | C24: BILL3203 | D24: LED PURCHASE | F24: 111500 | G24: =G23+F24-E24 -> 496700 | H24: =IF(G24=0,"NIL",IF(G24>0,"CR","DR")) -> CR
A25: 46075 | B25: PAYMENT | C25: PAYMENT | D25: BOP ONLINE PAYMENT | E25: 50000 | G25: =G24+F25-E25 -> 446700 | H25: =IF(G25=0,"NIL",IF(G25>0,"CR","DR")) -> CR
A26: 46085 | B26: PAYMENT | C26: PAYMENT | D26: BOP ONLINE PAYMENT | E26: 30000 | G26: =G25+F26-E26 -> 416700 | H26: =IF(G26=0,"NIL",IF(G26>0,"CR","DR")) -> CR
A27: 46085 | B27: PAYMENT | C27: PAYMENT | D27: PC PURCHASE | F27: 79000 | G27: =G26+F27-E27 -> 495700 | H27: =IF(G27=0,"NIL",IF(G27>0,"CR","DR")) -> CR
A28: 46097 | B28: PAYMENT | C28: PAYMENT | D28: BOP ONLINE PAYMENT | E28: 95700 | G28: =G27+F28-E28 -> 400000 | H28: =IF(G28=0,"NIL",IF(G28>0,"CR","DR")) -> CR
A29: 46107 | B29: PAYMENT | C29: PAYMENT | D29: BOP ONLINE PAYMENT | E29: 50000 | G29: =G28+F29-E29 -> 350000 | H29: =IF(G29=0,"NIL",IF(G29>0,"CR","DR")) -> CR
A30: 46139 | B30: PURCHASE | C30: BILL#3296 | D30: PC PURCHASE | F30: 67800 | G30: =G29+F30-E30 -> 417800 | H30: =IF(G30=0,"NIL",IF(G30>0,"CR","DR")) -> CR
A31: 46161 | B31: PURCHASE | C31: BILL#3296 | D31: SSD PURCHASE | F31: 9000 | G31: =G30+F31-E31 -> 426800 | H31: =IF(G31=0,"NIL",IF(G31>0,"CR","DR")) -> CR
A32: 46161 | B32: PAYMENT | C32: PAYMENT | D32: BOP ONLINE PAYMENT | E32: 126800 | G32: =G31+F32-E32 -> 300000 | H32: =IF(G32=0,"NIL",IF(G32>0,"CR","DR")) -> CR
A33: 46179 | B33: PURCHASE | C33: BILL#3304 | D33: SSD PURCHASE | F33: 55600 | G33: =G32+F33-E33 -> 355600 | H33: =IF(G33=0,"NIL",IF(G33>0,"CR","DR")) -> CR
A34: 46189 | B34: PURCHASE | C34: BILL#3304 | D34: 24ich adjustment / dell mouse | F34: 17000 | G34: =G33+F34-E34 -> 372600 | H34: =IF(G34=0,"NIL",IF(G34>0,"CR","DR")) -> CR
A35: 46196 | B35: PAYMENT | C35: PAYMENT | D35: BOP ONLINE PAYMENT | E35: 35000 | G35: =G34+F35-E35 -> 337600 | H35: =IF(G35=0,"NIL",IF(G35>0,"CR","DR")) -> CR
D36: TOTAL BALANCE | E36: =SUM(E6:E35) -> 829400 | F36: =SUM(F6:F35) -> 919100 | G36: =G5+F36-E36 -> 337600 | H36: =IF(G36=0,"NIL",IF(G36>0,"CR","DR")) -> CR

Sheet  ZAFAR & SONS RWP 5 
A1: TASNIM COMPUTERS SALES & SERVICE | J1: PAYABLE HOME
A2: ZAFAR & SONS RWP LEDGER
A3: FROM THE MONTH OF JANUARY 2024
A4: DATE | B4: TYPE | C4: REF# | D4: DESCRIPTION | E4: DEBIT | F4: CREDIT | G4: BALANCE
G5: =' ZAFAR & SONS RWP 4 '!G36 -> 337600
A6: 46211 | B6: PAYMENT | C6: PAYMENT | D6: BOP ONLINE PAYMENT | E6: 50000 | G6: =G5+F6-E6 -> 287600 | H6: =IF(G6=0,"NIL",IF(G6>0,"CR","DR")) -> CR
A7: 46215 | B7: PURCHASE | C7: BILL#3451 | D7: DELL LED | F7: 103200 | G7: =G6+F7-E7 -> 390800 | H7: =IF(G7=0,"NIL",IF(G7>0,"CR","DR")) -> CR
A8: 46217 | B8: PAYMENT | C8: PAYMENT | D8: BOP ONLINE PAYMENT | E8: 140000 | G8: =G7+F8-E8 -> 250800 | H8: =IF(G8=0,"NIL",IF(G8>0,"CR","DR")) -> CR
A9: 46218 | B9: PURCHASE | C9: BILL#3468 | D9: graphic cards | F9: 32500 | G9: =G8+F9-E9 -> 283300 | H9: =IF(G9=0,"NIL",IF(G9>0,"CR","DR")) -> CR
A10: 46230 | B10: PAYMENT | C10: PAYMENT | D10: BOP ONLINE PAYMENT | E10: 40000 | G10: =G9+F10-E10 -> 243300 | H10: =IF(G10=0,"NIL",IF(G10>0,"CR","DR")) -> CR
A11: 46232 | B11: PURCHASE | C11: BILL#3502 | D11: DELL LED | F11: 147400 | G11: =G10+F11-E11 -> 390700 | H11: =IF(G11=0,"NIL",IF(G11>0,"CR","DR")) -> CR
A12: 46240 | B12: PAYMENT | C12: PAYMENT | D12: BOP ONLINE PAYMENT | E12: 50000 | G12: =G11+F12-E12 -> 340700 | H12: =IF(G12=0,"NIL",IF(G12>0,"CR","DR")) -> CR
A13: 46242 | B13: PURCHASE | C13: BILL#3515 | D13: LED /PC | F13: 29000 | G13: =G12+F13-E13 -> 369700 | H13: =IF(G13=0,"NIL",IF(G13>0,"CR","DR")) -> CR
A14: 46246 | B14: PAYMENT | C14: PAYMENT | D14: BOP ONLINE PAYMENT | E14: 30000 | G14: =G13+F14-E14 -> 339700 | H14: =IF(G14=0,"NIL",IF(G14>0,"CR","DR")) -> CR
A15: 46251 | B15: PURCHASE | C15: BILL#3539 | D15: graphic cards | F15: 22000 | G15: =G14+F15-E15 -> 361700 | H15: =IF(G15=0,"NIL",IF(G15>0,"CR","DR")) -> CR
G16: =G15+F16-E16 -> 361700 | H16: =IF(G16=0,"NIL",IF(G16>0,"CR","DR")) -> CR
G17: =G16+F17-E17 -> 361700 | H17: =IF(G17=0,"NIL",IF(G17>0,"CR","DR")) -> CR
G18: =G17+F18-E18 -> 361700 | H18: =IF(G18=0,"NIL",IF(G18>0,"CR","DR")) -> CR
G19: =G18+F19-E19 -> 361700 | H19: =IF(G19=0,"NIL",IF(G19>0,"CR","DR")) -> CR
G20: =G19+F20-E20 -> 361700 | H20: =IF(G20=0,"NIL",IF(G20>0,"CR","DR")) -> CR
G21: =G20+F21-E21 -> 361700 | H21: =IF(G21=0,"NIL",IF(G21>0,"CR","DR")) -> CR
G22: =G21+F22-E22 -> 361700 | H22: =IF(G22=0,"NIL",IF(G22>0,"CR","DR")) -> CR
G23: =G22+F23-E23 -> 361700 | H23: =IF(G23=0,"NIL",IF(G23>0,"CR","DR")) -> CR
G24: =G23+F24-E24 -> 361700 | H24: =IF(G24=0,"NIL",IF(G24>0,"CR","DR")) -> CR
G25: =G24+F25-E25 -> 361700 | H25: =IF(G25=0,"NIL",IF(G25>0,"CR","DR")) -> CR
G26: =G25+F26-E26 -> 361700 | H26: =IF(G26=0,"NIL",IF(G26>0,"CR","DR")) -> CR
G27: =G26+F27-E27 -> 361700 | H27: =IF(G27=0,"NIL",IF(G27>0,"CR","DR")) -> CR
... G35: =G34+F35-E35 -> 361700 | H35: =IF(G35=0,"NIL",IF(G35>0,"CR","DR")) -> CR
D36: TOTAL BALANCE | E36: =SUM(E6:E35) -> 310000 | F36: =SUM(F6:F35) -> 334100 | G36: =G5+F36-E36 -> 361700 | H36: =IF(G36=0,"NIL",IF(G36>0,"CR","DR")) -> CR

Sheet AL AZIZ-LHR-1
A1: TASNIM COMPUTERS SALES & SERVICE
A2: AL-AZIZ LAHORE LEDGER
A3: FROM THE MONTH OF JULY-2019
A4: DATE | B4: TYPE | C4: REF# | D4: DESCRIPTION | E4: DEBIT | F4: CREDIT | G4: BALANCE
A6: 43663 | B6: PURCHASE | C6: BILL# 158542 | D6: BATTERIES 2 | E6: 0 | F6: 5150 | G6: =G5+F6-E6 -> 5150 | H6: =IF(G6=0,"NIL",IF(G6>0,"CR","DR")) -> CR
A7: 43663 | B7: PURCHASE | C7: BILL# 158549 | D7: 14" LED SLIM (30PIN) | E7: 0 | F7: 5150 | G7: =G6+F7-E7 -> 10300 | H7: =IF(G7=0,"NIL",IF(G7>0,"CR","DR")) -> CR
A8: 43668 | B8: PAYMENT | C8: RECIEPT# 4880801 | D8: ONLINE PAYMENT THROUGH BANK | E8: 10300 | F8: 0 | G8: =G7+F8-E8 -> 0 | H8: =IF(G8=0,"NIL",IF(G8>0,"CR","DR")) -> NIL
A9: 43668 | B9: PURCHASE | C9: BILL# 159186 | D9: 15.6" LED | E9: 0 | F9: 5200 | G9: =G8+F9-E9 -> 5200 | H9: =IF(G9=0,"NIL",IF(G9>0,"CR","DR")) -> CR
A10: 43675 | B10: PAYMENT | C10: RECIEPT# 5258638 | D10: ONLINE PAYMENT THROUGH BANK | E10: 5200 | F10: 0 | G10: =G9+F10-E10 -> 0 | H10: =IF(G10=0,"NIL",IF(G10>0,"CR","DR")) -> NIL
A11: 43678 | B11: PURCHASE | C11: BILL# 160459 | D11: LAPTOP FAN QTY-2 | E11: 0 | F11: 1300 | G11: =G10+F11-E11 -> 1300 | H11: =IF(G11=0,"NIL",IF(G11>0,"CR","DR")) -> CR
A12: 43678 | B12: PURCHASE | C12: BILL# 160460 | D12: HP 6930P BATTERY QTY-1 | E12: 0 | F12: 1800 | G12: =G11+F12-E12 -> 3100 | H12: =IF(G12=0,"NIL",IF(G12>0,"CR","DR")) -> CR
A13: 43677 | B13: PURCHASE | C13: BILL# 160276 | D13: LAPTOP FAN QTY-2 | E13: 0 | F13: 1100 | G13: =G12+F13-E13 -> 4200 | H13: =IF(G13=0,"NIL",IF(G13>0,"CR","DR")) -> CR
A14: 43680 | B14: PURCHASE | C14: BILL# 160696 | D14: BATTERY HP 8460 | E14: 0 | F14: 1900 | G14: =G13+F14-E14 -> 6100 | H14: =IF(G14=0,"NIL",IF(G14>0,"CR","DR")) -> CR
A15: 43682 | B15: PURCHASE | C15: BILL# 160885 | D15: BATTERY DELL E3340 | E15: 0 | F15: 2600 | G15: =G14+F15-E15 -> 8700 | H15: =IF(G15=0,"NIL",IF(G15>0,"CR","DR")) -> CR
A16: 43685 | B16: PAYMENT | C16: RECIEPT# 8293214 | D16: ONLINE PAYMENT THROUGH BANK | E16: 8600 | F16: 0 | G16: =G15+F16-E16 -> 100 | H16: =IF(G16=0,"NIL",IF(G16>0,"CR","DR")) -> CR
A17: 43684 | B17: PURCHASE | C17: BILL# 161274 | D17: BATTERY DELL E3340 | E17: 0 | F17: 2600 | G17: =G16+F17-E17 -> 2700 | H17: =IF(G17=0,"NIL",IF(G17>0,"CR","DR")) -> CR
... A22: 43720 | B22: PURCHASE | C22: BILL# 165119 | D22: 15.6" LED HP PROBOOK | E22: 0 | F22: 5200 | G22: =G21+F22-E22 -> 5400 | H22: =IF(G22=0,"NIL",IF(G22>0,"CR","DR")) -> CR
A23: 43725 | B23: PAYMENT | C23: RECIEPT# 8295682 | D23: ONLINE PAYMENT THROUGH BANK | E23: 5300 | G23: =G22+F23-E23 -> 100 | H23: =IF(G23=0,"NIL",IF(G23>0,"CR","DR")) -> CR
A24: 43724 | B24: PURCHASE | C24: BILL# 165542 | D24: DELL 14" LED | E24: 0 | F24: 5400 | G24: =G23+F24-E24 -> 5500 | H24: =IF(G24=0,"NIL",IF(G24>0,"CR","DR")) -> CR
A25: 43725 | B25: PURCHASE | C25: BILL# 165744 | D25: HP BATTERY 440 | E25: 0 | F25: 1900 | G25: =G24+F25-E25 -> 7400 | H25: =IF(G25=0,"NIL",IF(G25>0,"CR","DR")) -> CR
A26: 43729 | B26: RETURN | C26: BILL# 165744 | D26: BETTERY HP 440 G3/RO04 RETURN | E26: 1900 | F26: 0 | G26: =G25+F26-E26 -> 5500 | H26: =IF(G26=0,"NIL",IF(G26>0,"CR","DR")) -> CR
A27: 43727 | B27: PURCHASE | C27: BILL# 166101 | D27: HP BATTERY 430 | E27: 0 | F27: 1900 | G27: =G26+F27-E27 -> 7400 | H27: =IF(G27=0,"NIL",IF(G27>0,"CR","DR")) -> CR
A28: 43729 | B28: PURCHASE | C28: BILL# 166310 | D28: 14" LED DELL | E28: 0 | F28: 5350 | G28: =G27+F28-E28 -> 12750 | H28: =IF(G28=0,"NIL",IF(G28>0,"CR","DR")) -> CR
A29: 43731 | B29: PAYMENT | C29: RECIEPT# 8295374 | D29: ONLINE PAYMENT THROUGH BANK | E29: 7300 | F29: 0 | G29: =G28+F29-E29 -> 5450 | H29: =IF(G29=0,"NIL",IF(G29>0,"CR","DR")) -> CR
A30: 43729 | B30: PURCHASE | C30: BILL# 166298 | D30: BATTERY HP | E30: 0 | F30: 1900 | G30: =G29+F30-E30 -> 7350 | H30: =IF(G30=0,"NIL",IF(G30>0,"CR","DR")) -> CR
A31: 43731 | B31: PURCHASE | C31: BILL# 166492 | D31: 15.6" LED DELL | E31: 0 | F31: 5400 | G31: =G30+F31-E31 -> 12750 | H31: =IF(G31=0,"NIL",IF(G31>0,"CR","DR")) -> CR
A32: 43738 | B32: PAYMENT | C32: RECIEPT# 8299915 | D32: ONLINE PAYMENT THROUGH BANK | E32: 12650 | F32: 0 | G32: =G31+F32-E32 -> 100 | H32: =IF(G32=0,"NIL",IF(G32>0,"CR","DR")) -> CR
A33: 43746 | B33: PURCHASE | C33: BILL# 168239 | D33: BATTERY DELL 4050 | E33: 0 | F33: 1900 | G33: =G32+F33-E33 -> 2000 | H33: =IF(G33=0,"NIL",IF(G33>0,"CR","DR")) -> CR
A34: 43750 | B34: PURCHASE | C34: BILL# 168458 | D34: KEYBOARD D4110 | E34: 0 | F34: 1000 | G34: =G33+F34-E34 -> 3000 | H34: =IF(G34=0,"NIL",IF(G34>0,"CR","DR")) -> CR
A35: 43752 | B35: PAYMENT | C35: RECIEPT# 8297390 | D35: ONLINE PAYMENT THROUGH BANK | E35: 2900 | F35: 0 | G35: =G34+F35-E35 -> 100 | H35: =IF(G35=0,"NIL",IF(G35>0,"CR","DR")) -> CR
D36: TOTAL BALANCE | E36: =SUM(E6:E35) -> 59950 | F36: =SUM(F6:F35) -> 60050 | G36: =G5+F36-E36 -> 100 | H36: =IF(G36=0,"NIL",IF(G36>0,"CR","DR")) -> CR

Sheet AL AZIZ-LHR-2
A1: TASNIM COMPUTERS SALES & SERVICE
A2: AL-AZIZ LAHORE LEDGER
A3: FROM THE MONTH OF JULY-2019
A4: DATE | B4: TYPE | C4: REF# | D4: DESCRIPTION | E4: DEBIT | F4: CREDIT | G4: BALANCE
D5: BALANCE B/F | G5: ='AL AZIZ-LHR-1'!G36 -> 100
A6: 43752 | B6: PURCHASE | C6: BILL# 169137 | D6: BATTERY LAPTOP | E6: 0 | F6: 1900 | G6: =G5+F6-E6 -> 2000 | H6: =IF(G6=0,"NIL",IF(G6>0,"CR","DR")) -> CR
A7: 43752 | B7: PURCHASE | C7: BILL# 169098 | D7: LED 15.6" SLIM | E7: 0 | F7: 5400 | G7: =G6+F7-E7 -> 7400 | H7: =IF(G7=0,"NIL",IF(G7>0,"CR","DR")) -> CR
A8: 43753 | B8: PURCHASE | C8: BILL# 169369 | D8: BATTERY LAPTOP | E8: 0 | F8: 1900 | G8: =G7+F8-E8 -> 9300 | H8: =IF(G8=0,"NIL",IF(G8>0,"CR","DR")) -> CR
A9: 43759 | B9: PAYMENT | C9: RECIEPT# 9469433 | D9: ONLINE PAYMENT THROUGH BANK | E9: 9200 | F9: 0 | G9: =G8+F9-E9 -> 100 | H9: =IF(G9=0,"NIL",IF(G9>0,"CR","DR")) -> CR
A10: 43759 | B10: PURCHASE | C10: BILL# 170120 | D10: 15.6" LED SLIM | E10: 0 | F10: 5400 | G10: =G9+F10-E10 -> 5500 | H10: =IF(G10=0,"NIL",IF(G10>0,"CR","DR")) -> CR
A11: 43760 | B11: PURCHASE | C11: BILL# 170341 | D11: BATTERY LAPTOP | E11: 0 | F11: 2200 | G11: =G10+F11-E11 -> 7700 | H11: =IF(G11=0,"NIL",IF(G11>0,"CR","DR")) -> CR
A12: 43765 | B12: RETURN | C12: RETURN BILL BAK | D12: BATTERY DELL LAPTOP BILL# 170341 | E12: 2100 | F12: 0 | G12: =G11+F12-E12 -> 5600 | H12: =IF(G12=0,"NIL",IF(G12>0,"CR","DR")) -> CR
A13: 43766 | B13: PAYMENT | C13: RECIEPT# 9468612 | D13: ONLINE PAYMENT THROUGH BANK | E13: 5400 | F13: 0 | G13: =G12+F13-E13 -> 200 | H13: =IF(G13=0,"NIL",IF(G13>0,"CR","DR")) -> CR
A14: 43771 | B14: PURCHASE | C14: BILL# 171423 | D14: DELL BATTRIES E6420 QTY-2 | E14: 0 | F14: 4400 | G14: =G13+F14-E14 -> 4600 | H14: =IF(G14=0,"NIL",IF(G14>0,"CR","DR")) -> CR
A15: 43774 | B15: PURCHASE | C15: BILL# 171700 | D15: BATTERY D3521 | E15: 0 | F15: 2250 | G15: =G14+F15-E15 -> 6850 | H15: =IF(G15=0,"NIL",IF(G15>0,"CR","DR")) -> CR
A16: 43787 | B16: PAYMENT | C16: RECIEPT# 5263075 | D16: ONLINE PAYMENT THROUGH BANK | E16: 6650 | F16: 0 | G16: =G15+F16-E16 -> 200 | H16: =IF(G16=0,"NIL",IF(G16>0,"CR","DR")) -> CR
A17: 43794 | B17: PURCHASE | C17: BILL# 173646 | D17: 14" LED SLIM | E17: 0 | F17: 6000 | G17: =G16+F17-E17 -> 6200 | H17: =IF(G17=0,"NIL",IF(G17>0,"CR","DR")) -> CR
... A35: 43939 | B35: PURCHASE | C35: BILL# 186379 | D35: 15.6" LED SLIM | E35: 0 | F35: 5750 | G35: =G34+F35-E35 -> 5750 | H35: =IF(G35=0,"NIL",IF(G35>0,"CR","DR")) -> CR
D36: TOTAL BALANCE | E36: =SUM(E6:E35) -> 55850 | F36: =SUM(F6:F35) -> 61500 | G36: =G5+F36-E36 -> 5750 | H36: =IF(G36=0,"NIL",IF(G36>0,"CR","DR")) -> CR

Sheet AL AZIZ-LHR-3
A1: TASNIM COMPUTERS SALES & SERVICE
A2: AL-AZIZ LAHORE LEDGER
A3: FROM THE MONTH OF JULY-2019
A4: DATE | B4: TYPE | C4: REF# | D4: DESCRIPTION | E4: DEBIT | F4: CREDIT | G4: BALANCE
D5: BALANCE B/F | G5: ='AL AZIZ-LHR-2'!G36 -> 5750
A6: 43944 | B6: PURCHASE | C6: BILL# 186427 | D6: HP BATTERY | E6: 0 | F6: 2250 | G6: =G5+F6-E6 -> 8000 | H6: =IF(G6=0,"NIL",IF(G6>0,"CR","DR")) -> CR
A7: 43949 | B7: PAYMENT | C7: RECIEPT#7671345 | D7: ONLINE PAYMENT THROUGH BANK | E7: 8000 | F7: 0 | G7: =G6+F7-E7 -> 0 | H7: =IF(G7=0,"NIL",IF(G7>0,"CR","DR")) -> NIL
A8: 43951 | B8: PURCHASE | C8: BILL# 186577 | D8: 15.6" LED & BATTERY HP | E8: 0 | F8: 7600 | G8: =G7+F8-E8 -> 7600 | H8: =IF(G8=0,"NIL",IF(G8>0,"CR","DR")) -> CR
A9: 43950 | B9: PURCHASE | C9: BILL# 186549 | D9: HP BATTERY | E9: 0 | F9: 2200 | G9: =G8+F9-E9 -> 9800 | H9: =IF(G9=0,"NIL",IF(G9>0,"CR","DR")) -> CR
A10: 43958 | B10: PURCHASE | C10: BILL# 186788 | D10: 14" LED SLIM | E10: 0 | F10: 5700 | G10: =G9+F10-E10 -> 15500 | H10: =IF(G10=0,"NIL",IF(G10>0,"CR","DR")) -> CR
A11: 43972 | B11: PURCHASE | C11: BILL# 187876 | D11: 15.6" LED SLIM | E11: 0 | F11: 5700 | G11: =G10+F11-E11 -> 21200 | H11: =IF(G11=0,"NIL",IF(G11>0,"CR","DR")) -> CR
A12: 43978 | B12: PURCHASE | C12: BILL# 188592 | D12: BATTERY AC 5742 | E12: 0 | F12: 2200 | G12: =G11+F12-E12 -> 23400 | H12: =IF(G12=0,"NIL",IF(G12>0,"CR","DR")) -> CR
A13: 43981 | B13: PURCHASE | C13: BILL# 188386 | D13: 14" LED SLIM & CABLE HP 8460 | E13: 0 | F13: 6600 | G13: =G12+F13-E13 -> 30000 | H13: =IF(G13=0,"NIL",IF(G13>0,"CR","DR")) -> CR
A14: 43984 | B14: PURCHASE | C14: BILL# 188808 | D14: DELL BATTERY 2 & HAIER KB | E14: 0 | F14: 8050 | G14: =G13+F14-E14 -> 38050 | H14: =IF(G14=0,"NIL",IF(G14>0,"CR","DR")) -> CR
A15: 43986 | B15: PAYMENT | C15: RECIEPT#8296579 | D15: ONLINE PAYMENT THROUGH BANK | E15: 38050 | F15: 0 | G15: =G14+F15-E15 -> 0 | H15: =IF(G15=0,"NIL",IF(G15>0,"CR","DR")) -> NIL
A16: 44012 | B16: PURCHASE | C16: BILL# 192752 | D16: BATTERY IBM G50-70 | E16: 0 | F16: 2100 | G16: =G15+F16-E16 -> 2100 | H16: =IF(G16=0,"NIL",IF(G16>0,"CR","DR")) -> CR
A17: 44013 | B17: PURCHASE | C17: BILL# 192821 | D17: BATTERY HP 8460 | E17: 0 | F17: 2200 | G17: =G16+F17-E17 -> 4300 | H17: =IF(G17=0,"NIL",IF(G17>0,"CR","DR")) -> CR
... A34: 44058 | B34: PAYMENT | C34: ID8477709510 | D34: ONLINE PAYMENT THROUGH EASY PAISA | E34: 18850 | F34: 0 | G34: =G33+F34-E34 -> 0 | H34: =IF(G34=0,"NIL",IF(G34>0,"CR","DR")) -> NIL
D35: BALANCE C/F | G35: =G34+F35-E35 -> 0 | H35: =IF(G35=0,"NIL",IF(G35>0,"CR","DR")) -> NIL
D36: TOTAL BALANCE | E36: =SUM(E6:E35) -> 101600 | F36: =SUM(F6:F35) -> 95850 | G36: =G5+F36-E36 -> 0 | H36: =IF(G36=0,"NIL",IF(G36>0,"CR","DR")) -> NIL

Sheet AL AZIZ-LHR-4
A1: TASNIM COMPUTERS SALES & SERVICE
A2: AL-AZIZ LAHORE LEDGER
A3: FROM THE MONTH OF JULY-2019
A4: DATE | B4: TYPE | C4: REF# | D4: DESCRIPTION | E4: DEBIT | F4: CREDIT | G4: BALANCE
D5: BALANCE B/F | G5: ='AL AZIZ-LHR-3'!G36 -> 0
A6: 44062 | B6: PURCHASE | C6: BILL# 199975 | D6: FAN HP 8560P | E6: 0 | F6: 700 | G6: =G5+F6-E6 -> 700 | H6: =IF(G6=0,"NIL",IF(G6>0,"CR","DR")) -> CR
A7: 44068 | B7: PAYMENT | C7: ID8594190507 | D7: PAYMENT MADE THROGH EASY PAISA | E7: 700 | G7: =G6+F7-E7 -> 0 | H7: =IF(G7=0,"NIL",IF(G7>0,"CR","DR")) -> NIL
A8: 44092 | B8: PURCHASE | C8: BILL# 204285 | D8: BATTERY HP 8460 | E8: 0 | F8: 2200 | G8: =G7+F8-E8 -> 2200 | H8: =IF(G8=0,"NIL",IF(G8>0,"CR","DR")) -> CR
A9: 44111 | B9: PURCHASE | C9: BILL# 206442 | D9: LED 15.6" | E9: 0 | F9: 7250 | G9: =G8+F9-E9 -> 9450 | H9: =IF(G9=0,"NIL",IF(G9>0,"CR","DR")) -> CR
A10: 44116 | B10: PAYMENT | C10: EASY PAISA | D10: PAYMENT MADE THROGH EASY PAISA | E10: 9450 | F10: 0 | G10: =G9+F10-E10 -> 0 | H10: =IF(G10=0,"NIL",IF(G10>0,"CR","DR")) -> NIL
A11: 44116 | B11: PURCHASE | C11: BILL# 206938 | D11: HINGIS HP | E11: 0 | F11: 700 | G11: =G10+F11-E11 -> 700 | H11: =IF(G11=0,"NIL",IF(G11>0,"CR","DR")) -> CR
A12: 44117 | B12: PURCHASE | C12: BILL# 207027 | D12: KB DELL 5440 | E12: 0 | F12: 1600 | G12: =G11+F12-E12 -> 2300 | H12: =IF(G12=0,"NIL",IF(G12>0,"CR","DR")) -> CR
A13: 44118 | B13: PURCHASE | C13: BILL# 207191 | D13: HIN HP, KB HP, KB DELL | F13: 4200 | G13: =G12+F13-E13 -> 6500 | H13: =IF(G13=0,"NIL",IF(G13>0,"CR","DR")) -> CR
A14: 44121 | B14: PURCHASE | C14: BILL# 207469 | D14: DELL 6440 DPANEL | E14: 0 | F14: 3200 | G14: =G13+F14-E14 -> 9700 | H14: =IF(G14=0,"NIL",IF(G14>0,"CR","DR")) -> CR
A15: 44124 | B15: PAYMENT | C15: ID9288028389 | D15: PAYMENT MADE THROGH EASY PAISA | E15: 9700 | F15: 0 | G15: =G14+F15-E15 -> 0 | H15: =IF(G15=0,"NIL",IF(G15>0,"CR","DR")) -> NIL
A16: 44126 | B16: PURCHASE | C16: BILL# 360 | D16: LED, BATTRIES | E16: 0 | F16: 16000 | G16: =G15+F16-E16 -> 16000 | H16: =IF(G16=0,"NIL",IF(G16>0,"CR","DR")) -> CR
A17: 44143 | B17: PAYMENT | C17: EASY PAISA | D17: PAYMENT MADE THROGH EASY PAISA | E17: 16000 | F17: 0 | G17: =G16+F17-E17 -> 0 | H17: =IF(G17=0,"NIL",IF(G17>0,"CR","DR")) -> NIL
A18: 44147 | B18: PURCHASE | C18: BILL# 209462 | D18: KEYBOARD DEL E6420 | E18: 0 | F18: 1500 | G18: =G17+F18-E18 -> 1500 | H18: =IF(G18=0,"NIL",IF(G18>0,"CR","DR")) -> CR
A19: 44147 | B19: RETURN | C19: PURCHASE RETRN | D19: KEYBOARD DELL E6420 BILL#209462 | E19: 1500 | F19: 0 | G19: =G18+F19-E19 -> 0 | H19: =IF(G19=0,"NIL",IF(G19>0,"CR","DR")) -> NIL
A20: 44152 | B20: PURCHASE | C20: BILL# 210047 | D20: KEYBOARD DELL E6420 | E20: 0 | F20: 1600 | G20: =G19+F20-E20 -> 1600 | H20: =IF(G20=0,"NIL",IF(G20>0,"CR","DR")) -> CR
A21: 44156 | B21: PAYMENT | C21: EASY PAISA | D21: PAYMENT MADE THROGH EASY PAISA | E21: 1600 | G21: =G20+F21-E21 -> 0 | H21: =IF(G21=0,"NIL",IF(G21>0,"CR","DR")) -> NIL
A22: 44159 | B22: PURCHASE | C22: BILL# 211029 | D22: BAT HP 440 G2 | E22: 0 | F22: 2450 | G22: =G21+F22-E22 -> 2450 | H22: =IF(G22=0,"NIL",IF(G22>0,"CR","DR")) -> CR
A23: 44167 | B23: PURCHASE | C23: BILL# 212437 | D23: KBHP, KB AC, BAT AC5742 | E23: 0 | F23: 4800 | G23: =G22+F23-E23 -> 7250 | H23: =IF(G23=0,"NIL",IF(G23>0,"CR","DR")) -> CR
A24: 44175 | B24: PAYMENT | C24: EASY PAISA | D24: PAYMENT MADE THROGH EASY PAISA | E24: 7250 | G24: =G23+F24-E24 -> 0 | H24: =IF(G24=0,"NIL",IF(G24>0,"CR","DR")) -> NIL
A25: 44179 | B25: PURCHASE | C25: BILL# 214399 | D25: 15.6" LED SLIM | E25: 0 | F25: 10250 | G25: =G24+F25-E25 -> 10250 | H25: =IF(G25=0,"NIL",IF(G25>0,"CR","DR")) -> CR
A26: 44180 | B26: PURCHASE | C26: BILL# 214621 | D26: BATTERY DE E6420 | E26: 0 | F26: 3000 | G26: =G25+F26-E26 -> 13250 | H26: =IF(G26=0,"NIL",IF(G26>0,"CR","DR")) -> CR
A27: 44183 | B27: PURCHASE | C27: BILL# 215117 | D27: KB HP & DELL | E27: 0 | F27: 2500 | G27: =G26+F27-E27 -> 15750 | H27: =IF(G27=0,"NIL",IF(G27>0,"CR","DR")) -> CR
A28: 44182 | B28: PURCHASE | C28: BILL# 214967 | D28: BAT HP 8460 | E28: 0 | F28: 2350 | G28: =G27+F28-E28 -> 18100 | H28: =IF(G28=0,"NIL",IF(G28>0,"CR","DR")) -> CR
A29: 44186 | B29: PAYMENT | C29: EASY PAISA | D29: PAYMENT MADE THROGH EASY PAISA | E29: 18100 | F29: 0 | G29: =G28+F29-E29 -> 0 | H29: =IF(G29=0,"NIL",IF(G29>0,"CR","DR")) -> NIL
A30: 44186 | B30: PURCHASE | C30: BILL#215570 | D30: BAT HP | E30: 0 | F30: 2300 | G30: =G29+F30-E30 -> 2300 | H30: =IF(G30=0,"NIL",IF(G30>0,"CR","DR")) -> CR
A31: 44189 | B31: PAYMENT | C31: EASY PAISA | D31: PAYMENT MADE THROGH EASY PAISA | E31: 2300 | F31: 0 | G31: =G30+F31-E31 -> 0 | H31: =IF(G31=0,"NIL",IF(G31>0,"CR","DR")) -> NIL
A32: 44193 | B32: PURCHASE | C32: BILL#216640 | D32: 15.6" LED SLIM(30 PIN) & BAT HP | E32: 0 | F32: 12550 | G32: =G31+F32-E32 -> 12550 | H32: =IF(G32=0,"NIL",IF(G32>0,"CR","DR")) -> CR
A33: 44194 | B33: PAYMENT | C33: ID10300378802 | D33: PAYMENT MADE THROGH EASY PAISA | E33: 12550 | G33: =G32+F33-E33 -> 0 | H33: =IF(G33=0,"NIL",IF(G33>0,"CR","DR")) -> NIL
A34: 44197 | B34: PURCHASE | C34: BILL# 217315 | D34: BAT HP 840 G1 | E34: 0 | F34: 3600 | G34: =G33+F34-E34 -> 3600 | H34: =IF(G34=0,"NIL",IF(G34>0,"CR","DR")) -> CR
A35: 43836 | B35: PAYMENT | C35: ID10415510064 | D35: PAYMENT MADE THROGH EASY PAISA | E35: 3600 | G35: =G34+F35-E35 -> 0 | H35: =IF(G35=0,"NIL",IF(G35>0,"CR","DR")) -> NIL
D36: TOTAL BALANCE | E36: =SUM(E6:E35) -> 82750 | F36: =SUM(F6:F35) -> 82750 | G36: =G5+F36-E36 -> 0 | H36: =IF(G36=0,"NIL",IF(G36>0,"CR","DR")) -> NIL

Sheet AL AZIZ-LHR-5
A1: TASNIM COMPUTERS SALES & SERVICE
A2: AL-AZIZ LAHORE LEDGER
A3: FROM THE MONTH OF JULY-2019
A4: DATE | B4: TYPE | C4: REF# | D4: DESCRIPTION | E4: DEBIT | F4: CREDIT | G4: BALANCE
D5: BALANCE B/F | G5: ='AL AZIZ-LHR-4'!G36 -> 0
A6: 44205 | B6: PURCHASE | C6: BILL# 218794 | D6: BAT DELL6420 & BAT HP 640 | E6: 0 | F6: 5150 | G6: =G5+F6-E6 -> 5150 | H6: =IF(G6=0,"NIL",IF(G6>0,"CR","DR")) -> CR
A7: 44208 | B7: PURCHASE | C7: BILL# 219394 | D7: BAT HP PAVILION, X360 | E7: 0 | F7: 8050 | G7: =G6+F7-E7 -> 13200 | H7: =IF(G7=0,"NIL",IF(G7>0,"CR","DR")) -> CR
A8: 44215 | B8: PAYMENT | C8: RECIPT# 8296587 | D8: ONLINE PAYMENT THROUGH BANK | E8: 13200 | F8: 0 | G8: =G7+F8-E8 -> 0 | H8: =IF(G8=0,"NIL",IF(G8>0,"CR","DR")) -> NIL
A9: 44217 | B9: PURCHASE | C9: BILL# 220483 | D9: BAT HP PAVILION, X360 & DELL | E9: 0 | F9: 6550 | G9: =G8+F9-E9 -> 6550 | H9: =IF(G9=0,"NIL",IF(G9>0,"CR","DR")) -> CR
A10: 44217 | B10: RETURN | C10: BILL# 219394 | D10: BAT HP PAVILION X360 BILL# 219394 RET | E10: 3500 | F10: 0 | G10: =G9+F10-E10 -> 3050 | H10: =IF(G10=0,"NIL",IF(G10>0,"CR","DR")) -> CR
A11: 44221 | B11: PURCHASE | C11: BILL# 221043 | D11: BAT DE E5540 | E11: 0 | F11: 3050 | G11: =G10+F11-E11 -> 6100 | H11: =IF(G11=0,"NIL",IF(G11>0,"CR","DR")) -> CR
A12: 44223 | B12: RETURN | C12: BILL# 220483 | D12: BAT DE E5540 RETURN TO LAHORE | E12: 2900 | F12: 0 | G12: =G11+F12-E12 -> 3200 | H12: =IF(G12=0,"NIL",IF(G12>0,"CR","DR")) -> CR
A13: 44184 | B13: PURCHASE | C13: BILL# 221840 | D13: KB TOSHIBA | E13: 0 | F13: 1300 | G13: =G12+F13-E13 -> 4500 | H13: =IF(G13=0,"NIL",IF(G13>0,"CR","DR")) -> CR
A14: 44228 | B14: PURCHASE | C14: BILL# 222183 | D14: BAT HP 840 G1 | E14: 0 | F14: 3650 | G14: =G13+F14-E14 -> 8150 | H14: =IF(G14=0,"NIL",IF(G14>0,"CR","DR")) -> CR
A15: 44231 | B15: PURCHASE | C15: BILL# 222925 | D15: BAT DE M4600 | E15: 0 | F15: 4600 | G15: =G14+F15-E15 -> 12750 | H15: =IF(G15=0,"NIL",IF(G15>0,"CR","DR")) -> CR
A16: 44237 | B16: PAYMENT | C16: RECIEPT# 8296589 | D16: ONLINE PAYMENT THROUGH BANK | E16: 12750 | F16: 0 | G16: =G15+F16-E16 -> 0 | H16: =IF(G16=0,"NIL",IF(G16>0,"CR","DR")) -> NIL
A17: 44239 | B17: PURCHASE | C17: BILL# 223561 | D17: BAT HP 6930 | E17: 0 | F17: 2350 | G17: =G16+F17-E17 -> 2350 | H17: =IF(G17=0,"NIL",IF(G17>0,"CR","DR")) -> CR
... A31: 44291 | B31: PURCHASE | C31: BILL# 230181 | D31: KB IBM G50-70 | E31: 0 | F31: 1300 | G31: =G30+F31-E31 -> 20950 | H31: =IF(G31=0,"NIL",IF(G31>0,"CR","DR")) -> CR
A32: 44292 | B32: PAYMENT | C32: RECEIPT# | D32: ONLINE PAYMENT THROUGH BANK | E32: 21000 | G32: =G31+F32-E32 -> -50 | H32: =IF(G32=0,"NIL",IF(G32>0,"CR","DR")) -> DR
A33: 44292 | B33: PURCHASE | C33: Bill#230351 | D33: KB D620 | F33: 1300 | G33: =G32+F33-E33 -> 1250 | H33: =IF(G33=0,"NIL",IF(G33>0,"CR","DR")) -> CR
A34: 44294 | B34: PURCHASE | C34: Bill#230695 | D34: BAT HP 440 G2 | F34: 3150 | G34: =G33+F34-E34 -> 4400 | H34: =IF(G34=0,"NIL",IF(G34>0,"CR","DR")) -> CR
A35: 44306 | B35: PURCHASE | C35: Bill#231770 | D35: HPKB PAVILION 15-BS | F35: 1300 | G35: =G34+F35-E35 -> 5700 | H35: =IF(G35=0,"NIL",IF(G35>0,"CR","DR")) -> CR
D36: TOTAL BALANCE | E36: =SUM(E6:E35) -> 75150 | F36: =SUM(F6:F35) -> 80850 | G36: =G5+F36-E36 -> 5700 | H36: =IF(G36=0,"NIL",IF(G36>0,"CR","DR")) -> CR

Sheet AL AZIZ-LHR-6
A1: TASNIM COMPUTERS SALES & SERVICE
A2: AL-AZIZ LAHORE LEDGER
A3: FROM THE MONTH OF JULY-2019
A4: DATE | B4: TYPE | C4: REF# | D4: DESCRIPTION | E4: DEBIT | F4: CREDIT | G4: BALANCE
D5: BALANCE B/F | G5: ='AL AZIZ-LHR-5'!G36 -> 5700
A6: 44307 | B6: PURCHASE | C6: BILL# 231915 | D6: FAN DELL E5430 | F6: 700 | G6: =G5+F6-E6 -> 6400 | H6: =IF(G6=0,"NIL",IF(G6>0,"CR","DR")) -> CR
A7: 44302 | B7: PURCHASE | C7: BILL# 231641 | D7: BAT D5010 | F7: 2950 | G7: =G6+F7-E7 -> 9350 | H7: =IF(G7=0,"NIL",IF(G7>0,"CR","DR")) -> CR
A8: 44309 | B8: PAYMENT | C8: RECEIPT#4887305 | D8: ONLINE PAYMENT THROUGH BANK | E8: 9350 | G8: =G7+F8-E8 -> 0 | H8: =IF(G8=0,"NIL",IF(G8>0,"CR","DR")) -> NIL
A9: 44313 | B9: PURCHASE | C9: BILL# 232631 | D9: BAT HP 640 | E9: 0 | F9: 2950 | G9: =G8+F9-E9 -> 2950 | H9: =IF(G9=0,"NIL",IF(G9>0,"CR","DR")) -> CR
A10: 44314 | B10: PURCHASE | C10: BILL# 232809 | D10: BAT HP 640 | E10: 0 | F10: 2800 | G10: =G9+F10-E10 -> 5750 | H10: =IF(G10=0,"NIL",IF(G10>0,"CR","DR")) -> CR
A11: 44321 | B11: PAYMENT | C11: RECEIPT# 0595147 | D11: ONLINE PAYMENT THROUGH BANK | E11: 5750 | F11: 0 | G11: =G10+F11-E11 -> 0 | H11: =IF(G11=0,"NIL",IF(G11>0,"CR","DR")) -> NIL
A12: 44336 | B12: PURCHASE | C12: BILL# 234534 | D12: KB DELL E4310 & HP 8460 HINGIS | E12: 0 | F12: 3000 | G12: =G11+F12-E12 -> 3000 | H12: =IF(G12=0,"NIL",IF(G12>0,"CR","DR")) -> CR
A13: 44341 | B13: PURCHASE | C13: BILL#234940 | D13: BAT HP PAVILION 14T | E13: 0 | F13: 2750 | G13: =G12+F13-E13 -> 5750 | H13: =IF(G13=0,"NIL",IF(G13>0,"CR","DR")) -> CR
A14: 44341 | B14: PURCHASE | C14: BILL#235301 | D14: DELLL BATERY | E14: 0 | F14: 2750 | G14: =G13+F14-E14 -> 8500 | H14: =IF(G14=0,"NIL",IF(G14>0,"CR","DR")) -> CR
A15: 44341 | B15: PURCHASE | C15: BILL#235449 | D15: BAT DE E7440 | E15: 0 | F15: 4150 | G15: =G14+F15-E15 -> 12650 | H15: =IF(G15=0,"NIL",IF(G15>0,"CR","DR")) -> CR
A16: 44343 | B16: PURCHASE | C16: BILL#235655 | D16: KB DE E4310 | E16: 0 | F16: 1600 | G16: =G15+F16-E16 -> 14250 | H16: =IF(G16=0,"NIL",IF(G16>0,"CR","DR")) -> CR
A17: 44347 | B17: PAYMENT | C17: BILL#235982 | D17: BAT HP 8460, BAT DE E7440 | E17: 0 | F17: 6750 | G17: =G16+F17-E17 -> 21000 | H17: =IF(G17=0,"NIL",IF(G17>0,"CR","DR")) -> CR
A18: 44347 | B18: PAYMENT | C18: RECEIPT#4887308 | D18: ONLINE PAYMENT THROUGH BANK | E18: 12650 | F18: 0 | G18: =G17+F18-E18 -> 8350 | H18: =IF(G18=0,"NIL",IF(G18>0,"CR","DR")) -> CR
A19: 44348 | B19: RETURN | C19: BILL# 234534 RETURN | D19: KD DELL E4310 RETURN TO LHR | E19: 1500 | F19: 0 | G19: =G18+F19-E19 -> 6850 | H19: =IF(G19=0,"NIL",IF(G19>0,"CR","DR")) -> CR
A20: 44348 | B20: RETURN | C20: BILL#235449 RETURN | D20: DELL 7440 BATTERY FAULTED RETURN | E20: 4150 | F20: 0 | G20: =G19+F20-E20 -> 2700 | H20: =IF(G20=0,"NIL",IF(G20>0,"CR","DR")) -> CR
A21: 44350 | B21: PURCHASE | C21: BILL# 236816 | D21: BAT HP 255 G4 | E21: 0 | F21: 2750 | G21: =G20+F21-E21 -> 5450 | H21: =IF(G21=0,"NIL",IF(G21>0,"CR","DR")) -> CR
A22: 44354 | B22: PAYMENT | C22: RECEIPT#4659292 | D22: ONLINE PAYMENT THROUGH BANK | E22: 5450 | G22: =G21+F22-E22 -> 0 | H22: =IF(G22=0,"NIL",IF(G22>0,"CR","DR")) -> NIL
A23: 44357 | B23: PURCHASE | C23: BILL# 237768 | D23: KB HP PAVILION 15 | E23: 0 | F23: 1200 | G23: =G22+F23-E23 -> 1200 | H23: =IF(G23=0,"NIL",IF(G23>0,"CR","DR")) -> CR
A24: 44362 | B24: PURCHASE | C24: BILL#237971 | D24: BAT HP 15-CX/SR03XL,BAT HP PAVILION 14T | F24: 7750 | G24: =G23+F24-E24 -> 8950 | H24: =IF(G24=0,"NIL",IF(G24>0,"CR","DR")) -> CR
A25: 44363 | B25: PAYMENT | C25: RECEIPT#4659291 | D25: ONLINE PAYMENT THROUGH BANK | E25: 8950 | F25: 0 | G25: =G24+F25-E25 -> 0 | H25: =IF(G25=0,"NIL",IF(G25>0,"CR","DR")) -> NIL
A26: 44364 | B26: RETURN | C26: BILL# 237768 RETURN | D26: KB HP PAVILION 15 RETURN TO LAHORE | E26: 1100 | F26: 0 | G26: =G25+F26-E26 -> -1100 | H26: =IF(G26=0,"NIL",IF(G26>0,"CR","DR")) -> DR
A27: 44364 | B27: RETURN | C27: BILL# 237971 RETURN | D27: BAT HP 15-CX/SR03XL RETURN TO LAHORE | E27: 5000 | F27: 0 | G27: =G26+F27-E27 -> -6100 | H27: =IF(G27=0,"NIL",IF(G27>0,"CR","DR")) -> DR
A28: 44383 | B28: PURCHASE | C28: BILL# 241324 | D28: BAT HP 640 | E28: 0 | F28: 2700 | G28: =G27+F28-E28 -> -3400 | H28: =IF(G28=0,"NIL",IF(G28>0,"CR","DR")) -> DR
A29: 44383 | B29: PURCHASE | C29: BILL# 241414 | D29: 15.6" SCREEN | E29: 0 | F29: =12450 -> 12450 | G29: =G28+F29-E29 -> 9050 | H29: =IF(G29=0,"NIL",IF(G29>0,"CR","DR")) -> CR
A30: 44393 | B30: PAYMENT | C30: RECEIPT# 4659287 | D30: ONLINE PAYMENT THROUGH BANK | E30: 9050 | G30: =G29+F30-E30 -> 0 | H30: =IF(G30=0,"NIL",IF(G30>0,"CR","DR")) -> NIL
A31: 44396 | B31: PURCHASE | C31: BILL# 243099 | D31: BAT TOSHIBA, KEYBOARD TOSHIBA | E31: 0 | F31: =3800 -> 3800 | G31: =G30+F31-E31 -> 3800 | H31: =IF(G31=0,"NIL",IF(G31>0,"CR","DR")) -> CR
A32: 44407 | B32: PAYMENT | C32: RECEIPT#4659285 | D32: ONLINE PAYMENT THROUGH BANK | E32: 3800 | G32: =G31+F32-E32 -> 0 | H32: =IF(G32=0,"NIL",IF(G32>0,"CR","DR")) -> NIL
A33: 44410 | B33: PURCHASE | C33: BILL# 244326 | D33: BAT DELL E6400 | E33: 0 | F33: 2500 | G33: =G32+F33-E33 -> 2500 | H33: =IF(G33=0,"NIL",IF(G33>0,"CR","DR")) -> CR
A34: 44413 | B34: PAYMENT | C34: RECEIPT#4887310 | D34: ONLINE PAYMENT THROUGH BANK | E34: 2500 | G34: =G33+F34-E34 -> 0 | H34: =IF(G34=0,"NIL",IF(G34>0,"CR","DR")) -> NIL
A35: 44435 | B35: PURCHASE | C35: BILL# 247735 | D35: BAT D3521, BAT D5010 | E35: 0 | F35: 5550 | G35: =G34+F35-E35 -> 5550 | H35: =IF(G35=0,"NIL",IF(G35>0,"CR","DR")) -> CR
D36: TOTAL BALANCE | E36: =SUM(E6:E35) -> 69250 | F36: =SUM(F6:F35) -> 69100 | G36: =G5+F36-E36 -> 5550 | H36: =IF(G36=0,"NIL",IF(G36>0,"CR","DR")) -> CR

Sheet AL AZIZ-LHR-7 
A1: TASNIM COMPUTERS SALES & SERVICE
A2: AL-AZIZ LAHORE LEDGER
A3: FROM THE MONTH OF JULY-2019
A4: DATE | B4: TYPE | C4: REF# | D4: DESCRIPTION | E4: DEBIT | F4: CREDIT | G4: BALANCE
D5: BALANCE B/F | G5: ='AL AZIZ-LHR-6'!G36 -> 5550
A6: 44442 | B6: PAYMENT | C6: RECIEPT# 4887313 | D6: ONLINE TRANSFER THROUGH BANK | E6: 5550 | G6: =G5+F6-E6 -> 0 | H6: =IF(G6=0,"NIL",IF(G6>0,"CR","DR")) -> NIL
A7: 44447 | B7: PURCHASE | C7: BILL# 249504 | D7: KB HP PAVILION 15 | E7: 0 | F7: 1200 | G7: =G6+F7-E7 -> 1200 | H7: =IF(G7=0,"NIL",IF(G7>0,"CR","DR")) -> CR
A8: 44455 | B8: PURCHASE | C8: BILL# 250934 | D8: KB HAIER 7G-5H | E8: 0 | F8: 2050 | G8: =G7+F8-E8 -> 3250 | H8: =IF(G8=0,"NIL",IF(G8>0,"CR","DR")) -> CR
A9: 20-09-2021 | B9: PAYMENT | C9: RECIEPT# 4887316 | D9: ONLINE TRANSFER THROUGH BANK | E9: 3250 | G9: =G8+F9-E9 -> 0 | H9: =IF(G9=0,"NIL",IF(G9>0,"CR","DR")) -> NIL
A10: 44461 | B10: PURCHASE | C10: BILL#251682 | D10: BAT D5010 | F10: 2400 | G10: =G9+F10-E10 -> 2400 | H10: =IF(G10=0,"NIL",IF(G10>0,"CR","DR")) -> CR
A11: 44463 | B11: PURCHASE | C11: BILL#252304 | D11: KB TOS C55-A | E11: 0 | F11: 1200 | G11: =G10+F11-E11 -> 3600 | H11: =IF(G11=0,"NIL",IF(G11>0,"CR","DR")) -> CR
A12: 44466 | B12: PURCHASE | C12: BILL#252697 | D12: 14" LED SLIM 30 PIN | E12: 0 | F12: 10600 | G12: =G11+F12-E12 -> 14200 | H12: =IF(G12=0,"NIL",IF(G12>0,"CR","DR")) -> CR
A13: 44468 | B13: PAYMENT | C13: RECEITP# 4887318 | D13: ONLINE TRANSFER THROUGH BANK | E13: 14200 | F13: 0 | G13: =G12+F13-E13 -> 0 | H13: =IF(G13=0,"NIL",IF(G13>0,"CR","DR")) -> NIL
A14: 44469 | B14: PURCHASE | C14: BILL#253193 | D14: KB HP 840 G1 | F14: 1600 | G14: =G13+F14-E14 -> 1600 | H14: =IF(G14=0,"NIL",IF(G14>0,"CR","DR")) -> CR
A15: 44296 | B15: PURCHASE | C15: BILL#253518 | D15: KB HP 8440p | F15: 1200 | G15: =G14+F15-E15 -> 2800 | H15: =IF(G15=0,"NIL",IF(G15>0,"CR","DR")) -> CR
A16: 44478 | B16: PAYMENT | C16: THROUGH EASYPAISA | D16: PAYMENT THROUGH EASY PAISA | E16: 2800 | G16: =G15+F16-E16 -> 0 | H16: =IF(G16=0,"NIL",IF(G16>0,"CR","DR")) -> NIL
A17: 44477 | B17: PURCHASE | C17: BILL# 254548 | D17: BAT DELL E7440 | E17: 0 | F17: 4100 | G17: =G16+F17-E17 -> 4100 | H17: =IF(G17=0,"NIL",IF(G17>0,"CR","DR")) -> CR
A18: 44478 | B18: PURCHASE | C18: BILL# 254705 | D18: BAT IBM IDEAPAD | E18: 0 | F18: 4100 | G18: =G17+F18-E18 -> 8200 | H18: =IF(G18=0,"NIL",IF(G18>0,"CR","DR")) -> CR
A19: 44483 | B19: PURCHASE | C19: BILL# 255485 | D19: BAT HP 640 | E19: 0 | F19: 2400 | G19: =G18+F19-E19 -> 10600 | H19: =IF(G19=0,"NIL",IF(G19>0,"CR","DR")) -> CR
A20: 44486 | B20: PAYMENT | C20: THROUGH EASYPAISA | D20: PAYMENT THROUGH EASY PAISA | E20: 10600 | F20: 0 | G20: =G19+F20-E20 -> 0 | H20: =IF(G20=0,"NIL",IF(G20>0,"CR","DR")) -> NIL
A21: 44490 | B21: PURCHASE | C21: BILL# 256272 | D21: 15.6" LED SLIM (30 PIN) | E21: 0 | F21: 12250 | G21: =G20+F21-E21 -> 12250 | H21: =IF(G21=0,"NIL",IF(G21>0,"CR","DR")) -> CR
A22: 44480 | B22: PAYMENT | C22: THROUGH EASYPAISA | D22: PAYMENT THROUGH EASY PAISA | E22: 12250 | G22: =G21+F22-E22 -> 0 | H22: =IF(G22=0,"NIL",IF(G22>0,"CR","DR")) -> NIL
A23: 44515 | B23: PURCHASE | C23: BILL# 259252 | D23: KB HAIER 7G-5H | E23: 0 | F23: 2300 | G23: =G22+F23-E23 -> 2300 | H23: =IF(G23=0,"NIL",IF(G23>0,"CR","DR")) -> CR
A24: 44522 | B24: PAYMENT | C24: THROUGH EASYPAISA | D24: PAYMENT THROUGH EASY PAISA | E24: 2300 | G24: =G23+F24-E24 -> 0 | H24: =IF(G24=0,"NIL",IF(G24>0,"CR","DR")) -> NIL
A25: 44544 | B25: PURCHASE | C25: BILL# 262996 | D25: KB IBM T440P | E25: 0 | F25: 3100 | G25: =G24+F25-E25 -> 3100 | H25: =IF(G25=0,"NIL",IF(G25>0,"CR","DR")) -> CR
A26: 44557 | B26: PURCHASE | C26: BILL# 264317 | D26: BAT DELL E6420 | E26: 0 | F26: 3150 | G26: =G25+F26-E26 -> 6250 | H26: =IF(G26=0,"NIL",IF(G26>0,"CR","DR")) -> CR
A27: 44558 | B27: PURCHASE | C27: BILL# 264538 | D27: KB HP | E27: 0 | F27: 1400 | G27: =G26+F27-E27 -> 7650 | H27: =IF(G27=0,"NIL",IF(G27>0,"CR","DR")) -> CR
A28: 44562 | B28: PURCHASE | C28: BILL# 265085 | D28: KBHP & BAT DELL D5010 | E28: 0 | F28: 3850 | G28: =G27+F28-E28 -> 11500 | H28: =IF(G28=0,"NIL",IF(G28>0,"CR","DR")) -> CR
A29: 44564 | B29: PURCHASE | C29: BILL# 265258 | D29: DELL PANNEL & HINGIS | E29: 0 | F29: 4450 | G29: =G28+F29-E29 -> 15950 | H29: =IF(G29=0,"NIL",IF(G29>0,"CR","DR")) -> CR
A30: 44566 | B30: PURCHASE | C30: BILL# 265615 | D30: DELL BATTERY | E30: 0 | F30: 2450 | G30: =G29+F30-E30 -> 18400 | H30: =IF(G30=0,"NIL",IF(G30>0,"CR","DR")) -> CR
A31: 44567 | B31: PAYMENT | C31: THROUGH EASYPAISA | D31: PAYMENT THROUGH EASY PAISA | E31: 18400 | F31: 0 | G31: =G30+F31-E31 -> 0 | H31: =IF(G31=0,"NIL",IF(G31>0,"CR","DR")) -> NIL
A32: 44571 | B32: PURCHASE | C32: BILL# 266104 | D32: 15.6" LED | E32: 0 | F32: 6200 | G32: =G31+F32-E32 -> 6200 | H32: =IF(G32=0,"NIL",IF(G32>0,"CR","DR")) -> CR
A33: 44571 | B33: RETURN | C33: LED RETURN | D33: LED RETURN | E33: 6200 | G33: =G32+F33-E33 -> 0 | H33: =IF(G33=0,"NIL",IF(G33>0,"CR","DR")) -> NIL
A34: 44581 | B34: PURCHASE | C34: BILL# 267543 | D34: BAT HP 640 | F34: 2450 | G34: =G33+F34-E34 -> 2450 | H34: =IF(G34=0,"NIL",IF(G34>0,"CR","DR")) -> CR
A35: 44581 | B35: RETURN | C35: HP KEYBOARD RETURN | D35: HP KEYBOARD RETURN | E35: 1400 | F35: 0 | G35: =G34+F35-E35 -> 1050 | H35: =IF(G35=0,"NIL",IF(G35>0,"CR","DR")) -> CR
D36: TOTAL BALANCE | E36: =SUM(E6:E35) -> 76950 | F36: =SUM(F6:F35) -> 72450 | G36: =G5+F36-E36 -> 1050 | H36: =IF(G36=0,"NIL",IF(G36>0,"CR","DR")) -> CR

Sheet AL AZIZ-LHR-8
A1: TASNIM COMPUTERS SALES & SERVICE
A2: AL-AZIZ LAHORE LEDGER
A3: FROM THE MONTH OF JULY-2019
A4: DATE | B4: TYPE | C4: REF# | D4: DESCRIPTION | E4: DEBIT | F4: CREDIT | G4: BALANCE
D5: BALANCE B/F | G5: ='AL AZIZ-LHR-7 '!G36 -> 1050
A6: 44581 | B6: RETURN | C6: RETURN | D6: RETURN BATTERY HP 640 | E6: 2450 | G6: =G5+F6-E6 -> -1400 | H6: =IF(G6=0,"NIL",IF(G6>0,"CR","DR")) -> DR
A7: 44585 | B7: PURCHASE | C7: BILL# 267943 | D7: KB DELL E7250 | E7: 0 | F7: 1600 | G7: =G6+F7-E7 -> 200 | H7: =IF(G7=0,"NIL",IF(G7>0,"CR","DR")) -> CR
A8: 44586 | B8: RETURN | C8: RETURN | D8: KB DELL E7250 | E8: 1600 | G8: =G7+F8-E8 -> -1400 | H8: =IF(G8=0,"NIL",IF(G8>0,"CR","DR")) -> DR
A9: 44586 | B9: PURCHASE | C9: BILL#268233 | D9: KB DELL E7250 | E9: 0 | F9: 1600 | G9: =G8+F9-E9 -> 200 | H9: =IF(G9=0,"NIL",IF(G9>0,"CR","DR")) -> CR
A10: 44600 | B10: PURCHASE | C10: BILL#270131 | D10: 14" LED SLIM 30PIN | E10: 0 | F10: 10750 | G10: =G9+F10-E10 -> 10950 | H10: =IF(G10=0,"NIL",IF(G10>0,"CR","DR")) -> CR
A11: 44600 | B11: PURCHASE | C11: BILL#270132 | D11: KB DELL E7250 | E11: 0 | F11: 1500 | G11: =G10+F11-E11 -> 12450 | H11: =IF(G11=0,"NIL",IF(G11>0,"CR","DR")) -> CR
A12: 44600 | B12: RETURN | C12: RETURN BILL#270132 | D12: KB DELL E7250 NOT WORKING RETURN | E12: 1500 | F12: 0 | G12: =G11+F12-E12 -> 10950 | H12: =IF(G12=0,"NIL",IF(G12>0,"CR","DR")) -> CR
A13: 44615 | B13: PAYMENT | C13: THROUGH EASYPAISA | D13: CASH INTO EASYPASY | E13: 10950 | G13: =G12+F13-E13 -> 0 | H13: =IF(G13=0,"NIL",IF(G13>0,"CR","DR")) -> NIL
A14: 44623 | B14: PURCHASE | C14: BILL# 273527 | D14: 15.6" LED SLIM | E14: 0 | F14: 12300 | G14: =G13+F14-E14 -> 12300 | H14: =IF(G14=0,"NIL",IF(G14>0,"CR","DR")) -> CR
A15: 44627 | B15: PAYMENT | C15: THROUGH EASYPAISA | D15: CASH PAID THROUGH EASYPAISA | E15: 12300 | F15: 0 | G15: =G14+F15-E15 -> 0 | H15: =IF(G15=0,"NIL",IF(G15>0,"CR","DR")) -> NIL
A16: 44642 | B16: PURCHASE | C16: BILL# 275855 | D16: BAT DELL XPS 13 9360/PW23Y | E16: 0 | F16: 6950 | G16: =G15+F16-E16 -> 6950 | H16: =IF(G16=0,"NIL",IF(G16>0,"CR","DR")) -> CR
A17: 44644 | B17: PAYMENT | C17: THROUGH EASYPAISA | D17: CASH PAID THROUGH EASYPAISA | E17: 6950 | F17: 0 | G17: =G16+F17-E17 -> 0 | H17: =IF(G17=0,"NIL",IF(G17>0,"CR","DR")) -> NIL
A18: 44645 | B18: PURCHASE | C18: BILL# 276174 | D18: KB DELL E5450 | E18: 0 | F18: 2600 | G18: =G17+F18-E18 -> 2600 | H18: =IF(G18=0,"NIL",IF(G18>0,"CR","DR")) -> CR
A19: 44646 | B19: PURCHASE | C19: BILL# 276241 | D19: BAT HP 2170 | E19: 0 | F19: 2450 | G19: =G18+F19-E19 -> 5050 | H19: =IF(G19=0,"NIL",IF(G19>0,"CR","DR")) -> CR
A20: 44655 | B20: PURCHASE | C20: BILL# 277254 | D20: BAT D1525 | E20: 0 | F20: 2400 | G20: =G19+F20-E20 -> 7450 | H20: =IF(G20=0,"NIL",IF(G20>0,"CR","DR")) -> CR
A21: 44655 | B21: PURCHASE | C21: BILL#277293 | D21: BAT HP / DELL /HP | F21: 8600 | G21: =G20+F21-E21 -> 16050 | H21: =IF(G21=0,"NIL",IF(G21>0,"CR","DR")) -> CR
A22: 44658 | B22: PURCHASE | C22: BILL#277475 | D22: KB DELL 7440 | E22: 0 | F22: 1600 | G22: =G21+F22-E22 -> 17650 | H22: =IF(G22=0,"NIL",IF(G22>0,"CR","DR")) -> CR
A23: 44659 | B23: PAYMENT | C23: THROUGH BANK APP | D23: CASH PAID THROUGH MOBILE APP BOP | E23: 17650 | F23: 0 | G23: =G22+F23-E23 -> 0 | H23: =IF(G23=0,"NIL",IF(G23>0,"CR","DR")) -> NIL
A24: 44659 | B24: PURCHASE | C24: BILL# 277668 | D24: BAT D1525 | E24: 0 | F24: 2450 | G24: =G23+F24-E24 -> 2450 | H24: =IF(G24=0,"NIL",IF(G24>0,"CR","DR")) -> CR
A25: 44660 | B25: PURCHASE | C25: BILL# 277691 | D25: KB D3521, BATD3521 | F25: 4350 | G25: =G24+F25-E25 -> 6800 | H25: =IF(G25=0,"NIL",IF(G25>0,"CR","DR")) -> CR
A26: 44665 | B26: PURCHASE | C26: BILL# 278127 | D26: BAT HP 240-G2, BAT ASUS K53E | F26: =4800 -> 4800 | G26: =G25+F26-E26 -> 11600 | H26: =IF(G26=0,"NIL",IF(G26>0,"CR","DR")) -> CR
A27: 44671 | B27: PURCHASE | C27: BILL# 278615 | D27: SPEAKERS HP 820 G1 | F27: 1500 | G27: =G26+F27-E27 -> 13100 | H27: =IF(G27=0,"NIL",IF(G27>0,"CR","DR")) -> CR
A28: 44672 | B28: PURCHASE | C28: BILL# 278731 | D28: KB HP SLEEKBOOK 15 | F28: =1400 -> 1400 | G28: =G27+F28-E28 -> 14500 | H28: =IF(G28=0,"NIL",IF(G28>0,"CR","DR")) -> CR
A29: 44674 | B29: PAYMENT | C29: THROUGH EASYPAISA | D29: CASH PAID THROUGH EASYPAISA | E29: 14500 | F29: 0 | G29: =G28+F29-E29 -> 0 | H29: =IF(G29=0,"NIL",IF(G29>0,"CR","DR")) -> NIL
A30: 44674 | B30: PURCHASE | C30: BILL# 278884 | D30: FAN HP DV6-6000 | E30: 0 | F30: 700 | G30: =G29+F30-E30 -> 700 | H30: =IF(G30=0,"NIL",IF(G30>0,"CR","DR")) -> CR
A31: 44680 | B31: PURCHASE | C31: BILL#279205 | D31: HP ELITEBOOK KB 8460P | E31: 0 | F31: 2500 | G31: =G30+F31-E31 -> 3200 | H31: =IF(G31=0,"NIL",IF(G31>0,"CR","DR")) -> CR
A32: 44688 | B32: PURCHASE | C32: BILL#279599 | D32: KB HP SLEEK | E32: 0 | F32: 2500 | G32: =G31+F32-E32 -> 5700 | H32: =IF(G32=0,"NIL",IF(G32>0,"CR","DR")) -> CR
A33: 44693 | C33: THROUGH BANK APP | D33: CASH PAID THROUGH MOBILE APP BOP | E33: 5700 | G33: =G32+F33-E33 -> 0 | H33: =IF(G33=0,"NIL",IF(G33>0,"CR","DR")) -> NIL
A34: 44730 | B34: PURCHASE | C34: BILL# 285470 | D34: 14" LED SLIM 30PIN | E34: 0 | F34: 10750 | G34: =G33+F34-E34 -> 10750 | H34: =IF(G34=0,"NIL",IF(G34>0,"CR","DR")) -> CR
A35: 44733 | B35: PURCHASE | C35: BILL# 285821 | D35: HP BATTERY 8460 | E35: 0 | F35: 2450 | G35: =G34+F35-E35 -> 13200 | H35: =IF(G35=0,"NIL",IF(G35>0,"CR","DR")) -> CR
D36: TOTAL BALANCE | E36: =SUM(E6:E35) -> 73600 | F36: =SUM(F6:F35) -> 85750 | G36: =G5+F36-E36 -> 13200 | H36: =IF(G36=0,"NIL",IF(G36>0,"CR","DR")) -> CR

Sheet AL AZIZ-LHR-9
A1: TASNIM COMPUTERS SALES & SERVICE
A2: AL-AZIZ LAHORE LEDGER
A3: FROM THE MONTH OF JULY-2019
A4: DATE | B4: TYPE | C4: REF# | D4: DESCRIPTION | E4: DEBIT | F4: CREDIT | G4: BALANCE
D5: BALANCE B/F | G5: ='AL AZIZ-LHR-8'!G36 -> 13200
A6: 44737 | B6: PURCHASE | C6: BILL# 286518 | D6: BAT DE E7440 | E6: 0 | F6: 4150 | G6: =G5+F6-E6 -> 17350 | H6: =IF(G6=0,"NIL",IF(G6>0,"CR","DR")) -> CR
A7: 44737 | B7: PURCHASE | C7: BILL# 286443 | D7: BAT HP 8460 | E7: 0 | F7: 2450 | G7: =G6+F7-E7 -> 19800 | H7: =IF(G7=0,"NIL",IF(G7>0,"CR","DR")) -> CR
A8: 44741 | B8: RETURN | C8: BILL# 285821 RETURN | D8: RETURN TO LAHORE BATTERY FAULTED | E8: 2450 | F8: 0 | G8: =G7+F8-E8 -> 17350 | H8: =IF(G8=0,"NIL",IF(G8>0,"CR","DR")) -> CR
A9: 44741 | B9: PURCHASE | C9: BILL#286963 | D9: KB HP PAVILION 15-AC/HP 8460P | F9: 2550 | G9: =G8+F9-E9 -> 19900 | H9: =IF(G9=0,"NIL",IF(G9>0,"CR","DR")) -> CR
A10: 44741 | B10: PURCHASE | C10: BILL#286996 | D10: KB DELL E6420 | F10: 2100 | G10: =G9+F10-E10 -> 22000 | H10: =IF(G10=0,"NIL",IF(G10>0,"CR","DR")) -> CR
A11: 44658 | B11: PURCHASE | C11: BILL#287406 | D11: HP KB 640 | F11: 1300 | G11: =G10+F11-E11 -> 23300 | H11: =IF(G11=0,"NIL",IF(G11>0,"CR","DR")) -> CR
A12: 44749 | B12: PAYMENT | C12: THROUGH BANK APP | D12: CASH PAID THROUGH MOBILE APP BOP | E12: 23300 | F12: 0 | G12: =G11+F12-E12 -> 0 | H12: =IF(G12=0,"NIL",IF(G12>0,"CR","DR")) -> NIL
A13: 44763 | B13: PURCHASE | C13: BILL#289576 | D13: BAT AC E5-573G | F13: 3650 | G13: =G12+F13-E13 -> 3650 | H13: =IF(G13=0,"NIL",IF(G13>0,"CR","DR")) -> CR
A14: 44765 | B14: PURCHASE | C14: BILL#290277 | D14: KB D3521 | F14: 1350 | G14: =G13+F14-E14 -> 5000 | H14: =IF(G14=0,"NIL",IF(G14>0,"CR","DR")) -> CR
A15: 44767 | B15: PURCHASE | C15: BILL#290309 | D15: HINGIGS DE E5530 | F15: 800 | G15: =G14+F15-E15 -> 5800 | H15: =IF(G15=0,"NIL",IF(G15>0,"CR","DR")) -> CR
A16: 44767 | B16: PURCHASE | C16: BILL#290787 | D16: KB IBM G50-70 | F16: 1350 | G16: =G15+F16-E16 -> 7150 | H16: =IF(G16=0,"NIL",IF(G16>0,"CR","DR")) -> CR
A17: 44769 | B17: PURCHASE | C17: BILL#290735 | D17: BAT DE E4300 | F17: 2800 | G17: =G16+F17-E17 -> 9950 | H17: =IF(G17=0,"NIL",IF(G17>0,"CR","DR")) -> CR
A18: 44776 | B18: PURCHASE | C18: BILL#292003 | D18: KB AC5755/HP 8460P | F18: 3750 | G18: =G17+F18-E18 -> 13700 | H18: =IF(G18=0,"NIL",IF(G18>0,"CR","DR")) -> CR
A19: 44777 | B19: PAYMENT | C19: THROUGH BANK APP | D19: CASH PAID THROUGH MOBILE APP BOP | E19: 13700 | G19: =G18+F19-E19 -> 0 | H19: =IF(G19=0,"NIL",IF(G19>0,"CR","DR")) -> NIL
A20: 44783 | B20: PURCHASE | C20: BILL# 292835 | D20: BAT DELL E6420 | E20: 0 | F20: 3500 | G20: =G19+F20-E20 -> 3500 | H20: =IF(G20=0,"NIL",IF(G20>0,"CR","DR")) -> CR
A21: 44791 | B21: PURCHASE | C21: BILL#294210 | D21: DELL KB E5520 | F21: 2150 | G21: =G20+F21-E21 -> 5650 | H21: =IF(G21=0,"NIL",IF(G21>0,"CR","DR")) -> CR
A22: 44793 | B22: PURCHASE | C22: BILL#294897 | D22: KB HP 6560B | F22: 2150 | G22: =G21+F22-E22 -> 7800 | H22: =IF(G22=0,"NIL",IF(G22>0,"CR","DR")) -> CR
A23: 44794 | B23: PAYMENT | C23: PAYMENT | D23: CASH PAID THROUGH MOBILE APP BOP | E23: 7800 | F23: 0 | G23: =G22+F23-E23 -> 0 | H23: =IF(G23=0,"NIL",IF(G23>0,"CR","DR")) -> NIL
A24: 44798 | B24: PURCHASE | C24: BILL#295340 | D24: KB D15-3542/HP 6560B/HAIER 7G-5H | F24: 6400 | G24: =G23+F24-E24 -> 6400 | H24: =IF(G24=0,"NIL",IF(G24>0,"CR","DR")) -> CR
A25: 44800 | B25: PURCHASE | C25: BILL#296103 | D25: BAT HP 440 G2 | E25: 0 | F25: 2800 | G25: =G24+F25-E25 -> 9200 | H25: =IF(G25=0,"NIL",IF(G25>0,"CR","DR")) -> CR
A26: 44801 | B26: PAYMENT | C26: PAYMENT | D26: CASH PAID THROUGH MOBILE APP BOP | E26: 9200 | G26: =G25+F26-E26 -> 0 | H26: =IF(G26=0,"NIL",IF(G26>0,"CR","DR")) -> NIL
A27: 44805 | B27: PURCHASE | C27: BILL# 296910 | D27: BAT HP 745-G3/CS03XL | E27: 0 | F27: 5200 | G27: =G26+F27-E27 -> 5200 | H27: =IF(G27=0,"NIL",IF(G27>0,"CR","DR")) -> CR
A28: 44813 | B28: PURCHASE | C28: BILL# 298184 | D28: BAT DE E7480 | E28: 0 | F28: 6200 | G28: =G27+F28-E28 -> 11400 | H28: =IF(G28=0,"NIL",IF(G28>0,"CR","DR")) -> CR
A29: 44816 | B29: PURCHASE | C29: BILL#298650 | D29: BAT HP G62 9 CELL | E29: 0 | F29: 3500 | G29: =G28+F29-E29 -> 14900 | H29: =IF(G29=0,"NIL",IF(G29>0,"CR","DR")) -> CR
A30: 44816 | B30: PURCHASE | C30: BILL#298552 | D30: BAT E6420/E5420 9 CELL | E30: 0 | F30: 4500 | G30: =G29+F30-E30 -> 19400 | H30: =IF(G30=0,"NIL",IF(G30>0,"CR","DR")) -> CR
A31: 44818 | B31: PURCHASE | C31: BILL#299061 | D31: BAT HP 6930/8440 | E31: 0 | F31: 2750 | G31: =G30+F31-E31 -> 22150 | H31: =IF(G31=0,"NIL",IF(G31>0,"CR","DR")) -> CR
A32: 44821 | B32: PURCHASE | C32: BILL#299177 | D32: BAT HP 640 | F32: 2750 | G32: =G31+F32-E32 -> 24900 | H32: =IF(G32=0,"NIL",IF(G32>0,"CR","DR")) -> CR
A33: 44820 | B33: PURCHASE | C33: BILL#299336 | D33: BAT HP 8460 | F33: 2800 | G33: =G32+F33-E33 -> 27700 | H33: =IF(G33=0,"NIL",IF(G33>0,"CR","DR")) -> CR
A34: 44818 | B34: PURCHASE | C34: BILL#298989 | D34: BAT HP 8460 | F34: 2800 | G34: =G33+F34-E34 -> 30500 | H34: =IF(G34=0,"NIL",IF(G34>0,"CR","DR")) -> CR
A35: 44823 | B35: PURCHASE | C35: BILL#299737 | D35: BAT HP 255 G4 | F35: 2800 | G35: =G34+F35-E35 -> 33300 | H35: =IF(G35=0,"NIL",IF(G35>0,"CR","DR")) -> CR
D36: TOTAL BALANCE | E36: =SUM(E6:E35) -> 56450 | F36: =SUM(F6:F35) -> 76550 | G36: =G5+F36-E36 -> 33300 | H36: =IF(G36=0,"NIL",IF(G36>0,"CR","DR")) -> CR

Sheet AL AZIZ-LHR-10 
A1: TASNIM COMPUTERS SALES & SERVICE
A2: AL-AZIZ LAHORE LEDGER
A3: FROM THE MONTH OF JULY-2019
A4: DATE | B4: TYPE | C4: REF# | D4: DESCRIPTION | E4: DEBIT | F4: CREDIT | G4: BALANCE
D5: BALANCE B/F | G5: ='AL AZIZ-LHR-9'!G36 -> 33300
A6: 44823 | B6: PURCHASE | C6: BILL# 299612 | D6: BAT HP FOLIO 1040 | F6: 7700 | G6: =G5+F6-E6 -> 41000 | H6: =IF(G6=0,"NIL",IF(G6>0,"CR","DR")) -> CR
A7: 44826 | B7: PAYMENT | C7: ONLINE PAYMENT | D7: CASH PAYMENT THROUGH BANK BOP | E7: 41000 | F7: 0 | G7: =G6+F7-E7 -> 0 | H7: =IF(G7=0,"NIL",IF(G7>0,"CR","DR")) -> NIL
A8: 44752 | B8: PURCHASE | C8: BILL#302374 | D8: HP KEYBORD G6 | F8: 1350 | G8: =G7+F8-E8 -> 1350 | H8: =IF(G8=0,"NIL",IF(G8>0,"CR","DR")) -> CR
A9: 44845 | B9: PURCHASE | C9: BILL#302723 | D9: HP KB / BAT 4530 | F9: 4300 | G9: =G8+F9-E9 -> 5650 | H9: =IF(G9=0,"NIL",IF(G9>0,"CR","DR")) -> CR
A10: 44847 | B10: PURCHASE | C10: BILL#303144 | D10: KB HP 840 G1/ BAT 8460 | F10: 5850 | G10: =G9+F10-E10 -> 11500 | H10: =IF(G10=0,"NIL",IF(G10>0,"CR","DR")) -> CR
A11: 44849 | B11: PURCHASE | C11: BILL#303556 | D11: BAT DE E6320 | F11: 3500 | G11: =G10+F11-E11 -> 15000 | H11: =IF(G11=0,"NIL",IF(G11>0,"CR","DR")) -> CR
A12: 44851 | B12: PAYMENT | C12: ONLINE PAYMENT | D12: CASH PAYMENT THROUGH BANK BOP | E12: 15000 | G12: =G11+F12-E12 -> 0 | H12: =IF(G12=0,"NIL",IF(G12>0,"CR","DR")) -> NIL
A13: 44852 | B13: PURCHASE | C13: BILL#303767 | D13: HP BAT 640 G1 | F13: 2800 | G13: =G12+F13-E13 -> 2800 | H13: =IF(G13=0,"NIL",IF(G13>0,"CR","DR")) -> CR
A14: 44853 | B14: PURCHASE | C14: BILL#303960 | D14: DELL BATT E7240 | F14: 5200 | G14: =G13+F14-E14 -> 8000 | H14: =IF(G14=0,"NIL",IF(G14>0,"CR","DR")) -> CR
A15: 44853 | B15: PURCHASE | C15: BILL#304203 | D15: BAT DE E6320 | F15: 3500 | G15: =G14+F15-E15 -> 11500 | H15: =IF(G15=0,"NIL",IF(G15>0,"CR","DR")) -> CR
A16: 44858 | B16: PURCHASE | C16: BILL#304659 | D16: BAT HP 8460 | F16: 2750 | G16: =G15+F16-E16 -> 14250 | H16: =IF(G16=0,"NIL",IF(G16>0,"CR","DR")) -> CR
A17: 44860 | B17: PAYMENT | C17: ONLINE PAYMENT | D17: CASH PAYMENT THROUGH BANK BOP | E17: 14250 | G17: =G16+F17-E17 -> 0 | H17: =IF(G17=0,"NIL",IF(G17>0,"CR","DR")) -> NIL
A18: 44861 | B18: PURCHASE | C18: BILL#304942 | D18: hp 1000 D panel | F18: 1750 | G18: =G17+F18-E18 -> 1750 | H18: =IF(G18=0,"NIL",IF(G18>0,"CR","DR")) -> CR
A19: 44875 | B19: PURCHASE | C19: BILL#306214 | D19: BAT HP 8460 / BAT DE E6320 | F19: 6000 | G19: =G18+F19-E19 -> 7750 | H19: =IF(G19=0,"NIL",IF(G19>0,"CR","DR")) -> CR
A20: 44875 | B20: PURCHASE | C20: BILL#305532 | D20: KB HP 840 G1 QTY-2 | F20: 3150 | G20: =G19+F20-E20 -> 10900 | H20: =IF(G20=0,"NIL",IF(G20>0,"CR","DR")) -> CR
A21: 44880 | B21: PURCHASE | C21: BILL#307174 | D21: BAT HP ENVY X360 15M/BAT HP 8460 | F21: 8300 | G21: =G20+F21-E21 -> 19200 | H21: =IF(G21=0,"NIL",IF(G21>0,"CR","DR")) -> CR
A22: 44886 | B22: PURCHASE | C22: BILL#307777 | D22: KB ACER 5755 | F22: 1350 | G22: =G21+F22-E22 -> 20550 | H22: =IF(G22=0,"NIL",IF(G22>0,"CR","DR")) -> CR
A23: 44900 | B23: PURCHASE | C23: BILL#309405 | D23: KB IBM T440P | F23: 3150 | G23: =G22+F23-E23 -> 23700 | H23: =IF(G23=0,"NIL",IF(G23>0,"CR","DR")) -> CR
A24: 44907 | B24: PAYMENT | C24: ONLINE PAYMENT | D24: CASH PAYMENT THROUGH BANK BOP | E24: 23700 | F24: 0 | G24: =G23+F24-E24 -> 0 | H24: =IF(G24=0,"NIL",IF(G24>0,"CR","DR")) -> NIL
A25: 44935 | B25: PURCHASE | C25: BILL#313707 | D25: KB HP PAVILION 15-AC | E25: 0 | F25: 1350 | G25: =G24+F25-E25 -> 1350 | H25: =IF(G25=0,"NIL",IF(G25>0,"CR","DR")) -> CR
A26: 44935 | B26: PURCHASE | C26: BILL#313760 | D26: BAT DE E3340 | E26: 0 | F26: 3450 | G26: =G25+F26-E26 -> 4800 | H26: =IF(G26=0,"NIL",IF(G26>0,"CR","DR")) -> CR
A27: 44939 | B27: PURCHASE | C27: BILL#314376 | D27: BAT HP EVNY 13-AD009NG/AD03XL | E27: 0 | F27: 6650 | G27: =G26+F27-E27 -> 11450 | H27: =IF(G27=0,"NIL",IF(G27>0,"CR","DR")) -> CR
A28: 44942 | B28: PURCHASE | C28: BILL#314741 | D28: BAT HP 15-CC/TF03XL | F28: 6150 | G28: =G27+F28-E28 -> 17600 | H28: =IF(G28=0,"NIL",IF(G28>0,"CR","DR")) -> CR
A29: 44942 | B29: PURCHASE | C29: BILL#314804 | D29: BAT D3521 / D1525 | F29: 6000 | G29: =G28+F29-E29 -> 23600 | H29: =IF(G29=0,"NIL",IF(G29>0,"CR","DR")) -> CR
A30: 44946 | B30: PAYMENT | C30: ONLINE PAYMENT | D30: CASH PAYMENT THROUGH BANK BOP | E30: 23600 | F30: 0 | G30: =G29+F30-E30 -> 0 | H30: =IF(G30=0,"NIL",IF(G30>0,"CR","DR")) -> NIL
A31: 44952 | B31: PURCHASE | C31: BILL#316214 | D31: Lenovo KB ibm x240 | F31: 3150 | G31: =G30+F31-E31 -> 3150 | H31: =IF(G31=0,"NIL",IF(G31>0,"CR","DR")) -> CR
A32: 44951 | B32: PURCHASE | C32: BILL#315967 | D32: KB lenovo T550,KB Haier 7g-5G | F32: 5350 | G32: =G31+F32-E32 -> 8500 | H32: =IF(G32=0,"NIL",IF(G32>0,"CR","DR")) -> CR
A33: 44959 | B33: PURCHASE | C33: BILL#317098 | D33: KB HP 450 G3/455 G3 | E33: 0 | F33: 1550 | G33: =G32+F33-E33 -> 10050 | H33: =IF(G33=0,"NIL",IF(G33>0,"CR","DR")) -> CR
A34: 44965 | B34: PURCHASE | C34: BILL# 317905 | D34: BAT DELL E5540 | E34: 0 | F34: 4200 | G34: =G33+F34-E34 -> 14250 | H34: =IF(G34=0,"NIL",IF(G34>0,"CR","DR")) -> CR
A35: 44972 | B35: PURCHASE | C35: Bill#318739 | D35: HP BAT 8460 | F35: 3500 | G35: =G34+F35-E35 -> 17750 | H35: =IF(G35=0,"NIL",IF(G35>0,"CR","DR")) -> CR
D36: TOTAL BALANCE | E36: =SUM(E6:E35) -> 117550 | F36: =SUM(F6:F35) -> 102000 | G36: =G5+F36-E36 -> 17750 | H36: =IF(G36=0,"NIL",IF(G36>0,"CR","DR")) -> CR

Sheet AL AZIZ-LHR-11
A1: TASNIM COMPUTERS SALES & SERVICE
A2: AL-AZIZ LAHORE LEDGER
A3: FROM THE MONTH OF JULY-2019
A4: DATE | B4: TYPE | C4: REF# | D4: DESCRIPTION | E4: DEBIT | F4: CREDIT | G4: BALANCE
D5: BALANCE B/F | G5: ='AL AZIZ-LHR-10 '!G36 -> 17750
A6: 44975 | B6: PAYMENT | C6: ONLINE PAYMENT | D6: CASH PAYMENT THROUGH BANK BOP | E6: 17750 | F6: 0 | G6: =G5+F6-E6 -> 0 | H6: =IF(G6=0,"NIL",IF(G6>0,"CR","DR")) -> NIL
A7: 44981 | B7: PURCHASE | C7: BILL# 320067 | D7: BAT D15-3551 | E7: 0 | F7: 4400 | G7: =G6+F7-E7 -> 4400 | H7: =IF(G7=0,"NIL",IF(G7>0,"CR","DR")) -> CR
A8: 44982 | B8: PURCHASE | C8: BILL#320276 | D8: DELL BAT HP 430 | F8: 3700 | G8: =G7+F8-E8 -> 8100 | H8: =IF(G8=0,"NIL",IF(G8>0,"CR","DR")) -> CR
A9: 44929 | B9: PURCHASE | C9: BILL#320584 | D9: BAT D5010 KB D4110 | F9: 5300 | G9: =G8+F9-E9 -> 13400 | H9: =IF(G9=0,"NIL",IF(G9>0,"CR","DR")) -> CR
A10: 44989 | B10: PURCHASE | C10: BILL#320975 | D10: BAT DELL E7240 | F10: 5600 | G10: =G9+F10-E10 -> 19000 | H10: =IF(G10=0,"NIL",IF(G10>0,"CR","DR")) -> CR
A11: 44989 | B11: PURCHASE | C11: BILL#320950 | D11: KB DELL E5450 | F11: 2650 | G11: =G10+F11-E11 -> 21650 | H11: =IF(G11=0,"NIL",IF(G11>0,"CR","DR")) -> CR
A12: 44993 | B12: PAYMENT | C12: ONLINE PAYMENT | D12: CASH PAYMENT THROUGH BANK ALHABIB | E12: 21650 | G12: =G11+F12-E12 -> 0 | H12: =IF(G12=0,"NIL",IF(G12>0,"CR","DR")) -> NIL
A13: 44996 | B13: PURCHASE | C13: BILL# 321795 | D13: KB HP G6 | E13: 0 | F13: 1800 | G13: =G12+F13-E13 -> 1800 | H13: =IF(G13=0,"NIL",IF(G13>0,"CR","DR")) -> CR
A14: 44996 | B14: PURCHASE | C14: BILL# 321813 | D14: DC JACK IBM G-5070 | E14: 0 | F14: 700 | G14: =G13+F14-E14 -> 2500 | H14: =IF(G14=0,"NIL",IF(G14>0,"CR","DR")) -> CR
A15: 44998 | B15: PURCHASE | C15: BILL# 321959 | D15: BAT IBM X240 | E15: 0 | F15: 5200 | G15: =G14+F15-E15 -> 7700 | H15: =IF(G15=0,"NIL",IF(G15>0,"CR","DR")) -> CR
A16: 44999 | B16: PURCHASE | C16: BILL#322101 | D16: KB HP G6 | E16: 0 | F16: 1750 | G16: =G15+F16-E16 -> 9450 | H16: =IF(G16=0,"NIL",IF(G16>0,"CR","DR")) -> CR
A17: 45000 | B17: PAYMENT | C17: ONLINE PAYMENT | D17: CASH PAYMENT THROUGH ABL | E17: 9450 | F17: 0 | G17: =G16+F17-E17 -> 0 | H17: =IF(G17=0,"NIL",IF(G17>0,"CR","DR")) -> NIL
A18: 45000 | B18: PURCHASE | C18: BILL#322253 | D18: BAT D5010 | F18: 3700 | G18: =G17+F18-E18 -> 3700 | H18: =IF(G18=0,"NIL",IF(G18>0,"CR","DR")) -> CR
A19: 45005 | B19: PAYMENT | C19: ONLINE PAYMENT | D19: CASH PAYMENT THROUGH ABL | E19: 3700 | G19: =G18+F19-E19 -> 0 | H19: =IF(G19=0,"NIL",IF(G19>0,"CR","DR")) -> NIL
A20: 45014 | B20: PURCHASE | C20: BILL#323577 | D20: BAT HP 4530 | F20: 3700 | G20: =G19+F20-E20 -> 3700 | H20: =IF(G20=0,"NIL",IF(G20>0,"CR","DR")) -> CR
A21: 45029 | B21: PAYMENT | C21: ONLINE PAYMENT | D21: ON LINE PAYMENT THROUGH ABL | E21: 3700 | F21: 0 | G21: =G20+F21-E21 -> 0 | H21: =IF(G21=0,"NIL",IF(G21>0,"CR","DR")) -> NIL
A22: 45063 | B22: PURCHASE | C22: BILL#13462 | D22: KEYBOARD 9470 | E22: 0 | F22: 1750 | G22: =G21+F22-E22 -> 1750 | H22: =IF(G22=0,"NIL",IF(G22>0,"CR","DR")) -> CR
A23: 45075 | B23: PURCHASE | C23: BILL#329477 | D23: BAT HP640 G3 | F23: 5700 | G23: =G22+F23-E23 -> 7450 | H23: =IF(G23=0,"NIL",IF(G23>0,"CR","DR")) -> CR
A24: 45083 | B24: PAYMENT | C24: ONLINE PAYMENT | D24: ON LINE PAYMENT THROUGH BOP | E24: 7450 | G24: =G23+F24-E24 -> 0 | H24: =IF(G24=0,"NIL",IF(G24>0,"CR","DR")) -> NIL
A25: 45090 | B25: PURCHASE | C25: BILL#331548 | D25: SCREEN 15.6 LED | E25: 0 | F25: 10300 | G25: =G24+F25-E25 -> 10300 | H25: =IF(G25=0,"NIL",IF(G25>0,"CR","DR")) -> CR
A26: 45090 | B26: PAYMENT | C26: ONLINE PAYMENT | D26: CASH PAYMENT THROUGH BOP | E26: 10000 | F26: 0 | G26: =G25+F26-E26 -> 300 | H26: =IF(G26=0,"NIL",IF(G26>0,"CR","DR")) -> CR
A27: 45096 | B27: PURCHASE | C27: BILL# 332356 | D27: BAT HP 840 G1 | E27: 0 | F27: 5700 | G27: =G26+F27-E27 -> 6000 | H27: =IF(G27=0,"NIL",IF(G27>0,"CR","DR")) -> CR
A28: 45104 | B28: PAYMENT | C28: ONLINE PAYMENT | D28: CASH PAYMENT THROUGH BOP | E28: 6000 | F28: 0 | G28: =G27+F28-E28 -> 0 | H28: =IF(G28=0,"NIL",IF(G28>0,"CR","DR")) -> NIL
A29: 45114 | B29: PURCHASE | C29: BILL# 334222 | D29: KB D3521 | F29: 1750 | G29: =G28+F29-E29 -> 1750 | H29: =IF(G29=0,"NIL",IF(G29>0,"CR","DR")) -> CR
A30: 45116 | B30: PAYMENT | C30: ONLINE PAYMENT | D30: CASH PAYMENT THROUGH BOP | E30: 1750 | G30: =G29+F30-E30 -> 0 | H30: =IF(G30=0,"NIL",IF(G30>0,"CR","DR")) -> NIL
A31: 45121 | B31: PURCHASE | C31: BILL# 3335405 | D31: BAT D3521 | E31: 0 | F31: 4550 | G31: =G30+F31-E31 -> 4550 | H31: =IF(G31=0,"NIL",IF(G31>0,"CR","DR")) -> CR
A32: 45131 | B32: PURCHASE | C32: BILL#336869 | D32: KB LENOVO X240 | F32: 4650 | G32: =G31+F32-E32 -> 9200 | H32: =IF(G32=0,"NIL",IF(G32>0,"CR","DR")) -> CR
A33: 45146 | B33: PURCHASE | C33: BILL#339250 | D33: HP BAT 6510 | F33: 3700 | G33: =G32+F33-E33 -> 12900 | H33: =IF(G33=0,"NIL",IF(G33>0,"CR","DR")) -> CR
A34: 45153 | B34: PAYMENT | C34: ONLINE PAYMENT | D34: CASH PAYMENT THROUGH BOP | E34: 12900 | G34: =G33+F34-E34 -> 0 | H34: =IF(G34=0,"NIL",IF(G34>0,"CR","DR")) -> NIL
A35: 45154 | B35: PURCHASE | C35: BILL#340353 | D35: BAT/HP BAT/DELL KB | F35: 9800 | G35: =G34+F35-E35 -> 9800 | H35: =IF(G35=0,"NIL",IF(G35>0,"CR","DR")) -> CR
D36: TOTAL BALANCE | E36: =SUM(E6:E35) -> 94350 | F36: =SUM(F6:F35) -> 86400 | G36: =G5+F36-E36 -> 9800 | H36: =IF(G36=0,"NIL",IF(G36>0,"CR","DR")) -> CR

Sheet AL AZIZ-LHR-12
A1: TASNIM COMPUTERS SALES & SERVICE
A2: AL-AZIZ LAHORE LEDGER
A3: FROM THE MONTH OF JULY-2019
A4: DATE | B4: TYPE | C4: REF# | D4: DESCRIPTION | E4: DEBIT | F4: CREDIT | G4: BALANCE
D5: BALANCE B/F | G5: ='AL AZIZ-LHR-11'!G36 -> 9800
A6: 45159 | B6: PURCHASE | C6: BILL# 341114 | D6: BAT HP 450/LED15.6"/15.6" | F6: 23800 | G6: =G5+F6-E6 -> 33600 | H6: =IF(G6=0,"NIL",IF(G6>0,"CR","DR")) -> CR
A7: 45168 | B7: PAYMENT | C7: PAYMENT | D7: CASH PAYMENT THROUGH BOP | E7: 33600 | G7: =G6+F7-E7 -> 0 | H7: =IF(G7=0,"NIL",IF(G7>0,"CR","DR")) -> NIL
A8: 45182 | B8: PURCHASE | C8: BILL#344716 | D8: BATDELL E6420/E5420 | F8: 4600 | G8: =G7+F8-E8 -> 4600 | H8: =IF(G8=0,"NIL",IF(G8>0,"CR","DR")) -> CR
A9: 45188 | B9: PURCHASE | C9: BILL#345709 | D9: KB IBM T410 | F9: 4650 | G9: =G8+F9-E9 -> 9250 | H9: =IF(G9=0,"NIL",IF(G9>0,"CR","DR")) -> CR
A10: 45200 | B10: PAYMENT | C10: ONLINE PAYMENT | D10: CASH PAYMENT THROUGH BOP | E10: 9250 | G10: =G9+F10-E10 -> 0 | H10: =IF(G10=0,"NIL",IF(G10>0,"CR","DR")) -> NIL
A11: 45213 | B11: PURCHASE | C11: BILL#349451 | D11: BAT HP 640 G1 | F11: 3650 | G11: =G10+F11-E11 -> 3650 | H11: =IF(G11=0,"NIL",IF(G11>0,"CR","DR")) -> CR
A12: 45215 | B12: PURCHASE | C12: BILL#349750 | D12: BAT TOS 5185 | F12: 3650 | G12: =G11+F12-E12 -> 7300 | H12: =IF(G12=0,"NIL",IF(G12>0,"CR","DR")) -> CR
A13: 45215 | B13: PURCHASE | C13: BILL#349669 | D13: BAT DELL D5010 | F13: 3700 | G13: =G12+F13-E13 -> 11000 | H13: =IF(G13=0,"NIL",IF(G13>0,"CR","DR")) -> CR
A14: 45223 | B14: PURCHASE | C14: BILL#350914 | D14: SPK DELL E6530 | F14: 1150 | G14: =G13+F14-E14 -> 12150 | H14: =IF(G14=0,"NIL",IF(G14>0,"CR","DR")) -> CR
A15: 45229 | B15: PURCHASE | C15: BILL#351579 | D15: KB D4110 | F15: 1750 | G15: =G14+F15-E15 -> 13900 | H15: =IF(G15=0,"NIL",IF(G15>0,"CR","DR")) -> CR
A16: 45243 | B16: PURCHASE | C16: BILL#353131 | D16: BAT DELL E6400 | F16: 3650 | G16: =G15+F16-E16 -> 17550 | H16: =IF(G16=0,"NIL",IF(G16>0,"CR","DR")) -> CR
A17: 45245 | B17: PURCHASE | C17: BILL#353508 | D17: KB HP 9470 | F17: 1850 | G17: =G16+F17-E17 -> 19400 | H17: =IF(G17=0,"NIL",IF(G17>0,"CR","DR")) -> CR
A18: 45251 | B18: PAYMENT | C18: PAYMENT | D18: CASH PAYMENT THROUGH BOP | E18: 19400 | G18: =G17+F18-E18 -> 0 | H18: =IF(G18=0,"NIL",IF(G18>0,"CR","DR")) -> NIL
A19: 45253 | B19: PURCHASE | C19: BILL# 354437 | D19: KB D4110 | E19: 0 | F19: 1750 | G19: =G18+F19-E19 -> 1750 | H19: =IF(G19=0,"NIL",IF(G19>0,"CR","DR")) -> CR
A20: 45257 | B20: PURCHASE | C20: BILL#354800 | D20: BAT HP NC2400 | F20: 3700 | G20: =G19+F20-E20 -> 5450 | H20: =IF(G20=0,"NIL",IF(G20>0,"CR","DR")) -> CR
A21: 45271 | B21: PAYMENT | C21: PAYMENT | D21: CASH PAYMENT THROUGH BOP | E21: 5450 | G21: =G20+F21-E21 -> 0 | H21: =IF(G21=0,"NIL",IF(G21>0,"CR","DR")) -> NIL
A22: 45273 | B22: PURCHASE | C22: BILL# 356907 | D22: HIN HP 450 G3 | E22: 0 | F22: 1650 | G22: =G21+F22-E22 -> 1650 | H22: =IF(G22=0,"NIL",IF(G22>0,"CR","DR")) -> CR
A23: 45274 | B23: PURCHASE | C23: BILL# 357062 | D23: KB HP 840 G1 | E23: 0 | F23: 2850 | G23: =G22+F23-E23 -> 4500 | H23: =IF(G23=0,"NIL",IF(G23>0,"CR","DR")) -> CR | I23: 2700
A24: 45275 | B24: PURCHASE | C24: BILL# 357185 | D24: KB HP 840 G1 | E24: 0 | F24: 2850 | G24: =G23+F24-E24 -> 7350 | H24: =IF(G24=0,"NIL",IF(G24>0,"CR","DR")) -> CR
A25: 45287 | B25: PURCHASE | C25: BILL#358484 | D25: KB D15-3542 | E25: 0 | F25: 1650 | G25: =G24+F25-E25 -> 9000 | H25: =IF(G25=0,"NIL",IF(G25>0,"CR","DR")) -> CR
A26: 45288 | B26: PURCHASE | C26: BILL#358578 | D26: BAT D15-5568/WDXOR | E26: 0 | F26: 6000 | G26: =G25+F26-E26 -> 15000 | H26: =IF(G26=0,"NIL",IF(G26>0,"CR","DR")) -> CR
A27: 45289 | B27: PURCHASE | C27: BILL#358707 | D27: KB HP 4540 | E27: 0 | F27: 1850 | G27: =G26+F27-E27 -> 16850 | H27: =IF(G27=0,"NIL",IF(G27>0,"CR","DR")) -> CR
A28: 45293 | B28: PURCHASE | C28: BILL#359149 | D28: BAT DE E6320 | E28: 0 | F28: 4550 | G28: =G27+F28-E28 -> 21400 | H28: =IF(G28=0,"NIL",IF(G28>0,"CR","DR")) -> CR
A29: 45299 | B29: PURCHASE | C29: BILL#359388 | D29: KB IBM T440p | F29: 4650 | G29: =G28+F29-E29 -> 26050 | H29: =IF(G29=0,"NIL",IF(G29>0,"CR","DR")) -> CR
A30: 45299 | B30: PURCHASE | C30: BILL#359956 | D30: KB HP G6 | F30: 1650 | G30: =G29+F30-E30 -> 27700 | H30: =IF(G30=0,"NIL",IF(G30>0,"CR","DR")) -> CR
A31: 45310 | B31: PURCHASE | C31: BILL#361556 | D31: KB AC E5-573 | F31: 1750 | G31: =G30+F31-E31 -> 29450 | H31: =IF(G31=0,"NIL",IF(G31>0,"CR","DR")) -> CR | I31: 1600
A32: 45313 | B32: PURCHASE | C32: Bill#361947 | D32: KB SAMSUNG R540 | F32: 1850 | G32: =G31+F32-E32 -> 31300 | H32: =IF(G32=0,"NIL",IF(G32>0,"CR","DR")) -> CR
A33: 45313 | B33: PURCHASE | C33: BILL#361847 | D33: HIN DE E5440 | F33: 950 | G33: =G32+F33-E33 -> 32250 | H33: =IF(G33=0,"NIL",IF(G33>0,"CR","DR")) -> CR
A34: 45320 | B34: PAYMENT | C34: PAYMENT | D34: CASH PAYMENT THROUGH BOP | E34: 27700 | G34: =G33+F34-E34 -> 4550 | H34: =IF(G34=0,"NIL",IF(G34>0,"CR","DR")) -> CR
A35: 45322 | B35: PURCHASE | C35: BILL#363149 | D35: BAT HP 15-DA0033WNHT XL | F35: 6650 | G35: =G34+F35-E35 -> 11200 | H35: =IF(G35=0,"NIL",IF(G35>0,"CR","DR")) -> CR
D36: TOTAL BALANCE | E36: =SUM(E6:E35) -> 95400 | F36: =SUM(F6:F35) -> 96800 | G36: =G5+F36-E36 -> 11200 | H36: =IF(G36=0,"NIL",IF(G36>0,"CR","DR")) -> CR

Sheet AL AZIZ-LHR-13
A1: TASNIM COMPUTERS SALES & SERVICE | J1: PAYABLE HOME
A2: AL-AZIZ LAHORE LEDGER
A3: FROM THE MONTH OF JULY-2019
A4: DATE | B4: TYPE | C4: REF# | D4: DESCRIPTION | E4: DEBIT | F4: CREDIT | G4: BALANCE
D5: BALANCE B/F | G5: ='AL AZIZ-LHR-12'!G36 -> 11200
A6: 45338 | B6: PURCHASE | C6: BILL#364750 | D6: BAT IBM LENOVO 310 | F6: 5150 | G6: =G5+F6-E6 -> 16350 | H6: =IF(G6=0,"NIL",IF(G6>0,"CR","DR")) -> CR
A7: 45341 | B7: PURCHASE | C7: BILL#365174 | D7: FAN 840 G1/KB HP 840 G3 | F7: 3850 | G7: =G6+F7-E7 -> 20200 | H7: =IF(G7=0,"NIL",IF(G7>0,"CR","DR")) -> CR
A8: 45342 | B8: PURCHASE | C8: BILL#365397 | D8: KB HP 8460P | F8: 3150 | G8: =G7+F8-E8 -> 23350 | H8: =IF(G8=0,"NIL",IF(G8>0,"CR","DR")) -> CR
A9: 45350 | B9: PURCHASE | C9: BILL#366340 | D9: BAT D15-5547 | F9: 5650 | G9: =G8+F9-E9 -> 29000 | H9: =IF(G9=0,"NIL",IF(G9>0,"CR","DR")) -> CR
A10: 45352 | B10: PURCHASE | C10: BILL#366574 | D10: BAT HP 440 G2 | F10: 3650 | G10: =G9+F10-E10 -> 32650 | H10: =IF(G10=0,"NIL",IF(G10>0,"CR","DR")) -> CR
A11: 45356 | B11: PURCHASE | C11: BILL#367056 | D11: BAT IBM LENOVO D50-70 | F11: 3650 | G11: =G10+F11-E11 -> 36300 | H11: =IF(G11=0,"NIL",IF(G11>0,"CR","DR")) -> CR
A12: 45325 | B12: RETURN | C12: 33590 | D12: BAT DE E6320 | E12: 4400 | G12: =G11+F12-E12 -> 31900 | H12: =IF(G12=0,"NIL",IF(G12>0,"CR","DR")) -> CR
A13: 45325 | B13: RETURN | C13: 33590 | D13: KB AC E5-573 | E13: 1600 | G13: =G12+F13-E13 -> 30300 | H13: =IF(G13=0,"NIL",IF(G13>0,"CR","DR")) -> CR
A14: 45361 | B14: PURCHASE | C14: BILL#367651 | D14: KB HP 840 G3 | F14: 7150 | G14: =G13+F14-E14 -> 37450 | H14: =IF(G14=0,"NIL",IF(G14>0,"CR","DR")) -> CR
A15: 45367 | B15: PURCHASE | C15: BILL#368210 | D15: KB HP 450 G1 | F15: 1650 | G15: =G14+F15-E15 -> 39100 | H15: =IF(G15=0,"NIL",IF(G15>0,"CR","DR")) -> CR
A16: 45369 | B16: PAYMENT | C16: PAYMENT | D16: CASH PAYMENT THROUGH BOP | E16: 30000 | G16: =G15+F16-E16 -> 9100 | H16: =IF(G16=0,"NIL",IF(G16>0,"CR","DR")) -> CR
A17: 45376 | B17: PURCHASE | C17: BILL#368881 | D17: KB HP 450 G1 | F17: 1650 | G17: =G16+F17-E17 -> 10750 | H17: =IF(G17=0,"NIL",IF(G17>0,"CR","DR")) -> CR
A18: 45381 | B18: PURCHASE | C18: BILL#369430 | D18: BAT D3521 | F18: 4600 | G18: =G17+F18-E18 -> 15350 | H18: =IF(G18=0,"NIL",IF(G18>0,"CR","DR")) -> CR
A19: 45386 | B19: PURCHASE | C19: BILL#369933 | D19: BAT TOS 5024 | F19: 3700 | G19: =G18+F19-E19 -> 19050 | H19: =IF(G19=0,"NIL",IF(G19>0,"CR","DR")) -> CR
A20: 45413 | B20: PURCHASE | C20: BILL#372016 | D20: DELL SCREEN 1080/KB DE E5450 | F20: 15800 | G20: =G19+F20-E20 -> 34850 | H20: =IF(G20=0,"NIL",IF(G20>0,"CR","DR")) -> CR
A21: 45415 | B21: PURCHASE | C21: BILL#372094 | D21: HP 4540S BATTERY | F21: 3700 | G21: =G20+F21-E21 -> 38550 | H21: =IF(G21=0,"NIL",IF(G21>0,"CR","DR")) -> CR
A22: 45418 | B22: PAYMENT | C22: PAYMENT | D22: CASH PAYMENT THROUGH BOP | E22: 15800 | G22: =G21+F22-E22 -> 22750 | H22: =IF(G22=0,"NIL",IF(G22>0,"CR","DR")) -> CR
A23: 45422 | B23: PURCHASE | C23: BILL#373000 | D23: HP 8460 14"screen | F23: 9300 | G23: =G22+F23-E23 -> 32050 | H23: =IF(G23=0,"NIL",IF(G23>0,"CR","DR")) -> CR
A24: Return | B24: Return | C24: Return | D24: BAT IBM LENOVO 310 | E24: 5000 | G24: =G23+F24-E24 -> 27050 | H24: =IF(G24=0,"NIL",IF(G24>0,"CR","DR")) -> CR
A25: Return | B25: Return | C25: Return | D25: KB HP 450 G1 | E25: 1500 | G25: =G24+F25-E25 -> 25550 | H25: =IF(G25=0,"NIL",IF(G25>0,"CR","DR")) -> CR
A26: 45426 | B26: PURCHASE | C26: BILL#373382 | D26: DELL KB D4110 | F26: 1650 | G26: =G25+F26-E26 -> 27200 | H26: =IF(G26=0,"NIL",IF(G26>0,"CR","DR")) -> CR
A27: 45428 | B27: PURCHASE | C27: BILL#373562 | D27: BAT DE E6420/E5420 | F27: 4550 | G27: =G26+F27-E27 -> 31750 | H27: =IF(G27=0,"NIL",IF(G27>0,"CR","DR")) -> CR
A28: 45432 | B28: PURCHASE | C28: BILL#374005 | D28: BAT HP 255 G4 | F28: 3650 | G28: =G27+F28-E28 -> 35400 | H28: =IF(G28=0,"NIL",IF(G28>0,"CR","DR")) -> CR
A29: 45432 | B29: PURCHASE | C29: BILL#374037 | D29: KB DEL E5450 | F29: 3500 | G29: =G28+F29-E29 -> 38900 | H29: =IF(G29=0,"NIL",IF(G29>0,"CR","DR")) -> CR
A30: 45434 | B30: PURCHASE | C30: BILL#374237 | D30: KB DEL E5450 | F30: 3650 | G30: =G29+F30-E30 -> 42550 | H30: =IF(G30=0,"NIL",IF(G30>0,"CR","DR")) -> CR
A31: 45444 | B31: PURCHASE | C31: BILL#375173 | D31: DELL KB E6400 | F31: 2950 | G31: =G30+F31-E31 -> 45500 | H31: =IF(G31=0,"NIL",IF(G31>0,"CR","DR")) -> CR
A32: 45446 | B32: PURCHASE | C32: BILL#375287 | D32: KB AC 5755/BAT HP 240-G2 | F32: 5200 | G32: =G31+F32-E32 -> 50700 | H32: =IF(G32=0,"NIL",IF(G32>0,"CR","DR")) -> CR
A33: 45447 | B33: PURCHASE | C33: BILL#375476 | D33: KB HP 840 G1 | F33: 3300 | G33: =G32+F33-E33 -> 54000 | H33: =IF(G33=0,"NIL",IF(G33>0,"CR","DR")) -> CR
A34: 45447 | B34: PURCHASE | C34: BILL#375407 | D34: BAT HP 8460 | F34: 3650 | G34: =G33+F34-E34 -> 57650 | H34: =IF(G34=0,"NIL",IF(G34>0,"CR","DR")) -> CR
A35: 45448 | B35: PURCHASE | C35: BILL#375574 | D35: KB AC 5755 | F35: 1500 | G35: =G34+F35-E35 -> 59150 | H35: =IF(G35=0,"NIL",IF(G35>0,"CR","DR")) -> CR
D36: TOTAL BALANCE | E36: =SUM(E6:E35) -> 58300 | F36: =SUM(F6:F35) -> 106250 | G36: =G5+F36-E36 -> 59150 | H36: =IF(G36=0,"NIL",IF(G36>0,"CR","DR")) -> CR

Sheet AL AZIZ-LHR-14 
A1: TASNIM COMPUTERS SALES & SERVICE | J1: PAYABLE HOME
A2: AL-AZIZ LAHORE LEDGER
A3: FROM THE MONTH OF JULY-2019
A4: DATE | B4: TYPE | C4: REF# | D4: DESCRIPTION | E4: DEBIT | F4: CREDIT | G4: BALANCE
D5: BALANCE B/F | G5: ='AL AZIZ-LHR-13'!G36 -> 59150
A6: 45449 | B6: PURCHASE | C6: BILL#375618 | D6: HING DELL E5420 | F6: 1150 | G6: =G5+F6-E6 -> 60300 | H6: =IF(G6=0,"NIL",IF(G6>0,"CR","DR")) -> CR
A7: 45456 | B7: PAYMENT | C7: PAYMENT | D7: PAYMENT THROUGH BOP | E7: 32200 | F7: 0 | G7: =G6+F7-E7 -> 28100 | H7: =IF(G7=0,"NIL",IF(G7>0,"CR","DR")) -> CR
A8: 45456 | B8: PURCHASE | C8: BILL#376386 | D8: BAT DE E3340/KB DE V3340 | F8: 6300 | G8: =G7+F8-E8 -> 34400 | H8: =IF(G8=0,"NIL",IF(G8>0,"CR","DR")) -> CR
A9: 45456 | B9: PURCHASE | C9: BILL#376401 | D9: BAT HP 8530 | F9: 4100 | G9: =G8+F9-E9 -> 38500 | H9: =IF(G9=0,"NIL",IF(G9>0,"CR","DR")) -> CR
A10: 45464 | B10: PURCHASE | C10: BILL#376733 | D10: HP SCREEN 14" | F10: 8800 | G10: =G9+F10-E10 -> 47300 | H10: =IF(G10=0,"NIL",IF(G10>0,"CR","DR")) -> CR
A11: 45465 | B11: PURCHASE | C11: BILL#376787 | D11: BAT DELL 7440 | F11: 5650 | G11: =G10+F11-E11 -> 52950 | H11: =IF(G11=0,"NIL",IF(G11>0,"CR","DR")) -> CR
A12: 45465 | B12: PURCHASE | C12: BILL#376827 | D12: KB HP 840 G1/HP 840 G1 FAN | F12: 4300 | G12: =G11+F12-E12 -> 57250 | H12: =IF(G12=0,"NIL",IF(G12>0,"CR","DR")) -> CR
A13: 45471 | B13: PURCHASE | C13: BILL#3774414 | D13: BAT HP 240-G2 | F13: 3650 | G13: =G12+F13-E13 -> 60900 | H13: =IF(G13=0,"NIL",IF(G13>0,"CR","DR")) -> CR
A14: 45476 | B14: PURCHASE | C14: BILL#377898 | D14: BAT HP 6930 | F14: 3350 | G14: =G13+F14-E14 -> 64250 | H14: =IF(G14=0,"NIL",IF(G14>0,"CR","DR")) -> CR
A15: 45483 | B15: PURCHASE | C15: BILL#379044 | D15: KBHP PAVILION 15 | F15: 1650 | G15: =G14+F15-E15 -> 65900 | H15: =IF(G15=0,"NIL",IF(G15>0,"CR","DR")) -> CR
A16: 45485 | B16: PURCHASE | C16: BILL#379272 | D16: KB HP 6560B | F16: 2350 | G16: =G15+F16-E16 -> 68250 | H16: =IF(G16=0,"NIL",IF(G16>0,"CR","DR")) -> CR
A17: 45497 | B17: PAYMENT | C17: PAYMENT | D17: PAYMENT THROUGH BOP | E17: 33250 | F17: 0 | G17: =G16+F17-E17 -> 35000 | H17: =IF(G17=0,"NIL",IF(G17>0,"CR","DR")) -> CR
A18: 45502 | B18: PURCHASE | C18: BILL# 381162 | D18: BAT HP 2560 | E18: 0 | F18: 3150 | G18: =G17+F18-E18 -> 38150 | H18: =IF(G18=0,"NIL",IF(G18>0,"CR","DR")) -> CR
A19: 45503 | B19: PURCHASE | C19: BILL# 381372 | D19: KB IBM E550 | E19: 0 | F19: 3150 | G19: =G18+F19-E19 -> 41300 | H19: =IF(G19=0,"NIL",IF(G19>0,"CR","DR")) -> CR
A20: 45517 | B20: PURCHASE | C20: BILL#383237 | D20: HP820 KB/6470 BATT/HP 8440 KB | E20: 0 | F20: 6950 | G20: =G19+F20-E20 -> 48250 | H20: =IF(G20=0,"NIL",IF(G20>0,"CR","DR")) -> CR
A21: 45519 | B21: PURCHASE | C21: BILL#383607 | D21: KB 3521/KB 8440/BAT LENOVO G580 | E21: 0 | F21: 8000 | G21: =G20+F21-E21 -> 56250 | H21: =IF(G21=0,"NIL",IF(G21>0,"CR","DR")) -> CR
A22: 45527 | B22: PURCHASE | C22: BILL#384525 | D22: HP 650 G2 SCREEN/DELL BATTERY 3340 | E22: 0 | F22: 15500 | G22: =G21+F22-E22 -> 71750 | H22: =IF(G22=0,"NIL",IF(G22>0,"CR","DR")) -> CR
A23: ADJUSTMENT | B23: ADJUSTMENT | C23: ADJUSTMENT | D23: ADJUSTMENT OF DIFFERENCE IN LEDGER | E23: 0 | F23: 2340 | G23: =G22+F23-E23 -> 74090 | H23: =IF(G23=0,"NIL",IF(G23>0,"CR","DR")) -> CR
A24: 45549 | B24: PURCHASE | C24: BILL#388123 | D24: BAT HP PAVILIION 17/KLO4/K104 | E24: 0 | F24: 3350 | G24: =G23+F24-E24 -> 77440 | H24: =IF(G24=0,"NIL",IF(G24>0,"CR","DR")) -> CR
A25: 45554 | B25: PAYMENT | C25: PAYMENT | D25: PAYMENT THROUGH BOP | E25: 47440 | F25: 0 | G25: =G24+F25-E25 -> 30000 | H25: =IF(G25=0,"NIL",IF(G25>0,"CR","DR")) -> CR
A26: 45572 | B26: PAYMENT | C26: PAYMENT | D26: PAYMENT THROUGH BOP | E26: 30000 | F26: 0 | G26: =G25+F26-E26 -> 0 | H26: =IF(G26=0,"NIL",IF(G26>0,"CR","DR")) -> NIL
A27: 45575 | B27: PURCHASE | C27: BILL#391324 | D27: DELL BAT D3521 | F27: 4150 | G27: =G26+F27-E27 -> 4150 | H27: =IF(G27=0,"NIL",IF(G27>0,"CR","DR")) -> CR
A28: 45579 | B28: PURCHASE | C28: BILL#391728 | D28: BAT HP G2 | F28: 3350 | G28: =G27+F28-E28 -> 7500 | H28: =IF(G28=0,"NIL",IF(G28>0,"CR","DR")) -> CR
A29: 45582 | B29: PURCHASE | C29: BILL#392158 | D29: KB HAIER 7G-5H | F29: 2150 | G29: =G28+F29-E29 -> 9650 | H29: =IF(G29=0,"NIL",IF(G29>0,"CR","DR")) -> CR
A30: 45583 | B30: PURCHASE | C30: BILL#392286 | D30: BAT HP 450 G3 | F30: 3350 | G30: =G29+F30-E30 -> 13000 | H30: =IF(G30=0,"NIL",IF(G30>0,"CR","DR")) -> CR
A31: 45586 | B31: PAYMENT | C31: PAYMENT | D31: PAYMENT THROUGH BOP | E31: 13000 | G31: =G30+F31-E31 -> 0 | H31: =IF(G31=0,"NIL",IF(G31>0,"CR","DR")) -> NIL
A32: 45607 | B32: PURCHASE | C32: BILL#394707 | D32: KB IBM E550 | E32: 0 | F32: 3350 | G32: =G31+F32-E32 -> 3350 | H32: =IF(G32=0,"NIL",IF(G32>0,"CR","DR")) -> CR
A33: 45644 | B33: PURCHASE | C33: BILL#398301 | D33: KB HP G6 2000 | F33: 2950 | G33: =G32+F33-E33 -> 6300 | H33: =IF(G33=0,"NIL",IF(G33>0,"CR","DR")) -> CR
A34: 45670 | B34: PAYMENT | C34: PAYMENT | D34: PAYMENT THROUGH BOP | E34: 6300 | G34: =G33+F34-E34 -> 0 | H34: =IF(G34=0,"NIL",IF(G34>0,"CR","DR")) -> NIL
A35: 45677 | B35: PURCHASE | C35: BILL#401241 | D35: BAT FUJISTU AH530 | F35: 3150 | G35: =G34+F35-E35 -> 3150 | H35: =IF(G35=0,"NIL",IF(G35>0,"CR","DR")) -> CR
D36: TOTAL BALANCE | E36: =SUM(E6:E35) -> 162190 | F36: =SUM(F6:F35) -> 106190 | G36: =G5+F36-E36 -> 3150 | H36: =IF(G36=0,"NIL",IF(G36>0,"CR","DR")) -> CR

Sheet AL AZIZ-LHR-15 
A1: TASNIM COMPUTERS SALES & SERVICE | J1: PAYABLE HOME
A2: AL-AZIZ LAHORE LEDGER
A3: FROM THE MONTH OF JULY-2019
A4: DATE | B4: TYPE | C4: REF# | D4: DESCRIPTION | E4: DEBIT | F4: CREDIT | G4: BALANCE
D5: BALANCE B/F | G5: ='AL AZIZ-LHR-14 '!G36 -> 3150
A6: 45685 | B6: PURCHASE | C6: BILL#402080 | D6: HP 15.6" SCREEN | F6: 8750 | G6: =G5+F6-E6 -> 11900 | H6: =IF(G6=0,"NIL",IF(G6>0,"CR","DR")) -> CR
A7: 45690 | B7: PURCHASE | C7: BILL#402563 | D7: BAT HP 4530 / LENOVO YOGA / PWR | F7: 5700 | G7: =G6+F7-E7 -> 17600 | H7: =IF(G7=0,"NIL",IF(G7>0,"CR","DR")) -> CR
A8: 45691 | B8: PAYMENT | C8: PAYMENT | D8: PAYMENT THROUGH BOP | E8: 17600 | G8: =G7+F8-E8 -> 0 | H8: =IF(G8=0,"NIL",IF(G8>0,"CR","DR")) -> NIL
A9: 45696 | B9: PURCHASE | C9: BILL#403117 | D9: HP 15.6" SCREEN 30pin fhd | F9: 10000 | G9: =G8+F9-E9 -> 10000 | H9: =IF(G9=0,"NIL",IF(G9>0,"CR","DR")) -> CR
A10: 45698 | B10: PURCHASE | C10: BILL#403223 | D10: BAT 5560 | F10: 6150 | G10: =G9+F10-E10 -> 16150 | H10: =IF(G10=0,"NIL",IF(G10>0,"CR","DR")) -> CR
A11: 45691 | B11: PURCHASE | C11: BILL#402682 | D11: HP BAT 4530 | F11: 3000 | G11: =G10+F11-E11 -> 19150 | H11: =IF(G11=0,"NIL",IF(G11>0,"CR","DR")) -> CR
A12: 45700 | B12: ADJUSTMENT | C12: RETURE | D12: HP BAT 4530 QTY 2 | E12: 6000 | G12: =G11+F12-E12 -> 13150 | H12: =IF(G12=0,"NIL",IF(G12>0,"CR","DR")) -> CR
A13: 45693 | B13: PAYMENT | C13: PAYMENT | D13: PAYMENT THROUGH BOP | E13: 13150 | G13: =G12+F13-E13 -> 0 | H13: =IF(G13=0,"NIL",IF(G13>0,"CR","DR")) -> NIL
A14: 45769 | B14: PURCHASE | C14: BILL#408894 | D14: FAN HP 9470 | F14: 1650 | G14: =G13+F14-E14 -> 1650 | H14: =IF(G14=0,"NIL",IF(G14>0,"CR","DR")) -> CR
A15: 45771 | B15: PURCHASE | C15: BILL#409226 | D15: DELL BAT 7440 | F15: 5650 | G15: =G14+F15-E15 -> 7300 | H15: =IF(G15=0,"NIL",IF(G15>0,"CR","DR")) -> CR
A16: 45771 | B16: PURCHASE | C16: BILL#409230 | D16: HP 14"LED | F16: 7700 | G16: =G15+F16-E16 -> 15000 | H16: =IF(G16=0,"NIL",IF(G16>0,"CR","DR")) -> CR
A17: 45776 | B17: PURCHASE | C17: BILL#409423 | D17: DELL DC JACK | F17: 1400 | G17: =G16+F17-E17 -> 16400 | H17: =IF(G17=0,"NIL",IF(G17>0,"CR","DR")) -> CR
A18: 45782 | B18: PAYMENT | C18: PAYMENT | D18: PAYMENT THROUGH BOP | E18: 16400 | G18: =G17+F18-E18 -> 0 | H18: =IF(G18=0,"NIL",IF(G18>0,"CR","DR")) -> NIL
A19: 45812 | B19: PURCHASE | C19: BILL#412722 | D19: BAT D15-3551 KB D15 3542 | F19: 7200 | G19: =G18+F19-E19 -> 7200 | H19: =IF(G19=0,"NIL",IF(G19>0,"CR","DR")) -> CR
A20: 45818 | B20: PURCHASE | C20: BILL#412897 | D20: DELL BAT E5250 | F20: 5150 | G20: =G19+F20-E20 -> 12350 | H20: =IF(G20=0,"NIL",IF(G20>0,"CR","DR")) -> CR
A21: 45832 | B21: PAYMENT | C21: PAYMENT | D21: PAYMENT THROUGH BOP | E21: 12350 | G21: =G20+F21-E21 -> 0 | H21: =IF(G21=0,"NIL",IF(G21>0,"CR","DR")) -> NIL
A22: 45834 | B22: PURCHASE | C22: BILL#414398 | D22: HP KB 8440/BAT D15-3551 | F22: 5600 | G22: =G21+F22-E22 -> 5600 | H22: =IF(G22=0,"NIL",IF(G22>0,"CR","DR")) -> CR
A23: 45839 | B23: PURCHASE | C23: BILL#414799 | D23: BAT HP PAVILION 14T | F23: 3150 | G23: =G22+F23-E23 -> 8750 | H23: =IF(G23=0,"NIL",IF(G23>0,"CR","DR")) -> CR
A24: 45846 | B24: PAYMENT | C24: PAYMENT | D24: PAYMENT THROUGH BOP | E24: 8750 | G24: =G23+F24-E24 -> 0 | H24: =IF(G24=0,"NIL",IF(G24>0,"CR","DR")) -> NIL
A25: 45846 | B25: PURCHASE | C25: BILL#415409 | D25: Hanging | F25: 1150 | G25: =G24+F25-E25 -> 1150 | H25: =IF(G25=0,"NIL",IF(G25>0,"CR","DR")) -> CR
A26: 45846 | B26: PURCHASE | C26: BILL#415413 | D26: BAT 440 G2 | F26: 3050 | G26: =G25+F26-E26 -> 4200 | H26: =IF(G26=0,"NIL",IF(G26>0,"CR","DR")) -> CR
A27: 45850 | B27: PURCHASE | C27: BILL#415676 | D27: 14" LED SLIM FHD | F27: 9750 | G27: =G26+F27-E27 -> 13950 | H27: =IF(G27=0,"NIL",IF(G27>0,"CR","DR")) -> CR
A28: 45854 | B28: PAYMENT | C28: PAYMENT | D28: PAYMENT THROUGH BOP | E28: 13950 | G28: =G27+F28-E28 -> 0 | H28: =IF(G28=0,"NIL",IF(G28>0,"CR","DR")) -> NIL
A29: 45854 | B29: PURCHASE | C29: BILL#416022 | D29: 14" LED slim 30 pin | F29: 7750 | G29: =G28+F29-E29 -> 7750 | H29: =IF(G29=0,"NIL",IF(G29>0,"CR","DR")) -> CR
A30: 45862 | B30: PURCHASE | C30: BILL#416857 | D30: HP battery | F30: 3150 | G30: =G29+F30-E30 -> 10900 | H30: =IF(G30=0,"NIL",IF(G30>0,"CR","DR")) -> CR
A31: 45864 | B31: PURCHASE | C31: BILL#417293 | D31: KB TOS C850 | F31: 1500 | G31: =G30+F31-E31 -> 12400 | H31: =IF(G31=0,"NIL",IF(G31>0,"CR","DR")) -> CR
A32: 45876 | B32: PURCHASE | C32: BILL#418758 | D32: HP FAN ENVY 15-U | F32: 950 | G32: =G31+F32-E32 -> 13350 | H32: =IF(G32=0,"NIL",IF(G32>0,"CR","DR")) -> CR
A33: 45877 | B33: PURCHASE | C33: BILL#418910 | D33: 14"inch fhd | F33: 9750 | G33: =G32+F33-E33 -> 23100 | H33: =IF(G33=0,"NIL",IF(G33>0,"CR","DR")) -> CR
A34: 45880 | B34: PAYMENT | C34: PAYMENT | D34: PAYMENT THROUGH BOP | E34: 23100 | G34: =G33+F34-E34 -> 0 | H34: =IF(G34=0,"NIL",IF(G34>0,"CR","DR")) -> NIL
G35: =G34+F35-E35 -> 0 | H35: =IF(G35=0,"NIL",IF(G35>0,"CR","DR")) -> NIL
D36: TOTAL BALANCE | E36: =SUM(E6:E35) -> 111300 | F36: =SUM(F6:F35) -> 108150 | G36: =G5+F36-E36 -> 0 | H36: =IF(G36=0,"NIL",IF(G36>0,"CR","DR")) -> NIL

Sheet AL AZIZ-LHR-16 
A1: TASNIM COMPUTERS SALES & SERVICE | J1: PAYABLE HOME
A2: AL-AZIZ LAHORE LEDGER
A3: FROM THE MONTH OF JULY-2019
A4: DATE | B4: TYPE | C4: REF# | D4: DESCRIPTION | E4: DEBIT | F4: CREDIT | G4: BALANCE
G5: ='AL AZIZ-LHR-15 '!G36 -> 0
A6: 45884 | B6: PURCHASE | C6: BILL#419547 | D6: SPK IBM T470s | F6: 2150 | G6: =G5+F6-E6 -> 2150 | H6: =IF(G6=0,"NIL",IF(G6>0,"CR","DR")) -> CR
A7: 45887 | B7: PURCHASE | C7: BILL#419993 | D7: HP KB 440 G5 | F7: 1850 | G7: =G6+F7-E7 -> 4000 | H7: =IF(G7=0,"NIL",IF(G7>0,"CR","DR")) -> CR
A8: 45887 | B8: PURCHASE | C8: BILL#419932 | D8: DC JACK 450G3/HP 15-BS /HP FAN 840 G1 | F8: 4250 | G8: =G7+F8-E8 -> 8250 | H8: =IF(G8=0,"NIL",IF(G8>0,"CR","DR")) -> CR
A9: 45889 | B9: PURCHASE | C9: BILL#420237 | D9: HP KB 4540 /BAT HP 6930 | F9: 4900 | G9: =G8+F9-E9 -> 13150 | H9: =IF(G9=0,"NIL",IF(G9>0,"CR","DR")) -> CR
A10: 45889 | B10: PURCHASE | C10: BILL#420329 | D10: DELL DC JACK D5567 | F10: 1550 | G10: =G9+F10-E10 -> 14700 | H10: =IF(G10=0,"NIL",IF(G10>0,"CR","DR")) -> CR
A11: 45889 | B11: PURCHASE | C11: BILL#420331 | D11: KB HP 440 G5 B/L | F11: 3500 | G11: =G10+F11-E11 -> 18200 | H11: =IF(G11=0,"NIL",IF(G11>0,"CR","DR")) -> CR
A12: 45896 | B12: PURCHASE | C12: BILL#421016 | D12: DELL SPK 7490 | F12: 2150 | G12: =G11+F12-E12 -> 20350 | H12: =IF(G12=0,"NIL",IF(G12>0,"CR","DR")) -> CR
A13: 45896 | B13: PURCHASE | C13: BILL#421125 | D13: DELL BAT E5450 | F13: 5650 | G13: =G12+F13-E13 -> 26000 | H13: =IF(G13=0,"NIL",IF(G13>0,"CR","DR")) -> CR
A14: 45897 | B14: RETURN | C14: BILL#419993 | D14: HP KB 440 G5 RETURNE | E14: 1700 | G14: =G13+F14-E14 -> 24300 | H14: =IF(G14=0,"NIL",IF(G14>0,"CR","DR")) -> CR
A15: 45898 | B15: PAYMENT | C15: PAYMENT | D15: PAYMENT THROUGH BOP | E15: 24000 | G15: =G14+F15-E15 -> 300 | H15: =IF(G15=0,"NIL",IF(G15>0,"CR","DR")) -> CR
A16: 45898 | B16: PURCHASE | C16: BILL#421392 | D16: BAT D3521 | F16: 4150 | G16: =G15+F16-E16 -> 4450 | H16: =IF(G16=0,"NIL",IF(G16>0,"CR","DR")) -> CR
A17: 45879 | B17: PURCHASE | C17: BILL#422555 | D17: 14" screen /IBM G50 | F17: 9900 | G17: =G16+F17-E17 -> 14350 | H17: =IF(G17=0,"NIL",IF(G17>0,"CR","DR")) -> CR
A18: 45879 | B18: PURCHASE | C18: Bill#422631 | D18: HP KB PAVILION 15 | F18: 1400 | G18: =G17+F18-E18 -> 15750 | H18: =IF(G18=0,"NIL",IF(G18>0,"CR","DR")) -> CR
A19: 45910 | B19: PURCHASE | C19: BILL#422832 | D19: hp 15"6 LED | F19: 8350 | G19: =G18+F19-E19 -> 24100 | H19: =IF(G19=0,"NIL",IF(G19>0,"CR","DR")) -> CR
A20: 45915 | B20: PAYMENT | C20: PAYMENT | D20: PAYMENT THROUGH BOP | E20: 24100 | G20: =G19+F20-E20 -> 0 | H20: =IF(G20=0,"NIL",IF(G20>0,"CR","DR")) -> NIL
A21: 45916 | B21: PURCHASE | C21: BILL#423576 | D21: 14" LED SLIM 30PIN FHD | F21: 9850 | G21: =G20+F21-E21 -> 9850 | H21: =IF(G21=0,"NIL",IF(G21>0,"CR","DR")) -> CR
A22: 45924 | B22: PURCHASE | C22: BILL#423813 | D22: 14" LED SLIM 30PIN FHD | F22: 9800 | G22: =G21+F22-E22 -> 19650 | H22: =IF(G22=0,"NIL",IF(G22>0,"CR","DR")) -> CR
A23: 45923 | B23: PURCHASE | C23: BILL#424606 | D23: DELL HANGING | F23: 1150 | G23: =G22+F23-E23 -> 20800 | H23: =IF(G23=0,"NIL",IF(G23>0,"CR","DR")) -> CR
A24: 45926 | B24: PURCHASE | C24: BILL#424994 | D24: 14" LED SLIM 30PIN FHD | F24: 9850 | G24: =G23+F24-E24 -> 30650 | H24: =IF(G24=0,"NIL",IF(G24>0,"CR","DR")) -> CR
A25: 45927 | B25: PURCHASE | C25: BILL#425100 | D25: KB LENOVO X240 / T430 | F25: 6250 | G25: =G24+F25-E25 -> 36900 | H25: =IF(G25=0,"NIL",IF(G25>0,"CR","DR")) -> CR
A26: 45916 | B26: RETURN | C26: BILL#423576 | D26: 14" LED SLIM 30PIN FHD | E26: 9500 | G26: =G25+F26-E26 -> 27400 | H26: =IF(G26=0,"NIL",IF(G26>0,"CR","DR")) -> CR
A27: 45926 | B27: RETURN | C27: BILL#424994 | D27: 14" LED SLIM 30PIN FHD | E27: 9500 | G27: =G26+F27-E27 -> 17900 | H27: =IF(G27=0,"NIL",IF(G27>0,"CR","DR")) -> CR
A28: 45929 | B28: PURCHASE | C28: BILL#425258 | D28: KB IBM T470s | F28: 3650 | G28: =G27+F28-E28 -> 21550 | H28: =IF(G28=0,"NIL",IF(G28>0,"CR","DR")) -> CR
A29: 45929 | B29: PURCHASE | C29: BILL#425265 | D29: BAT AC E5-571 | F29: 3000 | G29: =G28+F29-E29 -> 24550 | H29: =IF(G29=0,"NIL",IF(G29>0,"CR","DR")) -> CR
A30: 45929 | B30: PURCHASE | C30: BILL#425301 | D30: hp 840 g3 cable | F30: 800 | G30: =G29+F30-E30 -> 25350 | H30: =IF(G30=0,"NIL",IF(G30>0,"CR","DR")) -> CR
A31: 45929 | B31: PURCHASE | C31: BILL#425337 | D31: 14" LED SLIM 30PIN FHD | F31: 9850 | G31: =G30+F31-E31 -> 35200 | H31: =IF(G31=0,"NIL",IF(G31>0,"CR","DR")) -> CR
A32: 45931 | B32: PURCHASE | C32: BILL#425546 | D32: BAT D5010 | F32: 3150 | G32: =G31+F32-E32 -> 38350 | H32: =IF(G32=0,"NIL",IF(G32>0,"CR","DR")) -> CR
A33: 45931 | B33: PURCHASE | C33: BILL#425622 | D33: DELL HANGING E5470 | F33: 800 | G33: =G32+F33-E33 -> 39150 | H33: =IF(G33=0,"NIL",IF(G33>0,"CR","DR")) -> CR
A34: 45934 | B34: PURCHASE | C34: BILL#426011 | D34: BAT E7440/KB DELL 7440 KB | F34: 7400 | G34: =G33+F34-E34 -> 46550 | H34: =IF(G34=0,"NIL",IF(G34>0,"CR","DR")) -> CR
A35: 45936 | B35: PAYMENT | C35: PAYMENT | D35: PAYMENT THROUGH BOP | E35: 25000 | G35: =G34+F35-E35 -> 21550 | H35: =IF(G35=0,"NIL",IF(G35>0,"CR","DR")) -> CR
D36: TOTAL BALANCE | E36: =SUM(E6:E35) -> 93800 | F36: =SUM(F6:F35) -> 115350 | G36: =G5+F36-E36 -> 21550 | H36: =IF(G36=0,"NIL",IF(G36>0,"CR","DR")) -> CR

Sheet AL AZIZ-LHR-17 
A1: TASNIM COMPUTERS SALES & SERVICE | J1: PAYABLE HOME
A2: AL-AZIZ LAHORE LEDGER
A3: FROM THE MONTH OF JULY-2019
A4: DATE | B4: TYPE | C4: REF# | D4: DESCRIPTION | E4: DEBIT | F4: CREDIT | G4: BALANCE
G5: ='AL AZIZ-LHR-16 '!G36 -> 21550
A6: 45938 | B6: PURCHASE | C6: BILL#426271 | D6: HP BAT 8460 | F6: 3150 | G6: =G5+F6-E6 -> 24700 | H6: =IF(G6=0,"NIL",IF(G6>0,"CR","DR")) -> CR
A7: 45939 | B7: PAYMENT | C7: PAYMENT | D7: PAYMENT THROUGH BOP | E7: 15000 | G7: =G6+F7-E7 -> 9700 | H7: =IF(G7=0,"NIL",IF(G7>0,"CR","DR")) -> CR
A8: 45955 | B8: PURCHASE | C8: BILL#428170 | D8: 15.6" LED SLIM 30 pin | F8: 9800 | G8: =G7+F8-E8 -> 19500 | H8: =IF(G8=0,"NIL",IF(G8>0,"CR","DR")) -> CR
A9: 45945 | B9: PAYMENT | C9: BILL#427122 | D9: SPK HP 840 G1 | F9: 1350 | G9: =G8+F9-E9 -> 20850 | H9: =IF(G9=0,"NIL",IF(G9>0,"CR","DR")) -> CR
A10: 45960 | B10: PURCHASE | C10: BILL428602 | D10: KB HP 850 G3 | F10: 3650 | G10: =G9+F10-E10 -> 24500 | H10: =IF(G10=0,"NIL",IF(G10>0,"CR","DR")) -> CR
A11: 45961 | B11: PURCHASE | C11: BILL#428707 | D11: BAT HP 430 / KB HP 430 | F11: 4600 | G11: =G10+F11-E11 -> 29100 | H11: =IF(G11=0,"NIL",IF(G11>0,"CR","DR")) -> CR
A12: 45962 | B12: PURCHASE | C12: BILL#428771 | D12: KB HP PAVILION 15 | F12: 1550 | G12: =G11+F12-E12 -> 30650 | H12: =IF(G12=0,"NIL",IF(G12>0,"CR","DR")) -> CR
A13: 45965 | B13: PURCHASE | C13: BILL#428981 | D13: 15.6" LED SLIM 30 pin | F13: 8350 | G13: =G12+F13-E13 -> 39000 | H13: =IF(G13=0,"NIL",IF(G13>0,"CR","DR")) -> CR
A14: 45966 | B14: PURCHASE | C14: BILL#429058 | D14: 15.6" LED / KB AC 5742 | F14: 9700 | G14: =G13+F14-E14 -> 48700 | H14: =IF(G14=0,"NIL",IF(G14>0,"CR","DR")) -> CR
A15: 45965 | B15: RETURNE | C15: BILL#428981 | D15: 15.6" LED | E15: 8000 | G15: =G14+F15-E15 -> 40700 | H15: =IF(G15=0,"NIL",IF(G15>0,"CR","DR")) -> CR
A16: 45969 | B16: PAYMENT | C16: PAYMENT | D16: PAYMENT THROUGH BOP | E16: 30000 | G16: =G15+F16-E16 -> 10700 | H16: =IF(G16=0,"NIL",IF(G16>0,"CR","DR")) -> CR
A17: 45974 | B17: PURCHASE | C17: BILL#429712 | D17: DELL BAT D15-3521 | F17: 3800 | G17: =G16+F17-E17 -> 14500 | H17: =IF(G17=0,"NIL",IF(G17>0,"CR","DR")) -> CR
A18: 45978 | B18: PURCHASE | C18: BILL#429997 | D18: 14" led / KB HP G6 | F18: 9250 | G18: =G17+F18-E18 -> 23750 | H18: =IF(G18=0,"NIL",IF(G18>0,"CR","DR")) -> CR
A19: 45981 | B19: PAYMENT | C19: PAYMENT | D19: PAYMENT THROUGH BOP | E19: 23750 | G19: =G18+F19-E19 -> 0 | H19: =IF(G19=0,"NIL",IF(G19>0,"CR","DR")) -> NIL
A20: 45982 | B20: PURCHASE | C20: BILL#430356 | D20: DELL BAT DE E7480 | F20: 5650 | G20: =G19+F20-E20 -> 5650 | H20: =IF(G20=0,"NIL",IF(G20>0,"CR","DR")) -> CR
A21: 45987 | B21: PURCHASE | C21: BILL#430709 | D21: 14" LED SLIM 30 PIN / KB IBM G505S | F21: 9300 | G21: =G20+F21-E21 -> 14950 | H21: =IF(G21=0,"NIL",IF(G21>0,"CR","DR")) -> CR
A22: 45988 | B22: PURCHASE | C22: BILL#430768 | D22: BAT HP 440 G2 | F22: 3150 | G22: =G21+F22-E22 -> 18100 | H22: =IF(G22=0,"NIL",IF(G22>0,"CR","DR")) -> CR
A23: 45992 | B23: PURCHASE | C23: BILL#431048 | D23: BAT DE E6400 | F23: 3000 | G23: =G22+F23-E23 -> 21100 | H23: =IF(G23=0,"NIL",IF(G23>0,"CR","DR")) -> CR
A24: 45992 | B24: PURCHASE | C24: BILL#431000 | D24: KB HP 840 G3 | F24: 3150 | G24: =G23+F24-E24 -> 24250 | H24: =IF(G24=0,"NIL",IF(G24>0,"CR","DR")) -> CR
A25: 45994 | B25: PURCHASE | C25: BILL#431183 | D25: HP 840 G1 SPEAKER | F25: 1350 | G25: =G24+F25-E25 -> 25600 | H25: =IF(G25=0,"NIL",IF(G25>0,"CR","DR")) -> CR
A26: 46003 | B26: PURCHASE | C26: BILL#431882 | D26: HP BAT 8460 | F26: 3150 | G26: =G25+F26-E26 -> 28750 | H26: =IF(G26=0,"NIL",IF(G26>0,"CR","DR")) -> CR
A27: 46007 | B27: PAYMENT | C27: PAYMENT | D27: PAYMENT THROUGH BOP | E27: 15000 | G27: =G26+F27-E27 -> 13750 | H27: =IF(G27=0,"NIL",IF(G27>0,"CR","DR")) -> CR
A28: 46017 | B28: PURCHASE | C28: BILL#432760 | D28: KB HP CQ61 /BAT HP DV4 | F28: 4600 | G28: =G27+F28-E28 -> 18350 | H28: =IF(G28=0,"NIL",IF(G28>0,"CR","DR")) -> CR
A29: 46021 | B29: PAYMENT | C29: PAYMENT | D29: PAYMENT THROUGH BOP | E29: 10000 | G29: =G28+F29-E29 -> 8350 | H29: =IF(G29=0,"NIL",IF(G29>0,"CR","DR")) -> CR
A30: 46025 | B30: PURCHASE | C30: BILL#433479 | D30: BAT HP 440 G2 | F30: 3000 | G30: =G29+F30-E30 -> 11350 | H30: =IF(G30=0,"NIL",IF(G30>0,"CR","DR")) -> CR
A31: 46025 | B31: PURCHASE | C31: BILL#433434 | D31: BAT HP 4530 | F31: 3150 | G31: =G30+F31-E31 -> 14500 | H31: =IF(G31=0,"NIL",IF(G31>0,"CR","DR")) -> CR
A32: 46027 | B32: RETURNE | C32: BILL#430768 | D32: BAT HP 440 G2 | E32: 3000 | G32: =G31+F32-E32 -> 11500 | H32: =IF(G32=0,"NIL",IF(G32>0,"CR","DR")) -> CR
A33: 46039 | B33: PAYMENT | C33: PAYMENT | D33: PAYMENT THROUGH BOP | E33: 10000 | G33: =G32+F33-E33 -> 1500 | H33: =IF(G33=0,"NIL",IF(G33>0,"CR","DR")) -> CR
A34: 46051 | B34: PURCHASE | C34: BILL#435770 | D34: BAT IBM G460 | F34: 3150 | G34: =G33+F34-E34 -> 4650 | H34: =IF(G34=0,"NIL",IF(G34>0,"CR","DR")) -> CR
G35: =G34+F35-E35 -> 4650 | H35: =IF(G35=0,"NIL",IF(G35>0,"CR","DR")) -> CR
D36: TOTAL BALANCE | E36: =SUM(E6:E35) -> 114750 | F36: =SUM(F6:F35) -> 97850 | G36: =G5+F36-E36 -> 4650 | H36: =IF(G36=0,"NIL",IF(G36>0,"CR","DR")) -> CR

Sheet AL AZIZ-LHR-18
A1: TASNIM COMPUTERS SALES & SERVICE | J1: PAYABLE HOME
A2: AL-AZIZ LAHORE LEDGER
A3: FROM THE MONTH OF JULY-2019
A4: DATE | B4: TYPE | C4: REF# | D4: DESCRIPTION | E4: DEBIT | F4: CREDIT | G4: BALANCE
G5: ='AL AZIZ-LHR-17 '!G36 -> 4650
A6: 46067 | B6: PURCHASE | C6: BILL#437024 | D6: BAT HP 440 G3/R004 | F6: 3150 | G6: =G5+F6-E6 -> 7800 | H6: =IF(G6=0,"NIL",IF(G6>0,"CR","DR")) -> CR
A7: 46083 | B7: PURCHASE | C7: BILL#438179 | D7: BAT TOS 5212 | F7: 3150 | G7: =G6+F7-E7 -> 10950 | H7: =IF(G7=0,"NIL",IF(G7>0,"CR","DR")) -> CR
A8: 46085 | B8: PURCHASE | C8: BILL#438383 | D8: BAT TOS 5185 | F8: 3150 | G8: =G7+F8-E8 -> 14100 | H8: =IF(G8=0,"NIL",IF(G8>0,"CR","DR")) -> CR
A9: 46083 | B9: RETURNE | C9: RETURNE | D9: BAT TOS 5212 | E9: 3000 | G9: =G8+F9-E9 -> 11100 | H9: =IF(G9=0,"NIL",IF(G9>0,"CR","DR")) -> CR
A10: 46083 | B10: RETURNE | C10: BILL#438383 | D10: BAT TOS 5185 | E10: 3000 | G10: =G9+F10-E10 -> 8100 | H10: =IF(G10=0,"NIL",IF(G10>0,"CR","DR")) -> CR
A11: 46092 | B11: PURCHASE | C11: BILL#438919 | D11: BAT TOS 5185/KB HP 9470 | F11: 4700 | G11: =G10+F11-E11 -> 12800 | H11: =IF(G11=0,"NIL",IF(G11>0,"CR","DR")) -> CR
A12: 46093 | B12: PURCHASE | C12: BILL#439031 | D12: BAT DEE5540 | F12: 4650 | G12: =G11+F12-E12 -> 17450 | H12: =IF(G12=0,"NIL",IF(G12>0,"CR","DR")) -> CR
A13: 46121 | B13: PURCHASE | C13: BILL#441095 | D13: 15.6" LED slim FHD | F13: 9750 | G13: =G12+F13-E13 -> 27200 | H13: =IF(G13=0,"NIL",IF(G13>0,"CR","DR")) -> CR
A14: 46126 | B14: PAYMENT | C14: PAYMENT | D14: PAYMENT THROUGH BOP | E14: 20000 | G14: =G13+F14-E14 -> 7200 | H14: =IF(G14=0,"NIL",IF(G14>0,"CR","DR")) -> CR
A15: 46127 | B15: PURCHASE | C15: BILL#441534 | D15: BAT 745-G3 | F15: 5150 | G15: =G14+F15-E15 -> 12350 | H15: =IF(G15=0,"NIL",IF(G15>0,"CR","DR")) -> CR
A16: 46133 | B16: PURCHASE | C16: BILL#442270 | D16: KB IBM T440P | F16: 3150 | G16: =G15+F16-E16 -> 15500 | H16: =IF(G16=0,"NIL",IF(G16>0,"CR","DR")) -> CR
A17: 46134 | B17: PURCHASE | C17: BILL#442386 | D17: KB HP 430 | F17: 1550 | G17: =G16+F17-E17 -> 17050 | H17: =IF(G17=0,"NIL",IF(G17>0,"CR","DR")) -> CR
A18: 46137 | B18: PURCHASE | C18: BILL#4452743 | D18: KB TOS C850 | F18: 1550 | G18: =G17+F18-E18 -> 18600 | H18: =IF(G18=0,"NIL",IF(G18>0,"CR","DR")) -> CR
A19: 46140 | B19: PAYMENT | C19: PAYMENT | D19: PAYMENT THROUGH BOP | E19: 10000 | G19: =G18+F19-E19 -> 8600 | H19: =IF(G19=0,"NIL",IF(G19>0,"CR","DR")) -> CR
A20: 46139 | B20: PURCHASE | C20: BILL#442836 | D20: KB IBM T440P/KB XPS 13-9343 | F20: 6150 | G20: =G19+F20-E20 -> 14750 | H20: =IF(G20=0,"NIL",IF(G20>0,"CR","DR")) -> CR
A21: 46140 | B21: RETURNE | C21: RETURNE | D21: KB IBM T440P/KB XPS 13-9343 | E21: 6000 | G21: =G20+F21-E21 -> 8750 | H21: =IF(G21=0,"NIL",IF(G21>0,"CR","DR")) -> CR
A22: 46141 | B22: PURCHASE | C22: BILL#442941 | D22: KB DE XPS 13-9343 | F22: 3000 | G22: =G21+F22-E22 -> 11750 | H22: =IF(G22=0,"NIL",IF(G22>0,"CR","DR")) -> CR
A23: 46140 | B23: RETURNE | C23: RETURNE | D23: KB IBM IBM T440P | E23: 3000 | G23: =G22+F23-E23 -> 8750 | H23: =IF(G23=0,"NIL",IF(G23>0,"CR","DR")) -> CR
A24: 46142 | B24: PURCHASE | C24: BILL#443183 | D24: KB D14-5447/KB HP 640 | F24: 4400 | G24: =G23+F24-E24 -> 13150 | H24: =IF(G24=0,"NIL",IF(G24>0,"CR","DR")) -> CR
A25: 46146 | B25: PURCHASE | C25: BILL#443407 | D25: BAT HP 640 | F25: 3000 | G25: =G24+F25-E25 -> 16150 | H25: =IF(G25=0,"NIL",IF(G25>0,"CR","DR")) -> CR
A26: 46174 | B26: PURCHASE | C26: BILL#445452 | D26: BAT HP 840 G3 | F26: 5200 | G26: =G25+F26-E26 -> 21350 | H26: =IF(G26=0,"NIL",IF(G26>0,"CR","DR")) -> CR
A27: 46177 | B27: PURCHASE | C27: BILL#445819 | D27: HP KB 8460P | F27: 3000 | G27: =G26+F27-E27 -> 24350 | H27: =IF(G27=0,"NIL",IF(G27>0,"CR","DR")) -> CR
A28: 46182 | B28: PAYMENT | C28: PAYMENT | D28: PAYMENT THROUGH BOP | E28: 15000 | G28: =G27+F28-E28 -> 9350 | H28: =IF(G28=0,"NIL",IF(G28>0,"CR","DR")) -> CR
A29: 46200 | B29: PURCHASE | C29: BILL#447752 | D29: BAT HP 840 G3 | F29: 5150 | G29: =G28+F29-E29 -> 14500 | H29: =IF(G29=0,"NIL",IF(G29>0,"CR","DR")) -> CR
A30: 46202 | B30: PURCHASE | C30: BILL#447908 | D30: lenovo 14inch/bat 7440 | F30: 14300 | G30: =G29+F30-E30 -> 28800 | H30: =IF(G30=0,"NIL",IF(G30>0,"CR","DR")) -> CR
A31: 46205 | B31: PAYMENT | C31: PAYMENT | D31: PAYMENT THROUGH BOP | E31: 20000 | G31: =G30+F31-E31 -> 8800 | H31: =IF(G31=0,"NIL",IF(G31>0,"CR","DR")) -> CR
A32: 46211 | B32: PURCHASE | C32: BILL#448882 | D32: 15.6" slime 30 pin | F32: 7800 | G32: =G31+F32-E32 -> 16600 | H32: =IF(G32=0,"NIL",IF(G32>0,"CR","DR")) -> CR
A33: 46219 | B33: PURCHASE | C33: BILL#449766 | D33: lenovo speaker t470s | F33: 2150 | G33: =G32+F33-E33 -> 18750 | H33: =IF(G33=0,"NIL",IF(G33>0,"CR","DR")) -> CR
A34: 46225 | B34: PURCHASE | C34: BILL#450241 | D34: BATTERY E7240 | F34: 4950 | G34: =G33+F34-E34 -> 23700 | H34: =IF(G34=0,"NIL",IF(G34>0,"CR","DR")) -> CR
G35: =G34+F35-E35 -> 23700 | H35: =IF(G35=0,"NIL",IF(G35>0,"CR","DR")) -> CR
D36: TOTAL BALANCE | E36: =SUM(E6:E35) -> 80000 | F36: =SUM(F6:F35) -> 99050 | G36: =G5+F36-E36 -> 23700 | H36: =IF(G36=0,"NIL",IF(G36>0,"CR","DR")) -> CR

Sheet AL AZIZ-LHR-19
A1: TASNIM COMPUTERS SALES & SERVICE | J1: PAYABLE HOME
A2: AL-AZIZ LAHORE LEDGER
A3: FROM THE MONTH OF JULY-2019
A4: DATE | B4: TYPE | C4: REF# | D4: DESCRIPTION | E4: DEBIT | F4: CREDIT | G4: BALANCE
G5: ='AL AZIZ-LHR-18'!G36 -> 23700
A6: 46230 | B6: PURCHASE | C6: BILL#450849 | D6: DELL PRECISION 3530 ORG 6 CELL | F6: 10000 | G6: =G5+F6-E6 -> 33700 | H6: =IF(G6=0,"NIL",IF(G6>0,"CR","DR")) -> CR
A7: 46231 | B7: PURCHASE | C7: BILL#451053 | D7: DELL KB B/L E5450 | F7: 3650 | G7: =G6+F7-E7 -> 37350 | H7: =IF(G7=0,"NIL",IF(G7>0,"CR","DR")) -> CR
A8: 46233 | B8: PAYMENT | C8: PAYMENT | D8: PAYMENT THROUGH BOP | E8: 20000 | G8: =G7+F8-E8 -> 17350 | H8: =IF(G8=0,"NIL",IF(G8>0,"CR","DR")) -> CR
A9: 46235 | B9: PURCHASE | C9: BILL#451561 | D9: HP BATERY PAVILION 15 | F9: 2750 | G9: =G8+F9-E9 -> 20100 | H9: =IF(G9=0,"NIL",IF(G9>0,"CR","DR")) -> CR
A10: 46237 | B10: PURCHASE | C10: BILL#451715 | D10: HP KB /DC JACK | F10: 5250 | G10: =G9+F10-E10 -> 25350 | H10: =IF(G10=0,"NIL",IF(G10>0,"CR","DR")) -> CR
A11: 46240 | B11: PURCHASE | C11: BILL#452086 | D11: KB IBM T440P /KB AC 5742 | F11: 4250 | G11: =G10+F11-E11 -> 29600 | H11: =IF(G11=0,"NIL",IF(G11>0,"CR","DR")) -> CR
A12: 46241 | B12: PURCHASE | C12: BILL#452249 | D12: HP BATTERY 820 G1 | F12: 4650 | G12: =G11+F12-E12 -> 34250 | H12: =IF(G12=0,"NIL",IF(G12>0,"CR","DR")) -> CR
A13: 46237 | B13: PURCHASE | C13: BILL#451730 | D13: APPLE CHARGER 60W MS2 | F13: 5150 | G13: =G12+F13-E13 -> 39400 | H13: =IF(G13=0,"NIL",IF(G13>0,"CR","DR")) -> CR
A14: 46244 | B14: PAYMENT | C14: PAYMENT | D14: PAYMENT THROUGH BOP | E14: 15000 | G14: =G13+F14-E14 -> 24400 | H14: =IF(G14=0,"NIL",IF(G14>0,"CR","DR")) -> CR
A15: 46245 | B15: PURCHASE | C15: BILL#452647 | D15: DELL BATTERY D5010 | F15: 2750 | G15: =G14+F15-E15 -> 27150 | H15: =IF(G15=0,"NIL",IF(G15>0,"CR","DR")) -> CR
A16: 46247 | B16: PURCHASE | C16: BILL#452964 | D16: HP KB 840 G3 BACKLIGHT | F16: 5550 | G16: =G15+F16-E16 -> 32700 | H16: =IF(G16=0,"NIL",IF(G16>0,"CR","DR")) -> CR
A17: 46247 | B17: PURCHASE | C17: BILL#452988 | D17: BAT AC 5742 | F17: 2600 | G17: =G16+F17-E17 -> 35300 | H17: =IF(G17=0,"NIL",IF(G17>0,"CR","DR")) -> CR
A18: 46250 | B18: PURCHASE | C18: BILL#453135 | D18: BAT D15 /FAN E5440 | F18: 6200 | G18: =G17+F18-E18 -> 41500 | H18: =IF(G18=0,"NIL",IF(G18>0,"CR","DR")) -> CR
A19: 46251 | B19: PURCHASE | C19: BILL#453279 | D19: BAT TOS 3634 / KB DV6 100 | F19: 4100 | G19: =G18+F19-E19 -> 45600 | H19: =IF(G19=0,"NIL",IF(G19>0,"CR","DR")) -> CR
A20: 46256 | B20: PURCHASE | C20: BILL#45941 | D20: HP LAPTOP BODY HP SPKR KB TOS Z40 | F20: 17300 | G20: =G19+F20-E20 -> 62900 | H20: =IF(G20=0,"NIL",IF(G20>0,"CR","DR")) -> CR
A21: 46258 | B21: PURCHASE | C21: BILL#454086 | D21: KB HP 440 G3 | F21: 1450 | G21: =G20+F21-E21 -> 64350 | H21: =IF(G21=0,"NIL",IF(G21>0,"CR","DR")) -> CR
G22: =G21+F22-E22 -> 64350 | H22: =IF(G22=0,"NIL",IF(G22>0,"CR","DR")) -> CR
G23: =G22+F23-E23 -> 64350 | H23: =IF(G23=0,"NIL",IF(G23>0,"CR","DR")) -> CR
G24: =G23+F24-E24 -> 64350 | H24: =IF(G24=0,"NIL",IF(G24>0,"CR","DR")) -> CR
G25: =G24+F25-E25 -> 64350 | H25: =IF(G25=0,"NIL",IF(G25>0,"CR","DR")) -> CR
G26: =G25+F26-E26 -> 64350 | H26: =IF(G26=0,"NIL",IF(G26>0,"CR","DR")) -> CR
G27: =G26+F27-E27 -> 64350 | H27: =IF(G27=0,"NIL",IF(G27>0,"CR","DR")) -> CR
G28: =G27+F28-E28 -> 64350 | H28: =IF(G28=0,"NIL",IF(G28>0,"CR","DR")) -> CR
G29: =G28+F29-E29 -> 64350 | H29: =IF(G29=0,"NIL",IF(G29>0,"CR","DR")) -> CR
G30: =G29+F30-E30 -> 64350 | H30: =IF(G30=0,"NIL",IF(G30>0,"CR","DR")) -> CR
G31: =G30+F31-E31 -> 64350 | H31: =IF(G31=0,"NIL",IF(G31>0,"CR","DR")) -> CR
G32: =G31+F32-E32 -> 64350 | H32: =IF(G32=0,"NIL",IF(G32>0,"CR","DR")) -> CR
G33: =G32+F33-E33 -> 64350 | H33: =IF(G33=0,"NIL",IF(G33>0,"CR","DR")) -> CR
... G35: =G34+F35-E35 -> 64350 | H35: =IF(G35=0,"NIL",IF(G35>0,"CR","DR")) -> CR
D36: TOTAL BALANCE | E36: =SUM(E6:E35) -> 35000 | F36: =SUM(F6:F35) -> 75650 | G36: =G5+F36-E36 -> 64350 | H36: =IF(G36=0,"NIL",IF(G36>0,"CR","DR")) -> CR

Sheet NASNIM BHI-1
A2: Nasim Bahi Nawababad Shop | J2: PAYABLE HOME
A3: Ledger 2025
A4: DATE | B4: TYPE | C4: REF# | D4: DESCRIPTION | E4: DEBIT | F4: CREDIT | G4: BALANCE
D5: OPENING BLANCE | G5: 109280
B6: SALE | D6: DELL 19"INCH LED | E6: 7000 | F6: 0 | G6: =G5+F6-E6 -> 102280 | H6: =IF(G6=0,"NIL",IF(G6>0,"CR","DR")) -> CR
B7: SALE | D7: LAPTOP REPAING MOEEN BHAI | E7: 2500 | F7: 0 | G7: =G6+F7-E7 -> 99780 | H7: =IF(G7=0,"NIL",IF(G7>0,"CR","DR")) -> CR
B8: SALE | D8: HP BLUE PIN CHAGER | E8: 1500 | F8: 0 | G8: =G7+F8-E8 -> 98280 | H8: =IF(G8=0,"NIL",IF(G8>0,"CR","DR")) -> CR
B9: SALE | D9: HP 8440 KEYBOARD | E9: 1700 | F9: 0 | G9: =G8+F9-E9 -> 96580 | H9: =IF(G9=0,"NIL",IF(G9>0,"CR","DR")) -> CR
B10: SALE | D10: TENDA ROUTER N301 | E10: 2550 | F10: 0 | G10: =G9+F10-E10 -> 94030 | H10: =IF(G10=0,"NIL",IF(G10>0,"CR","DR")) -> CR
A11: 45554 | B11: PURCHASE | D11: SUMSUNG SSD 128GB | E11: 0 | F11: 2800 | G11: =G10+F11-E11 -> 96830 | H11: =IF(G11=0,"NIL",IF(G11>0,"CR","DR")) -> CR
A12: 45554 | B12: PURCHASE | D12: DELL CHARGER 130 WATT | E12: 0 | F12: 1150 | G12: =G11+F12-E12 -> 97980 | H12: =IF(G12=0,"NIL",IF(G12>0,"CR","DR")) -> CR
A13: 45557 | B13: PURCHASE | D13: SUMSUNG SSD 128GB | E13: 0 | F13: 2800 | G13: =G12+F13-E13 -> 100780 | H13: =IF(G13=0,"NIL",IF(G13>0,"CR","DR")) -> CR
A14: 45557 | B14: SALE | D14: 256GB NVME | E14: 4800 | F14: 0 | G14: =G13+F14-E14 -> 95980 | H14: =IF(G14=0,"NIL",IF(G14>0,"CR","DR")) -> CR
A15: 45559 | B15: PURCHASE | D15: Segate hdd 2tb pc | F15: 6500 | G15: =G14+F15-E15 -> 102480 | H15: =IF(G15=0,"NIL",IF(G15>0,"CR","DR")) -> CR
A16: 24-09-2024 | B16: PURCHASE | D16: vga cable 300*10 | F16: 3000 | G16: =G15+F16-E16 -> 105480 | H16: =IF(G16=0,"NIL",IF(G16>0,"CR","DR")) -> CR
A17: 45569 | B17: PURCHASE | D17: 128gb ssd qty-2 | F17: =2700*2 -> 5400 | G17: =G16+F17-E17 -> 110880 | H17: =IF(G17=0,"NIL",IF(G17>0,"CR","DR")) -> CR
A18: 45570 | B18: PAYMENT | D18: Cash payment to Nasim bahi | E18: 5000 | G18: =G17+F18-E18 -> 105880 | H18: =IF(G18=0,"NIL",IF(G18>0,"CR","DR")) -> CR
A19: 45573 | B19: PURCHASE | D19: i3-4th-x-500gb dell tower cpu 3020 | E19: 0 | F19: =11500 -> 11500 | G19: =G18+F19-E19 -> 117380 | H19: =IF(G19=0,"NIL",IF(G19>0,"CR","DR")) -> CR
A20: 45576 | B20: PAYMENT | C20: PAYMENT | D20: Cash payment to Nasim bahi | E20: 20000 | G20: =G19+F20-E20 -> 97380 | H20: =IF(G20=0,"NIL",IF(G20>0,"CR","DR")) -> CR
A21: 45576 | B21: PURCHASE | C21: PURCHASE | D21: LAPTOP CHARGER +HDD +PC | F21: 15250 | G21: =G20+F21-E21 -> 112630 | H21: =IF(G21=0,"NIL",IF(G21>0,"CR","DR")) -> CR
A22: 45577 | B22: SALE | D22: sff desktop i5-3rd-8-500 | E22: 12000 | G22: =G21+F22-E22 -> 100630 | H22: =IF(G22=0,"NIL",IF(G22>0,"CR","DR")) -> CR
A23: 45581 | B23: PURCHASE | C23: PURCHASE | D23: RAMS & SYSTEMS | F23: 15800 | G23: =G22+F23-E23 -> 116430 | H23: =IF(G23=0,"NIL",IF(G23>0,"CR","DR")) -> CR
A24: 45583 | B24: PURCHASE | C24: PURCHASE | D24: ACCESSORIES & LAPTOPS | F24: 192650 | G24: =G23+F24-E24 -> 309080 | H24: =IF(G24=0,"NIL",IF(G24>0,"CR","DR")) -> CR
A25: 45586 | B25: SALE | C25: SALE | D25: HDMI SIPLITER 4 PORTS | E25: 1400 | G25: =G24+F25-E25 -> 307680 | H25: =IF(G25=0,"NIL",IF(G25>0,"CR","DR")) -> CR
A26: 45586 | B26: SALE | C26: SALE | D26: HDMI TO VGA | E26: 350 | G26: =G25+F26-E26 -> 307330 | H26: =IF(G26=0,"NIL",IF(G26>0,"CR","DR")) -> CR
A27: 45591 | B27: PURCHASE | C27: PURCHASE | D27: HP 840 G3 I5-6TH-8-256 + CHARGER | F27: 47000 | G27: =G26+F27-E27 -> 354330 | H27: =IF(G27=0,"NIL",IF(G27>0,"CR","DR")) -> CR
A28: 45593 | B28: SALE | C28: SALE | D28: lcd repairing from rwp | E28: 700 | G28: =G27+F28-E28 -> 353630 | H28: =IF(G28=0,"NIL",IF(G28>0,"CR","DR")) -> CR
A29: 45594 | B29: PAYMENT | C29: PAYMENT | D29: Cash payment to Nasim bahi 5490 | E29: 44000 | G29: =G28+F29-E29 -> 309630 | H29: =IF(G29=0,"NIL",IF(G29>0,"CR","DR")) -> CR
A30: 45597 | B30: PURCHASE | C30: PURCHASE | D30: ACCESSORIES & SSD | F30: 21050 | G30: =G29+F30-E30 -> 330680 | H30: =IF(G30=0,"NIL",IF(G30>0,"CR","DR")) -> CR
A31: 45597 | B31: PAYMENT | C31: PAYMENT | D31: Cash payment to Nasim bahi 5490 | E31: 44000 | G31: =G30+F31-E31 -> 286680 | H31: =IF(G31=0,"NIL",IF(G31>0,"CR","DR")) -> CR
A32: 45600 | B32: PAYMENT | C32: PAYMENT | D32: CASH PAYMENT DELL LATITUDE 3300 | E32: 21000 | G32: =G31+F32-E32 -> 265680 | H32: =IF(G32=0,"NIL",IF(G32>0,"CR","DR")) -> CR
A33: 45600 | B33: PAYMENT | C33: PAYMENT | D33: CASH PAYMENT ACCESSORIES | E33: 10000 | G33: =G32+F33-E33 -> 255680 | H33: =IF(G33=0,"NIL",IF(G33>0,"CR","DR")) -> CR
A34: 45602 | B34: PURCHASE | C34: PURCHASE | D34: DELL D.T 7010 / L.P P.CABLES | F34: 18000 | G34: =G33+F34-E34 -> 273680 | H34: =IF(G34=0,"NIL",IF(G34>0,"CR","DR")) -> CR
A35: 45603 | B35: PAYMENT | C35: PAYMENT | D35: CASH PAYMENT | E35: 15000 | G35: =G34+F35-E35 -> 258680 | H35: =IF(G35=0,"NIL",IF(G35>0,"CR","DR")) -> CR
A36: 45603 | B36: PURCHASE | C36: PURCHASE | D36: RAMS & SSD & CHARGER | F36: 16450 | G36: =G35+F36-E36 -> 275130 | H36: =IF(G36=0,"NIL",IF(G36>0,"CR","DR")) -> CR
A37: 45607 | B37: PURCHASE | C37: PURCHASE | D37: HDD, ROUTER, SSD | F37: 12100 | G37: =G36+F37-E37 -> 287230 | H37: =IF(G37=0,"NIL",IF(G37>0,"CR","DR")) -> CR
A38: 45610 | B38: PURCHASE | C38: PURCHASE | D38: DELL CHARGER 189 WATT (BUY FRAHAN ) | F38: 1500 | G38: =G37+F38-E38 -> 288730 | H38: =IF(G38=0,"NIL",IF(G38>0,"CR","DR")) -> CR
A39: 45610 | B39: PAYMENT | C39: PAYMENT | D39: CORE 2 DUO PC LESS | E39: 2000 | G39: =G38+F39-E39 -> 286730 | H39: =IF(G39=0,"NIL",IF(G39>0,"CR","DR")) -> CR
A40: 45611 | B40: PAYMENT | C40: PAYMENT | D40: CASH PAYMENT | E40: 11500 | G40: =G39+F40-E40 -> 275230 | H40: =IF(G40=0,"NIL",IF(G40>0,"CR","DR")) -> CR
A41: 45612 | B41: PAYMENT | C41: PAYMENT | D41: HP ELITEBOOK 840 G3 i5 6th 8th 256 | E41: 47000 | G41: =G40+F41-E41 -> 228230 | H41: =IF(G41=0,"NIL",IF(G41>0,"CR","DR")) -> CR
A42: 45612 | B42: PURCHASE | C42: PURCHASE | D42: DELL 5430 I5 3rd 4/320 | F42: 18000 | G42: =G41+F42-E42 -> 246230 | H42: =IF(G42=0,"NIL",IF(G42>0,"CR","DR")) -> CR
A43: 45612 | B43: PURCHASE | C43: PURCHASE | D43: DELL 5470 I5 +D21:L436TH 8/256 | F43: 42500 | G43: =G42+F43-E43 -> 288730 | H43: =IF(G43=0,"NIL",IF(G43>0,"CR","DR")) -> CR
A44: 45612 | B44: PURCHASE | C44: PURCHASE | D44: HP ELITEBOOK 840 G3 i5 6th 8th 256 | F44: 47000 | G44: =G43+F44-E44 -> 335730 | H44: =IF(G44=0,"NIL",IF(G44>0,"CR","DR")) -> CR
A45: 45612 | B45: PURCHASE | C45: PURCHASE | D45: LENOVO T410 I5 1ST 4/250GB | F45: 13000 | G45: =G44+F45-E45 -> 348730 | H45: =IF(G45=0,"NIL",IF(G45>0,"CR","DR")) -> CR
A46: 45612 | B46: PURCHASE | C46: PURCHASE | D46: DELL 3300 4/128 | F46: 22500 | G46: =G45+F46-E46 -> 371230 | H46: =IF(G46=0,"NIL",IF(G46>0,"CR","DR")) -> CR
A47: 45615 | B47: PAYMENT | C47: PAYMENT | D47: HP ELITEBOOK 840 G3 i5 6th 8th 256 | E47: 47000 | G47: =G46+F47-E47 -> 324230 | H47: =IF(G47=0,"NIL",IF(G47>0,"CR","DR")) -> CR
A48: 45616 | B48: PURCHASE | C48: PURCHASE | D48: DELL 7490 I5 8TH 8GB/256SSD | F48: 52000 | G48: =G47+F48-E48 -> 376230 | H48: =IF(G48=0,"NIL",IF(G48>0,"CR","DR")) -> CR
A49: 45616 | B49: PURCHASE | C49: PURCHASE | D49: HP ELITEBOOK 840 G3 i5 6th 8th 256 | F49: 47000 | G49: =G48+F49-E49 -> 423230 | H49: =IF(G49=0,"NIL",IF(G49>0,"CR","DR")) -> CR
A50: 45616 | B50: PURCHASE | C50: PURCHASE | D50: HP ELITEBOOK 840 G4 i5 7th 8th 256 | F50: 59000 | G50: =G49+F50-E50 -> 482230 | H50: =IF(G50=0,"NIL",IF(G50>0,"CR","DR")) -> CR
A51: 45616 | B51: PURCHASE | C51: PURCHASE | D51: HP CHARGER CENTERNO | F51: 1700 | G51: =G50+F51-E51 -> 483930 | H51: =IF(G51=0,"NIL",IF(G51>0,"CR","DR")) -> CR
A52: 45616 | B52: PURCHASE | C52: PURCHASE | D52: DELL NEW BAG | F52: 1000 | G52: =G51+F52-E52 -> 484930 | H52: =IF(G52=0,"NIL",IF(G52>0,"CR","DR")) -> CR
A53: 45626 | B53: PAYMENT | C53: PAYMENT | D53: HP ELITEBOOK 840 G3 i5 6th 8th 256 | E53: 47000 | G53: =G52+F53-E53 -> 437930 | H53: =IF(G53=0,"NIL",IF(G53>0,"CR","DR")) -> CR
A54: 45626 | B54: RETURNE | C54: RETURNE | D54: DELL PRECISION M4800 | E54: 25000 | G54: =G53+F54-E54 -> 412930 | H54: =IF(G54=0,"NIL",IF(G54>0,"CR","DR")) -> CR
A55: 45629 | B55: PAYMENT | C55: SALE | D55: SUMSUNG USB 8GB QTY 4 | E55: 1680 | G55: =G54+F55-E55 -> 411250 | H55: =IF(G55=0,"NIL",IF(G55>0,"CR","DR")) -> CR
A56: 45629 | B56: PAYMENT | C56: PAYMENT | D56: DELL 3300 4/128 | E56: 22500 | G56: =G55+F56-E56 -> 388750 | H56: =IF(G56=0,"NIL",IF(G56>0,"CR","DR")) -> CR
A57: 45631 | B57: PAYMENT | C57: SALE | D57: HDD CASE ORICO 3.0 3 | E57: 2700 | G57: =G56+F57-E57 -> 386050 | H57: =IF(G57=0,"NIL",IF(G57>0,"CR","DR")) -> CR
A58: 45632 | B58: PURCHASE | C58: PURCHASE | D58: LAPTOPS CHARGERS | F58: 12900 | G58: =G57+F58-E58 -> 398950 | H58: =IF(G58=0,"NIL",IF(G58>0,"CR","DR")) -> CR
A59: 45638 | B59: PAYMENT | C59: SALE | D59: DESKTOP RAMS DDR3 8GB QTY 2 | E59: 4600 | G59: =G58+F59-E59 -> 394350 | H59: =IF(G59=0,"NIL",IF(G59>0,"CR","DR")) -> CR
A60: 45638 | B60: PURCHASE | C60: PURCHASE | D60: ACER LAPTOP I5 4TH 8GB/500GB HDD,CHARGER | F60: 25000 | G60: =G59+F60-E60 -> 419350 | H60: =IF(G60=0,"NIL",IF(G60>0,"CR","DR")) -> CR
A61: 45640 | B61: PAYMENT | C61: SALE | D61: VISITING CARD AND BILL BOOKS PRINTING | E61: 3660 | G61: =G60+F61-E61 -> 415690 | H61: =IF(G61=0,"NIL",IF(G61>0,"CR","DR")) -> CR
A62: 45642 | B62: PURCHASE | C62: PURCHASE | D62: HP ELITEBOOK 840 G3 i5 6th 8th 256 | F62: 47000 | G62: =G61+F62-E62 -> 462690 | H62: =IF(G62=0,"NIL",IF(G62>0,"CR","DR")) -> CR
A63: 45647 | B63: PAYMENT | C63: PAYMENT | D63: DELL 5430/7490 | E63: 70000 | G63: =G62+F63-E63 -> 392690 | H63: =IF(G63=0,"NIL",IF(G63>0,"CR","DR")) -> CR
A64: 45649 | B64: PURCHASE | C64: PURCHASE | D64: DELL 5280 I5 7TH 8/256GB | F64: 39000 | G64: =G63+F64-E64 -> 431690 | H64: =IF(G64=0,"NIL",IF(G64>0,"CR","DR")) -> CR
A65: 45649 | B65: PURCHASE | C65: PURCHASE | D65: DELL 7490 I5 8TH 8GB/256SSD | F65: 47000 | G65: =G64+F65-E65 -> 478690 | H65: =IF(G65=0,"NIL",IF(G65>0,"CR","DR")) -> CR
A66: 45649 | B66: PURCHASE | C66: PURCHASE | D66: HP PROBOOK 440 G5 I5 8TH 8GB/256SSD | F66: 49500 | G66: =G65+F66-E66 -> 528190 | H66: =IF(G66=0,"NIL",IF(G66>0,"CR","DR")) -> CR
A67: 45649 | B67: PURCHASE | C67: PURCHASE | D67: HP PROBOOK 640 G2 I5 6TH 8GB/256SSD | F67: 36500 | G67: =G66+F67-E67 -> 564690 | H67: =IF(G67=0,"NIL",IF(G67>0,"CR","DR")) -> CR
A68: 45649 | B68: PURCHASE | C68: PURCHASE | D68: DELL CHARGER / LENOVO CHARGER | F68: 4400 | G68: =G67+F68-E68 -> 569090 | H68: =IF(G68=0,"NIL",IF(G68>0,"CR","DR")) -> CR
A69: 45297 | B69: PURCHASE | C69: PURCHASE | D69: HP 850 G3 I5 7TH 8GB 256 SSD | F69: 48000 | G69: =G68+F69-E69 -> 617090 | H69: =IF(G69=0,"NIL",IF(G69>0,"CR","DR")) -> CR
A70: 45670 | B70: PAYMENT | C70: PAYMENT | D70: HP 850 G3/ACER/DELL 7490 | E70: 131000 | G70: =G69+F70-E70 -> 486090 | H70: =IF(G70=0,"NIL",IF(G70>0,"CR","DR")) -> CR
A71: 45670 | B71: PURCHASE | C71: PURCHASE | D71: DELL PRECISION 3540 I5 TH GEN 16/256 | F71: 75000 | G71: =G70+F71-E71 -> 561090 | H71: =IF(G71=0,"NIL",IF(G71>0,"CR","DR")) -> CR
A72: 45670 | B72: PURCHASE | C72: PURCHASE | D72: DELL 7490 I5 8TH 8GB/256SSD | F72: 47000 | G72: =G71+F72-E72 -> 608090 | H72: =IF(G72=0,"NIL",IF(G72>0,"CR","DR")) -> CR
A73: 45670 | B73: PURCHASE | C73: PURCHASE | D73: LENOVO T480 I5 8TH 16/256GB | F73: 51000 | G73: =G72+F73-E73 -> 659090 | H73: =IF(G73=0,"NIL",IF(G73>0,"CR","DR")) -> CR
A74: 45673 | B74: PURCHASE | C74: PURCHASE | D74: DELL /HP CHARGER | F74: 4100 | G74: =G73+F74-E74 -> 663190 | H74: =IF(G74=0,"NIL",IF(G74>0,"CR","DR")) -> CR
A75: 45678 | B75: PAYMENT | C75: PAYMENT | D75: DELL 5470/HP 840G3/440G5/850G3 | E75: 187000 | G75: =G74+F75-E75 -> 476190 | H75: =IF(G75=0,"NIL",IF(G75>0,"CR","DR")) -> CR
A76: 45679 | B76: PURCHASE | C76: PURCHASE | D76: DELL 3580 I5 7TH 8GB 256SSD | F76: 47000 | G76: =G75+F76-E76 -> 523190 | H76: =IF(G76=0,"NIL",IF(G76>0,"CR","DR")) -> CR
A77: 45679 | B77: PURCHASE | C77: PURCHASE | D77: HP 840 G3 I5-6TH-8-256 + CHARGER | F77: 47000 | G77: =G76+F77-E77 -> 570190 | H77: =IF(G77=0,"NIL",IF(G77>0,"CR","DR")) -> CR
A78: 45679 | B78: PURCHASE | C78: PURCHASE | D78: HP 850 G3 I5 7TH 8GB 256 SSD | F78: 48000 | G78: =G77+F78-E78 -> 618190 | H78: =IF(G78=0,"NIL",IF(G78>0,"CR","DR")) -> CR
A79: 45679 | B79: PURCHASE | C79: PURCHASE | D79: DELL 5470 I5 6TH 8GB 256 | F79: 39000 | G79: =G78+F79-E79 -> 657190 | H79: =IF(G79=0,"NIL",IF(G79>0,"CR","DR")) -> CR
A80: 45686 | B80: PURCHASE | C80: PURCHASE | D80: HP 840 G5 I5 7TH /DELL DESKTOP 755 | F80: 66500 | G80: =G79+F80-E80 -> 723690 | H80: =IF(G80=0,"NIL",IF(G80>0,"CR","DR")) -> CR
A81: 45689 | B81: PAYMENT | C81: PAYMENT | D81: DELL 3580/640G2/850 G3 | E81: 131500 | G81: =G80+F81-E81 -> 592190 | H81: =IF(G81=0,"NIL",IF(G81>0,"CR","DR")) -> CR
A82: 45689 | B82: PAYMENT | C82: PAYMENT | D82: DELL 7490 BATTERY ADJUST | E82: 3000 | G82: =G81+F82-E82 -> 589190 | H82: =IF(G82=0,"NIL",IF(G82>0,"CR","DR")) -> CR
A83: 45689 | B83: PURCHASE | C83: PURCHASE | D83: HP ELITEBOOK 840 G3 i5 6th 8th 256 | F83: 47000 | G83: =G82+F83-E83 -> 636190 | H83: =IF(G83=0,"NIL",IF(G83>0,"CR","DR")) -> CR
A84: 45689 | B84: PURCHASE | C84: PURCHASE | D84: HP PROOBOOK 640 G1 I5 4TH 8/128/500 | F84: 31000 | G84: =G83+F84-E84 -> 667190 | H84: =IF(G84=0,"NIL",IF(G84>0,"CR","DR")) -> CR
A85: 45699 | B85: PAYMENT | C85: PAYMENT | D85: LENOVO 410/HP 840 G3 /840 G5 | E85: 122000 | G85: =G84+F85-E85 -> 545190 | H85: =IF(G85=0,"NIL",IF(G85>0,"CR","DR")) -> CR
A86: 45710 | B86: PURCHASE | C86: PURCHASE | D86: DELL XPS I3 5TH 4GB 128GB | F86: 34000 | G86: =G85+F86-E86 -> 579190 | H86: =IF(G86=0,"NIL",IF(G86>0,"CR","DR")) -> CR
A87: 45710 | B87: PURCHASE | C87: PURCHASE | D87: DELL 7480 I5 7TH GEN 16GB/256SSD | F87: 51000 | G87: =G86+F87-E87 -> 630190 | H87: =IF(G87=0,"NIL",IF(G87>0,"CR","DR")) -> CR
A88: 45710 | B88: PURCHASE | C88: PURCHASE | D88: DELL XPS 15 9560 I7 7TH GEN 8GB 256SSD | F88: 90000 | G88: =G87+F88-E88 -> 720190 | H88: =IF(G88=0,"NIL",IF(G88>0,"CR","DR")) -> CR
A89: 45710 | B89: PURCHASE | C89: PURCHASE | D89: HP PROBOOK 450 G2 I5 5TH 8GB.500GB | F89: 35500 | G89: =G88+F89-E89 -> 755690 | H89: =IF(G89=0,"NIL",IF(G89>0,"CR","DR")) -> CR
A90: 45710 | B90: PURCHASE | C90: PURCHASE | D90: LENOVO 360 I5 6TH 8GB 256SSD | F90: 42000 | G90: =G89+F90-E90 -> 797690 | H90: =IF(G90=0,"NIL",IF(G90>0,"CR","DR")) -> CR
A91: 45710 | B91: PURCHASE | C91: PURCHASE | D91: LENOVO T440 I5 4TH 4GB 500GB | F91: 25500 | G91: =G90+F91-E91 -> 823190 | H91: =IF(G91=0,"NIL",IF(G91>0,"CR","DR")) -> CR
A92: 45710 | B92: PURCHASE | C92: PURCHASE | D92: DELL 5500 I5 8TH 8GB 256SSD | F92: 55000 | G92: =G91+F92-E92 -> 878190 | H92: =IF(G92=0,"NIL",IF(G92>0,"CR","DR")) -> CR
A93: 45710 | B93: PURCHASE | C93: PURCHASE | D93: HP PROBOOK 430 G3 8GB/256SSD | F93: 40000 | G93: =G92+F93-E93 -> 918190 | H93: =IF(G93=0,"NIL",IF(G93>0,"CR","DR")) -> CR
A94: 45710 | B94: PURCHASE | C94: PURCHASE | D94: HP NOOTBOOK 250 G6 I5 7TH 8GB/500 | F94: 39000 | G94: =G93+F94-E94 -> 957190 | H94: =IF(G94=0,"NIL",IF(G94>0,"CR","DR")) -> CR
A95: 45713 | B95: PAYMENT | C95: PAYMENT | D95: HP RAZON 8/256/DELL 5470 | E95: 82000 | G95: =G94+F95-E95 -> 875190 | H95: =IF(G95=0,"NIL",IF(G95>0,"CR","DR")) -> CR
A96: 45726 | B96: PAYMENT | C96: PAYMENT | D96: LENOVO T480 I5 8TH 16/256GB | E96: 51000 | G96: =G95+F96-E96 -> 824190 | H96: =IF(G96=0,"NIL",IF(G96>0,"CR","DR")) -> CR
A97: 45737 | B97: PAYMENT | C97: PAYMENT | D97: DELL PRECISION 3540 I5 TH GEN 16/256 | E97: 60000 | G97: =G96+F97-E97 -> 764190 | H97: =IF(G97=0,"NIL",IF(G97>0,"CR","DR")) -> CR
A98: 45739 | B98: PAYMENT | C98: PAYMENT | D98: DAHWA CAT 6 / TENDA 8 PORT 2 | E98: 11700 | G98: =G97+F98-E98 -> 752490 | H98: =IF(G98=0,"NIL",IF(G98>0,"CR","DR")) -> CR
A99: 45756 | B99: PAYMENT | C99: PAYMENT | D99: HP G3/G1/LENVO TOUCH I5 6TH | E99: 120000 | G99: =G98+F99-E99 -> 632490 | H99: =IF(G99=0,"NIL",IF(G99>0,"CR","DR")) -> CR
A100: 45759 | B100: PURCHASE | C100: PURCHASE | D100: HP 640 G2 /DELL 5480 /HP 640 G1 | F100: 101500 | G100: =G99+F100-E100 -> 733990 | H100: =IF(G100=0,"NIL",IF(G100>0,"CR","DR")) -> CR
A101: 45763 | B101: =$B$99 -> PAYMENT | C101: PAYMENT | D101: PAYMENT | E101: 40000 | G101: =G100+F101-E101 -> 693990 | H101: =IF(G101=0,"NIL",IF(G101>0,"CR","DR")) -> CR
...

Sheet NASNIM BHI-2
A2: Nasim Bahi Nawababad Shop | J2: PAYABLE HOME
A3: Ledger 2025
A4: DATE | B4: TYPE | C4: REF# | D4: DESCRIPTION | E4: DEBIT | F4: CREDIT | G4: BALANCE
D5: OPENING BLANCE | G5: ='NASNIM BHI-1'!G132 -> 1098540
A6: 45832 | B6: PURCHASE | C6: PURCHASE | D6: DELL NEW PIN | F6: 1100 | G6: =G5+F6-E6 -> 1099640 | H6: =IF(G6=0,"NIL",IF(G6>0,"CR","DR")) -> CR
A7: 45832 | B7: PURCHASE | C7: PURCHASE | D7: LENOVO USB 850*5 | F7: 4250 | G7: =G6+F7-E7 -> 1103890 | H7: =IF(G7=0,"NIL",IF(G7>0,"CR","DR")) -> CR
A8: 45832 | B8: PURCHASE | C8: PURCHASE | D8: DELL 130W 1100*6 | F8: 6600 | G8: =G7+F8-E8 -> 1110490 | H8: =IF(G8=0,"NIL",IF(G8>0,"CR","DR")) -> CR
A9: 45832 | B9: PURCHASE | C9: PURCHASE | D9: HP BLUE PIN 1250*6 | F9: 7500 | G9: =G8+F9-E9 -> 1117990 | H9: =IF(G9=0,"NIL",IF(G9>0,"CR","DR")) -> CR
A10: 45832 | B10: PURCHASE | C10: PURCHASE | D10: HP CENTROIN 900*6 | F10: 5400 | G10: =G9+F10-E10 -> 1123390 | H10: =IF(G10=0,"NIL",IF(G10>0,"CR","DR")) -> CR
A11: 45836 | B11: PURCHASE | C11: PURCHASE | D11: LENOVO E450 I3 5TH GEN 8GB 500GB | F11: 24000 | G11: =G10+F11-E11 -> 1147390 | H11: =IF(G11=0,"NIL",IF(G11>0,"CR","DR")) -> CR
A12: 45836 | B12: PURCHASE | C12: PURCHASE | D12: LENOVO E450 I3 5TH GEN 8GB 500GB | F12: 24000 | G12: =G11+F12-E12 -> 1171390 | H12: =IF(G12=0,"NIL",IF(G12>0,"CR","DR")) -> CR
A13: 45836 | B13: PURCHASE | C13: PURCHASE | D13: DELL LATITUDE 5410 I5 10TH 8GB 256SSD | F13: 58000 | G13: =G12+F13-E13 -> 1229390 | H13: =IF(G13=0,"NIL",IF(G13>0,"CR","DR")) -> CR
A14: 45836 | B14: PURCHASE | C14: PURCHASE | D14: DELL XPS I7 7TH GEN 16GB 512SSD TOUCH | F14: 68000 | G14: =G13+F14-E14 -> 1297390 | H14: =IF(G14=0,"NIL",IF(G14>0,"CR","DR")) -> CR
A15: 45846 | B15: PURCHASE | C15: PURCHASE | D15: SSD 128/256/Power cable /DELL NEW PIN CHARGER | F15: 10900 | G15: =G14+F15-E15 -> 1308290 | H15: =IF(G15=0,"NIL",IF(G15>0,"CR","DR")) -> CR
A16: 45847 | B16: PAYMENT | C16: PAYMENT | D16: CASH PAYMENT | E16: 80000 | G16: =G15+F16-E16 -> 1228290 | H16: =IF(G16=0,"NIL",IF(G16>0,"CR","DR")) -> CR
A17: 45847 | B17: PURCHASE | C17: PURCHASE | D17: DELL LATITUDE 3540 I5 4TH 8GB 120SSD | F17: 26000 | G17: =G16+F17-E17 -> 1254290 | H17: =IF(G17=0,"NIL",IF(G17>0,"CR","DR")) -> CR
A18: 45850 | B18: PAYMENT | C18: PAYMENT | D18: DELL 17 INCH | E18: 5000 | G18: =G17+F18-E18 -> 1249290 | H18: =IF(G18=0,"NIL",IF(G18>0,"CR","DR")) -> CR
A19: 45850 | B19: PAYMENT | C19: PAYMENT | D19: HP ELITEBOOK 840 G2 | E19: 30000 | G19: =G18+F19-E19 -> 1219290 | H19: =IF(G19=0,"NIL",IF(G19>0,"CR","DR")) -> CR
A20: 45850 | B20: PAYMENT | C20: PAYMENT | D20: DELL 6540 I7 4TH 8GB 500GB | E20: 28500 | G20: =G19+F20-E20 -> 1190790 | H20: =IF(G20=0,"NIL",IF(G20>0,"CR","DR")) -> CR
A21: 45850 | B21: PAYMENT | C21: PAYMENT | D21: LENOVO E450 I3 5TH GEN 8GB 500GB | E21: 24000 | G21: =G20+F21-E21 -> 1166790 | H21: =IF(G21=0,"NIL",IF(G21>0,"CR","DR")) -> CR
A22: 45852 | B22: PURCHASE | C22: PURCHASE | D22: ACER P658 I7 6TH 8GB 256GB SSD | F22: 39000 | G22: =G21+F22-E22 -> 1205790 | H22: =IF(G22=0,"NIL",IF(G22>0,"CR","DR")) -> CR
A23: 45852 | B23: PURCHASE | C23: PURCHASE | D23: DELL 3570 I3 6TH GEN 8GB 500GB | F23: 28500 | G23: =G22+F23-E23 -> 1234290 | H23: =IF(G23=0,"NIL",IF(G23>0,"CR","DR")) -> CR
A24: 45852 | B24: PURCHASE | C24: PURCHASE | D24: DELL 5570 I3 6TH GEN 8GB 500GB | F24: 28500 | G24: =G23+F24-E24 -> 1262790 | H24: =IF(G24=0,"NIL",IF(G24>0,"CR","DR")) -> CR
A25: 45871 | B25: RETURNE | C25: RETURNE | D25: DELL XPS I7 7TH GEN 16GB 512SSD TOUCH | E25: 68000 | G25: =G24+F25-E25 -> 1194790 | H25: =IF(G25=0,"NIL",IF(G25>0,"CR","DR")) -> CR
A26: 45871 | B26: RETURNE | C26: RETURNE | D26: CASH PAYMENT | E26: 70000 | G26: =G25+F26-E26 -> 1124790 | H26: =IF(G26=0,"NIL",IF(G26>0,"CR","DR")) -> CR
A27: 45130 | B27: PAYMENT | C27: PAYMENT | D27: CASH PAYMENT | E27: 8700 | G27: =G26+F27-E27 -> 1116090 | H27: =IF(G27=0,"NIL",IF(G27>0,"CR","DR")) -> CR
A28: 45874 | B28: PAYMENT | C28: PAYMENT | D28: CASH PAYMENT | E28: 30000 | G28: =G27+F28-E28 -> 1086090 | H28: =IF(G28=0,"NIL",IF(G28>0,"CR","DR")) -> CR
A29: 45884 | B29: PAYMENT | C29: PAYMENT | D29: CASH PAYMENT | E29: 115500 | G29: =G28+F29-E29 -> 970590 | H29: =IF(G29=0,"NIL",IF(G29>0,"CR","DR")) -> CR
A30: 45885 | B30: PURCHASE | C30: PURCHASE | D30: HP 440 G5 I5 7TH GEN 8GB 256GB | F30: 44500 | G30: =G29+F30-E30 -> 1015090 | H30: =IF(G30=0,"NIL",IF(G30>0,"CR","DR")) -> CR
A31: 45885 | B31: PURCHASE | C31: PURCHASE | D31: HP ELITEBOOK 840 G3 I5 6TH 8GB 256GB | F31: 39000 | G31: =G30+F31-E31 -> 1054090 | H31: =IF(G31=0,"NIL",IF(G31>0,"CR","DR")) -> CR
A32: 45885 | B32: PURCHASE | C32: PURCHASE | D32: DELL LATITUDE I5 8TH GEN 8GB 256GB SSD | F32: 48000 | G32: =G31+F32-E32 -> 1102090 | H32: =IF(G32=0,"NIL",IF(G32>0,"CR","DR")) -> CR
A33: 45894 | B33: PAYMENT | C33: PAYMENT | D33: CASH PAYMENT | E33: 30000 | G33: =G32+F33-E33 -> 1072090 | H33: =IF(G33=0,"NIL",IF(G33>0,"CR","DR")) -> CR
A34: 45900 | B34: PAYMENT | C34: PAYMENT | D34: CASH PAYMENT | E34: 40000 | G34: =G33+F34-E34 -> 1032090 | H34: =IF(G34=0,"NIL",IF(G34>0,"CR","DR")) -> CR
A35: 45902 | B35: RETURNE | C35: RETURNE | D35: DELL LATITUDE 3500 Return | E35: 48000 | G35: =G34+F35-E35 -> 984090 | H35: =IF(G35=0,"NIL",IF(G35>0,"CR","DR")) -> CR
A36: 45907 | B36: PURCHASE | C36: PURCHASE | D36: DELL LATITUDE 5280 I5 7TH 8/256 W/C | F36: 42000 | G36: =G35+F36-E36 -> 1026090 | H36: =IF(G36=0,"NIL",IF(G36>0,"CR","DR")) -> CR
A37: 45907 | B37: PURCHASE | C37: PURCHASE | D37: DELL LATITUDE 5480 I5 7TH 8/256 W/C | F37: 46000 | G37: =G36+F37-E37 -> 1072090 | H37: =IF(G37=0,"NIL",IF(G37>0,"CR","DR")) -> CR
A38: 45907 | B38: PURCHASE | C38: PURCHASE | D38: DELL LATITUDE 3480 I3 7TH 8/256 W/C | F38: 33000 | G38: =G37+F38-E38 -> 1105090 | H38: =IF(G38=0,"NIL",IF(G38>0,"CR","DR")) -> CR
A39: 45907 | B39: PURCHASE | C39: PURCHASE | D39: DELL LATITUDE 5490 I5 8TH 8/256 W/C | F39: 47000 | G39: =G38+F39-E39 -> 1152090 | H39: =IF(G39=0,"NIL",IF(G39>0,"CR","DR")) -> CR
A40: 45907 | B40: PURCHASE | C40: PURCHASE | D40: DELL LATITUDE 5470 I5 6TH 8/256 W/C | F40: 39000 | G40: =G39+F40-E40 -> 1191090 | H40: =IF(G40=0,"NIL",IF(G40>0,"CR","DR")) -> CR
A41: 45908 | B41: PAYMENT | C41: PAYMENT | D41: CASH PAYMENT SEND PBM ACCOUNT ISB | E41: 100000 | G41: =G40+F41-E41 -> 1091090 | H41: =IF(G41=0,"NIL",IF(G41>0,"CR","DR")) -> CR
A42: 45908 | B42: PAYMENT | C42: PAYMENT | D42: CASH PAYMENT SEND PBM ACCOUNT ISB | E42: 50000 | G42: =G41+F42-E42 -> 1041090 | H42: =IF(G42=0,"NIL",IF(G42>0,"CR","DR")) -> CR
A43: 45909 | B43: PAYMENT | C43: PAYMENT | D43: CASH PAYMENT | E43: 50000 | G43: =G42+F43-E43 -> 991090 | H43: =IF(G43=0,"NIL",IF(G43>0,"CR","DR")) -> CR
A44: 45938 | B44: PAYMENT | C44: PAYMENT | D44: CASH PAYMENT | E44: 80000 | G44: =G43+F44-E44 -> 911090 | H44: =IF(G44=0,"NIL",IF(G44>0,"CR","DR")) -> CR
A45: 45950 | B45: PAYMENT | C45: PAYMENT | D45: CASH PAYMENT | E45: 45000 | G45: =G44+F45-E45 -> 866090 | H45: =IF(G45=0,"NIL",IF(G45>0,"CR","DR")) -> CR
A46: 45978 | B46: PAYMENT | C46: PAYMENT | D46: CASH PAYMENT | E46: 50000 | G46: =G45+F46-E46 -> 816090 | H46: =IF(G46=0,"NIL",IF(G46>0,"CR","DR")) -> CR
A47: 46017 | B47: PAYMENT | C47: PAYMENT | D47: CASH PAYMENT | E47: 50000 | G47: =G46+F47-E47 -> 766090 | H47: =IF(G47=0,"NIL",IF(G47>0,"CR","DR")) -> CR
A48: 46017 | B48: PURCHASE | C48: PURCHASE | D48: HP 840 G2 I5 5TH 8GB 500GB | F48: 30000 | G48: =G47+F48-E48 -> 796090 | H48: =IF(G48=0,"NIL",IF(G48>0,"CR","DR")) -> CR
A49: 46017 | B49: PURCHASE | C49: PURCHASE | D49: DELL 6440 174TH 8GB 500GB | F49: 30000 | G49: =G48+F49-E49 -> 826090 | H49: =IF(G49=0,"NIL",IF(G49>0,"CR","DR")) -> CR
A50: 46002 | B50: PAYMENT | C50: PAYMENT | D50: CASH PAYMENT | E50: 40000 | G50: =G49+F50-E50 -> 786090 | H50: =IF(G50=0,"NIL",IF(G50>0,"CR","DR")) -> CR
A51: 45840 | B51: RETURNE | C51: RETURNE | D51: LAPTOPS RETURE | E51: 196000 | G51: =G50+F51-E51 -> 590090 | H51: =IF(G51=0,"NIL",IF(G51>0,"CR","DR")) -> CR
G52: =G51+F52-E52 -> 590090 | H52: =IF(G52=0,"NIL",IF(G52>0,"CR","DR")) -> CR
G53: =G52+F53-E53 -> 590090 | H53: =IF(G53=0,"NIL",IF(G53>0,"CR","DR")) -> CR
G54: =G53+F54-E54 -> 590090 | H54: =IF(G54=0,"NIL",IF(G54>0,"CR","DR")) -> CR
G55: =G54+F55-E55 -> 590090 | H55: =IF(G55=0,"NIL",IF(G55>0,"CR","DR")) -> CR
G56: =G55+F56-E56 -> 590090 | H56: =IF(G56=0,"NIL",IF(G56>0,"CR","DR")) -> CR
G57: =G56+F57-E57 -> 590090 | H57: =IF(G57=0,"NIL",IF(G57>0,"CR","DR")) -> CR
G58: =G57+F58-E58 -> 590090 | H58: =IF(G58=0,"NIL",IF(G58>0,"CR","DR")) -> CR
G59: =G58+F59-E59 -> 590090 | H59: =IF(G59=0,"NIL",IF(G59>0,"CR","DR")) -> CR
G60: =G59+F60-E60 -> 590090 | H60: =IF(G60=0,"NIL",IF(G60>0,"CR","DR")) -> CR
G61: =G60+F61-E61 -> 590090 | H61: =IF(G61=0,"NIL",IF(G61>0,"CR","DR")) -> CR
G62: =G61+F62-E62 -> 590090 | H62: =IF(G62=0,"NIL",IF(G62>0,"CR","DR")) -> CR
G63: =G62+F63-E63 -> 590090 | H63: =IF(G63=0,"NIL",IF(G63>0,"CR","DR")) -> CR
... G131: =G130+F131-E131 -> 590090 | H131: =IF(G131=0,"NIL",IF(G131>0,"CR","DR")) -> CR
D132: TOTAL BALANCE | E132: =SUM(E6:E131) -> 1238700 | F132: =SUM(F6:F131) -> 730250 | G132: =G5+F132-E132 -> 590090 | H132: =IF(G132=0,"NIL",IF(G132>0,"CR","DR")) -> CR

Sheet Abdul Rafay
A1: TASNIM COMPUTERS SALES & SERVICE
A2: Abdul Rafay | L2: PAYABLE HOME
A3: Ledger
A4: DATE | B4: TYPE | C4: REF# | D4: DESCRIPTION | E4: QTY | F4: RATE | G4: DEBIT | H4: CREDIT | I4: BALANCE
I5: 0
A6: 45590 | B6: PURCHASE | D6: Gtx 350 MouseKeyboard Combo | E6: 1 | F6: 1580 | H6: =E6*F6 -> 1580 | I6: =I5+H6-G6 -> 1580 | J6: =IF(I6=0,"NIL",IF(I6>0,"CR","DR")) -> CR
A7: 45590 | B7: PURCHASE | D7: Aula Mechanical BrownBox | E7: 1 | F7: 3950 | H7: =E7*F7 -> 3950 | I7: =I6+H7-G7 -> 5530 | J7: =IF(I7=0,"NIL",IF(I7>0,"CR","DR")) -> CR
A8: 45590 | B8: PURCHASE | D8: Ocg Mechanical Keyboard | E8: 1 | F8: 4200 | H8: =E8*F8 -> 4200 | I8: =I7+H8-G8 -> 9730 | J8: =IF(I8=0,"NIL",IF(I8>0,"CR","DR")) -> CR
A9: 45590 | B9: PURCHASE | D9: Jedel K500+ | E9: 2 | F9: 1580 | H9: =E9*F9 -> 3160 | I9: =I8+H9-G9 -> 12890 | J9: =IF(I9=0,"NIL",IF(I9>0,"CR","DR")) -> CR
A10: 45590 | B10: PURCHASE | D10: Luminous Membrane Gaming | E10: 1 | F10: 1550 | H10: =E10*F10 -> 1550 | I10: =I9+H10-G10 -> 14440 | J10: =IF(I10=0,"NIL",IF(I10>0,"CR","DR")) -> CR
A11: 45590 | B11: PURCHASE | D11: Marvo K607 | E11: 2 | F11: 1650 | H11: =E11*F11 -> 3300 | I11: =I10+H11-G11 -> 17740 | J11: =IF(I11=0,"NIL",IF(I11>0,"CR","DR")) -> CR
A12: 45590 | B12: PURCHASE | D12: Bnda Km99 Mouse Keyboard Combo | E12: 2 | F12: 1580 | H12: =E12*F12 -> 3160 | I12: =I11+H12-G12 -> 20900 | J12: =IF(I12=0,"NIL",IF(I12>0,"CR","DR")) -> CR
A13: 45590 | B13: PURCHASE | D13: Phillips White Keyboard | E13: 1 | F13: 3800 | H13: =E13*F13 -> 3800 | I13: =I12+H13-G13 -> 24700 | J13: =IF(I13=0,"NIL",IF(I13>0,"CR","DR")) -> CR
A14: 45590 | B14: PURCHASE | D14: Hp Gk400 Ey Mechanical Keyboard | E14: 2 | F14: 3800 | H14: =E14*F14 -> 7600 | I14: =I13+H14-G14 -> 32300 | J14: =IF(I14=0,"NIL",IF(I14>0,"CR","DR")) -> CR
A15: 45590 | B15: PURCHASE | D15: Monster Office Use Mouse Keyboard Combo | E15: 1 | F15: 2250 | H15: =E15*F15 -> 2250 | I15: =I14+H15-G15 -> 34550 | J15: =IF(I15=0,"NIL",IF(I15>0,"CR","DR")) -> CR
A16: 45590 | B16: PURCHASE | D16: Zidli Zm K60 Office Use Mouse Keyboard Wireless | E16: 2 | F16: 2180 | H16: =E16*F16 -> 4360 | I16: =I15+H16-G16 -> 38910 | J16: =IF(I16=0,"NIL",IF(I16>0,"CR","DR")) -> CR
A17: 45590 | B17: PURCHASE | D17: Brown Box MouseKeyboard Combo Black | E17: 1 | F17: 1750 | H17: =E17*F17 -> 1750 | I17: =I16+H17-G17 -> 40660 | J17: =IF(I17=0,"NIL",IF(I17>0,"CR","DR")) -> CR
... A23: 45590 | B23: PURCHASE | D23: Onikum K18 | E23: 1 | F23: 1280 | H23: =E23*F23 -> 1280 | I23: =I22+H23-G23 -> 64040 | J23: =IF(I23=0,"NIL",IF(I23>0,"CR","DR")) -> CR
A24: 45590 | B24: PURCHASE | D24: Audeeo Velocity Wired Gaming Mouse | E24: 4 | F24: 1180 | H24: =E24*F24 -> 4720 | I24: =I23+H24-G24 -> 68760 | J24: =IF(I24=0,"NIL",IF(I24>0,"CR","DR")) -> CR | K24: 1
A25: 45590 | B25: PURCHASE | D25: Altec Lancing Algm9002 | E25: 2 | F25: 2950 | H25: =E25*F25 -> 5900 | I25: =I24+H25-G25 -> 74660 | J25: =IF(I25=0,"NIL",IF(I25>0,"CR","DR")) -> CR
A26: 45590 | B26: PURCHASE | D26: Bebk G13 Plastic Box | E26: 2 | F26: 2200 | H26: =E26*F26 -> 4400 | I26: =I25+H26-G26 -> 79060 | J26: =IF(I26=0,"NIL",IF(I26>0,"CR","DR")) -> CR
A27: 45590 | B27: PURCHASE | D27: Oex Gaming White Black | E27: 2 | F27: 1550 | H27: =E27*F27 -> 3100 | I27: =I26+H27-G27 -> 82160 | J27: =IF(I27=0,"NIL",IF(I27>0,"CR","DR")) -> CR
A28: 45590 | B28: PURCHASE | D28: Wireless Gaming Mouse | E28: 4 | F28: 1050 | H28: =E28*F28 -> 4200 | I28: =I27+H28-G28 -> 86360 | J28: =IF(I28=0,"NIL",IF(I28>0,"CR","DR")) -> CR
A29: 45590 | B29: PURCHASE | D29: Bengo km-1 | E29: 2 | F29: 1600 | H29: =E29*F29 -> 3200 | I29: =I28+H29-G29 -> 89560 | J29: =IF(I29=0,"NIL",IF(I29>0,"CR","DR")) -> CR
A30: 45590 | B30: PURCHASE | D30: Oex Ms-320 | E30: 2 | F30: 1850 | H30: =E30*F30 -> 3700 | I30: =I29+H30-G30 -> 93260 | J30: =IF(I30=0,"NIL",IF(I30>0,"CR","DR")) -> CR
A31: 45590 | B31: PURCHASE | D31: Ega Type M-6 | E31: 2 | F31: 1550 | H31: =E31*F31 -> 3100 | I31: =I30+H31-G31 -> 96360 | J31: =IF(I31=0,"NIL",IF(I31>0,"CR","DR")) -> CR
A32: 45590 | B32: PURCHASE | D32: Mars Gaming MM 218 | E32: 1 | F32: 2200 | H32: =E32*F32 -> 2200 | I32: =I31+H32-G32 -> 98560 | J32: =IF(I32=0,"NIL",IF(I32>0,"CR","DR")) -> CR
A33: 45590 | B33: PURCHASE | D33: Evoke X39 | E33: 1 | F33: 2050 | H33: =E33*F33 -> 2050 | I33: =I32+H33-G33 -> 100610 | J33: =IF(I33=0,"NIL",IF(I33>0,"CR","DR")) -> CR
A34: 45590 | B34: PURCHASE | D34: Panteon Ms 70 | E34: 1 | F34: 1850 | H34: =E34*F34 -> 1850 | I34: =I33+H34-G34 -> 102460 | J34: =IF(I34=0,"NIL",IF(I34>0,"CR","DR")) -> CR
A35: 45590 | B35: PURCHASE | D35: Corsair Sabre Pro Rgb Champion Edition | E35: 1 | F35: 6400 | H35: =E35*F35 -> 6400 | I35: =I34+H35-G35 -> 108860 | J35: =IF(I35=0,"NIL",IF(I35>0,"CR","DR")) -> CR
A36: 45590 | B36: PURCHASE | D36: Pioneer Xg 73 | E36: 3 | F36: 365 | H36: =E36*F36 -> 1095 | I36: =I35+H36-G36 -> 109955 | J36: =IF(I36=0,"NIL",IF(I36>0,"CR","DR")) -> CR
... A42: 45590 | B42: PURCHASE | D42: Aukey Webcam 1080p | E42: 1 | F42: 2800 | H42: =E42*F42 -> 2800 | I42: =I41+H42-G42 -> 121425 | J42: =IF(I42=0,"NIL",IF(I42>0,"CR","DR")) -> CR
A43: 45607 | B43: PAYMENT | D43: 2 MOUSE PAYMENT | E43: 2 | G43: 1550 | H43: =E43*F43 -> 0 | I43: =I42+H43-G43 -> 119875 | J43: =IF(I43=0,"NIL",IF(I43>0,"CR","DR")) -> CR
A44: 45605 | B44: PURCHASE | D44: KEYBOARD TKL K-11 SMALL X1 | E44: 1 | F44: 1450 | H44: =E44*F44 -> 1450 | I44: =I43+H44-G44 -> 121325 | J44: =IF(I44=0,"NIL",IF(I44>0,"CR","DR")) -> CR
A45: 45605 | B45: PURCHASE | D45: KEYBOARD OOK-102 FULL GAMING | E45: 1 | F45: 1360 | H45: =E45*F45 -> 1360 | I45: =I44+H45-G45 -> 122685 | J45: =IF(I45=0,"NIL",IF(I45>0,"CR","DR")) -> CR
A46: 45605 | B46: PURCHASE | D46: HEADPHONE ZIDLI L-3 | E46: 1 | F46: 2180 | H46: =E46*F46 -> 2180 | I46: =I45+H46-G46 -> 124865 | J46: =IF(I46=0,"NIL",IF(I46>0,"CR","DR")) -> CR
A47: 45610 | B47: PURCHASE | D47: WEB CAM AUKEY 1080P | E47: 2 | F47: 2800 | H47: =E47*F47 -> 5600 | I47: =I46+H47-G47 -> 130465 | J47: =IF(I47=0,"NIL",IF(I47>0,"CR","DR")) -> CR
A48: 45611 | B48: PAYMENT | D48: AUKEY WEB CAM 1080P | E48: 2 | G48: 5600 | H48: =E48*F48 -> 0 | I48: =I47+H48-G48 -> 124865 | J48: =IF(I48=0,"NIL",IF(I48>0,"CR","DR")) -> CR
A49: 45642 | B49: PAYMENT | D49: KEYBOARD/MOUSE/GAMING | E49: 3 | G49: 5110 | H49: =E49*F49 -> 0 | I49: =I48+H49-G49 -> 119755 | J49: =IF(I49=0,"NIL",IF(I49>0,"CR","DR")) -> CR
A50: 45642 | B50: RETURE | C50: RETURE | D50: WEB CAM AUKEY 1080P | E50: 1 | G50: 2800 | H50: =E50*F50 -> 0 | I50: =I49+H50-G50 -> 116955 | J50: =IF(I50=0,"NIL",IF(I50>0,"CR","DR")) -> CR
A51: 45660 | B51: RETURE | C51: RETURE | D51: Onikum K18 | E51: 1 | G51: 1280 | H51: =E51*F51 -> 0 | I51: =I50+H51-G51 -> 115675 | J51: =IF(I51=0,"NIL",IF(I51>0,"CR","DR")) -> CR
A52: 45667 | B52: PAYMENT | D52: KEYBOARD/MOUSE/GAMING | G52: 6800 | H52: =E52*F52 -> 0 | I52: =I51+H52-G52 -> 108875 | J52: =IF(I52=0,"NIL",IF(I52>0,"CR","DR")) -> CR
A53: 45681 | B53: RETURE | C53: RETURE | D53: Ocg Mechanical Keyboard/ GAMING MOUSE G13 | E53: 2 | G53: 8300 | H53: =E53*F53 -> 0 | I53: =I52+H53-G53 -> 100575 | J53: =IF(I53=0,"NIL",IF(I53>0,"CR","DR")) -> CR
A54: 45708 | B54: PAYMENT | D54: KEYBOARD/MOUSE/GAMING | G54: 5860 | H54: =E54*F54 -> 0 | I54: =I53+H54-G54 -> 94715 | J54: =IF(I54=0,"NIL",IF(I54>0,"CR","DR")) -> CR
A55: 45732 | B55: PAYMENT | D55: Phillips White Keyboard | E55: 1 | G55: 3800 | H55: =E55*F55 -> 0 | I55: =I54+H55-G55 -> 90915 | J55: =IF(I55=0,"NIL",IF(I55>0,"CR","DR")) -> CR
A56: 45732 | B56: PAYMENT | D56: Eksa T8 | G56: 1600 | H56: =E56*F56 -> 0 | I56: =I55+H56-G56 -> 89315 | J56: =IF(I56=0,"NIL",IF(I56>0,"CR","DR")) -> CR
A57: 45732 | B57: PAYMENT | D57: Gamdias Eros M3 Elite | E57: 1 | G57: 2600 | H57: =E57*F57 -> 0 | I57: =I56+H57-G57 -> 86715 | J57: =IF(I57=0,"NIL",IF(I57>0,"CR","DR")) -> CR
A58: 45732 | B58: PAYMENT | D58: Zidli L5 Usb 2500 each | E58: 2 | G58: 5000 | H58: =E58*F58 -> 0 | I58: =I57+H58-G58 -> 81715 | J58: =IF(I58=0,"NIL",IF(I58>0,"CR","DR")) -> CR
A59: 45732 | B59: PAYMENT | D59: Audeeo Velocity Wired Gaming Mouse | E59: 1 | G59: 1180 | H59: =E59*F59 -> 0 | I59: =I58+H59-G59 -> 80535 | J59: =IF(I59=0,"NIL",IF(I59>0,"CR","DR")) -> CR
A60: 45804 | B60: PAYMENT | D60: Marvo K607 | E60: 1 | G60: 1650 | H60: =E60*F60 -> 0 | I60: =I59+H60-G60 -> 78885 | J60: =IF(I60=0,"NIL",IF(I60>0,"CR","DR")) -> CR
A61: 45804 | B61: PAYMENT | D61: Hp Gk400 Ey Mechanical Keyboard | E61: 1 | G61: 3800 | H61: =E61*F61 -> 0 | I61: =I60+H61-G61 -> 75085 | J61: =IF(I61=0,"NIL",IF(I61>0,"CR","DR")) -> CR
A62: 45804 | B62: PAYMENT | D62: mouse pad booldy | E62: 1 | G62: 1550 | H62: =E62*F62 -> 0 | I62: =I61+H62-G62 -> 73535 | J62: =IF(I62=0,"NIL",IF(I62>0,"CR","DR")) -> CR
A63: 45848 | B63: PAYMENT | D63: Gtx 350 MouseKeyboard Combo | E63: 1 | G63: 1580 | H63: =E63*F63 -> 0 | I63: =I62+H63-G63 -> 71955 | J63: =IF(I63=0,"NIL",IF(I63>0,"CR","DR")) -> CR
D64: Jedel K500+ | E64: 1 | G64: 1580 | H64: =E64*F64 -> 0 | I64: =I63+H64-G64 -> 70375 | J64: =IF(I64=0,"NIL",IF(I64>0,"CR","DR")) -> CR
D65: Marvo K607 | E65: 1 | G65: 1650 | H65: =E65*F65 -> 0 | I65: =I64+H65-G65 -> 68725 | J65: =IF(I65=0,"NIL",IF(I65>0,"CR","DR")) -> CR
D66: banda km 99 mouse keyboad combo | E66: 1 | G66: 1580 | H66: =E66*F66 -> 0 | I66: =I65+H66-G66 -> 67145 | J66: =IF(I66=0,"NIL",IF(I66>0,"CR","DR")) -> CR
D67: Hp Gk400 Ey Mechanical Keyboard | E67: 1 | G67: 3800 | H67: =E67*F67 -> 0 | I67: =I66+H67-G67 -> 63345 | J67: =IF(I67=0,"NIL",IF(I67>0,"CR","DR")) -> CR
D68: zidi zm k60 keyboard mouse | E68: 1 | G68: 2180 | H68: =E68*F68 -> 0 | I68: =I67+H68-G68 -> 61165 | J68: =IF(I68=0,"NIL",IF(I68>0,"CR","DR")) -> CR
D69: k-11 tki keyboard | E69: 1 | G69: 1450 | H69: =E69*F69 -> 0 | I69: =I68+H69-G69 -> 59715 | J69: =IF(I69=0,"NIL",IF(I69>0,"CR","DR")) -> CR
D70: Pioneer Xg 73 | E70: 2 | G70: 730 | H70: =E70*F70 -> 0 | I70: =I69+H70-G70 -> 58985 | J70: =IF(I70=0,"NIL",IF(I70>0,"CR","DR")) -> CR
D71: headphone stands | E71: 2 | G71: =580*E71 -> 1160 | H71: =E71*F71 -> 0 | I71: =I70+H71-G71 -> 57825 | J71: =IF(I71=0,"NIL",IF(I71>0,"CR","DR")) -> CR
H72: =E72*F72 -> 0 | I72: =I71+H72-G72 -> 57825 | J72: =IF(I72=0,"NIL",IF(I72>0,"CR","DR")) -> CR
H73: =E73*F73 -> 0 | I73: =I72+H73-G73 -> 57825 | J73: =IF(I73=0,"NIL",IF(I73>0,"CR","DR")) -> CR
H74: =E74*F74 -> 0 | I74: =I73+H74-G74 -> 57825 | J74: =IF(I74=0,"NIL",IF(I74>0,"CR","DR")) -> CR
H75: =E75*F75 -> 0 | I75: =I74+H75-G75 -> 57825 | J75: =IF(I75=0,"NIL",IF(I75>0,"CR","DR")) -> CR
H76: =E76*F76 -> 0 | I76: =I75+H76-G76 -> 57825 | J76: =IF(I76=0,"NIL",IF(I76>0,"CR","DR")) -> CR
H77: =E77*F77 -> 0 | I77: =I76+H77-G77 -> 57825 | J77: =IF(I77=0,"NIL",IF(I77>0,"CR","DR")) -> CR
H78: =E78*F78 -> 0 | I78: =I77+H78-G78 -> 57825 | J78: =IF(I78=0,"NIL",IF(I78>0,"CR","DR")) -> CR
H79: =E79*F79 -> 0 | I79: =I78+H79-G79 -> 57825 | J79: =IF(I79=0,"NIL",IF(I79>0,"CR","DR")) -> CR
H80: =E80*F80 -> 0 | I80: =I79+H80-G80 -> 57825 | J80: =IF(I80=0,"NIL",IF(I80>0,"CR","DR")) -> CR
H81: =E81*F81 -> 0 | I81: =I80+H81-G81 -> 57825 | J81: =IF(I81=0,"NIL",IF(I81>0,"CR","DR")) -> CR
H82: =E82*F82 -> 0 | I82: =I81+H82-G82 -> 57825 | J82: =IF(I82=0,"NIL",IF(I82>0,"CR","DR")) -> CR
H83: =E83*F83 -> 0 | I83: =I82+H83-G83 -> 57825 | J83: =IF(I83=0,"NIL",IF(I83>0,"CR","DR")) -> CR
... H104: =E104*F104 -> 0 | I104: =I103+H104-G104 -> 57825 | J104: =IF(I104=0,"NIL",IF(I104>0,"CR","DR")) -> CR
D105: TOTAL BALANCE | G105: =SUM(G75:G104) -> 0 | H105: =SUM(H75:H104) -> 0 | I105: =I74+H105-G105 -> 57825 | J105: =IF(I105=0,"NIL",IF(I105>0,"CR","DR")) -> CR
